Workbook

Sheet 利润试算表
A1: f | B1: 142 | I1: 填写格 | K1: 不要修改 | M1: 信封大 | N1: 34x24x2
I2: 计算格 | K2: 实际测量体积 | M2: 信封中 | N2: 28.5x20x2
A3: EC site URL | B3: eBayURL | C3: ItemID（SKU) | D3: 刊登 | E3: 优化 | F3: 视频 | G3: UPC | H3: 广告费 | I3: 价格折扣 | J3: 采购价格 （日） | K3: JP重量 (g) | L3: 长 （cm） | M3: 高 （cm) | N3: 高 （cm) | O3: OC重量 （g) | P3: 销售价格 USD | Q3: 物流费用 US外 | R3: 物流定价 US | S3: 增加成本 US | T3: 总价 US | U3: SP运费 | V3: 关税及 手续费 | W3: eBay 佣金 | X3: 海外 手数料 | Y3: 利润 （US外） | Z3: 利润率 （US外） | AA3: ROI （US外） | AB3: 利润 （US） | AC3: 利润率 （US） | AD3: ROI （US） | AE3: eBay费用 （US外） | AF3: eBay费用 （US） | AG3: 备注
A4: 例子 | B4: 例子 | C4: 01-2507-0003 | G4: 这一行不要改 | H4: 0.05 | I4: 0 | J4: 2000 | K4: 210 | L4: 34 | M4: 24 | N4: 2 | O4: =max(L4*M4*N4/8000*1000,K4) -> 210 | P4: 36.43 | Q4: {=XLOOKUP(K4/1000, '运费（邮政）'!$A$2:$A$21, '运费（邮政）'!$B$2:$B$21, "超出范围", 1)} -> 1240 | R4: 12 | S4: =(V4+U4-Q4)/$B$1 -> 7.7054185 | T4: =P4+R4 -> 48.43 | U4: {=XLOOKUP(O4/1000, '运费（橙联）'!$A$2:$A$57, '运费（橙联）'!$B$2:$B$57, "超出范围", 1)} -> 1581 | V4: =(P4*'参数表'!$C$2*(1+'参数表'!$C$3))*$B$1+'参数表'!$C$4 -> 753.16943 | W4: 0.127 | X4: 0.0135 | Y4: =(P4*(1-I4)-AE4)*$B$1-J4-Q4 -> 678.1638 | Z4: =Y4/P4/$B$1 -> 0.13109529 | AA4: =Y4/J4 -> 0.3390819 | AB4: =(P4*(1-I4)+R4-AF4)*$B$1-J4-U4-V4 -> 930.92118 | AC4: =AB4/T4/$B$1 -> 0.13536616 | AD4: =AB4/J4 -> 0.46546059 | AE4: =P4*(1-I4)*(1+'参数表'!$C$6)*(W4+X4+H4)*1.1+0.4*1.1 -> 8.8372971 | AF4: =(P4*(1-I4)*1.1+R4)*(W4+X4+H4)*1.1+0.4*1.1 -> 11.351897
A5: https://www.amazon.co.jp/PILOT-%E3%83%9C%E3%83%BC%E3%83%AB%E3%83%9A%E3%83%B3-%E3%82%B8%E3%83%A5%E3%83%BC%E3%82%B9%E3%83%97%E3%83%A9%E3%82%B93%E8%89%B2%E3%82%BB%E3%83%83%E3%83%88-0-4mm-LJL143CA/dp/B0FW4M3LH7/ref=sr_1_9?crid=3NWFUPINP4YPW&dib=eyJ2IjoiMSJ9.VoEIf6XsPD72Nnsq7obLDQNFAPoKxm4HuckZ4JaCj4hrQ3AllLYOmNO1gDAC2gMX5ZSuyQGaPOAEsyfzCt7MTBgedsxRSQVj7F3bURQv7g8c8tQHHxUEbSjdHLeeQigHKetmvJk2KpWQOIjCG6s_t95rlO1w2uJI646uZHkCZyA0ojXqT4QFQXnnkpBXb1Zg73If2Hnmp9r_WE1N6s5gW-Xg2Z3XR1AsDwDro3TVsGGcwJo2CPfkyGQFpSSC0EZajSj7FF7jPxheONdsqC3JxExu9U5fga9QDSNFv2NtbVY.nzwlsZPC1vN2AGRLcmx8r_1CD4JyD5CVIorNudhCbdY&dib_tag=se&keywords=pilot%2Bjuice%2B&qid=1768525949&sprefix=pilot%2Bjuice%2B%2Caps%2C293&sr=8-9&th=1 | C5: 01-2601-0074 | D5: 没货 | F5: 可直接上3个的套装 | H5: 0.05 | I5: 0 | L5: 34 | M5: 24 | N5: 2 | O5: =max(L5*M5*N5/8000*1000,K5) -> 204 | Q5: {=XLOOKUP(K5/1000, '运费（邮政）'!$A$2:$A$21, '运费（邮政）'!$B$2:$B$21, "超出范围", 1)} -> 880 | S5: =(V5+U5-Q5)/$B$1 -> 6.5211268 | T5: =P5+R5 -> 0 | U5: {=XLOOKUP(O5/1000, '运费（橙联）'!$A$2:$A$57, '运费（橙联）'!$B$2:$B$57, "超出范围", 1)} -> 1581 | V5: =(P5*'参数表'!$C$2*(1+'参数表'!$C$3))*$B$1+'参数表'!$C$4 -> 225 | W5: 0.127 | X5: 0.0135 | Y5: =(P5*(1-I5)-AE5)*$B$1-J5-Q5 -> -942.48 | Z5: =Y5/P5/$B$1 -> #DIV/0! | AA5: =Y5/J5 -> #DIV/0! | AB5: =(P5*(1-I5)+R5-AF5)*$B$1-J5-U5-V5 -> -1868.48 | AC5: =AB5/T5/$B$1 -> #DIV/0! | AD5: =AB5/J5 -> #DIV/0! | AE5: =P5*(1-I5)*(1+'参数表'!$C$6)*(W5+X5+H5)*1.1+0.4*1.1 -> 0.44 | AF5: =(P5*(1-I5)*1.1+R5)*(W5+X5+H5)*1.1+0.4*1.1 -> 0.44
A6: https://www.amazon.co.jp/%E3%83%91%E3%82%A4%E3%83%AD%E3%83%83%E3%83%88-4%E8%89%B2%E3%83%9C%E3%83%BC%E3%83%AB%E3%83%9A%E3%83%B3-%E3%83%95%E3%83%AA%E3%82%AF%E3%82%B7%E3%83%A7%E3%83%B3%E3%83%9C%E3%83%BC%E3%83%AB4-LKFB-3SEF-BN-0-5mm/dp/B00IMDNQ3A?ref_=ast_sto_dp&th=1 | C6: 01-2601-0075 | D6: 4色变体 | G6: 4902505472954 | H6: 0.05 | I6: 0 | J6: 3300 | K6: 80 | L6: 34 | M6: 24 | N6: 2 | O6: =max(L6*M6*N6/8000*1000,K6) -> 204 | P6: 47.8 | Q6: {=XLOOKUP(K6/1000, '运费（邮政）'!$A$2:$A$21, '运费（邮政）'!$B$2:$B$21, "超出范围", 1)} -> 880 | R6: 18.99 | S6: =(V6+U6-Q6)/$B$1 -> 11.401507 | T6: =P6+R6 -> 66.79 | U6: {=XLOOKUP(O6/1000, '运费（橙联）'!$A$2:$A$57, '运费（橙联）'!$B$2:$B$57, "超出范围", 1)} -> 1581 | V6: =(P6*'参数表'!$C$2*(1+'参数表'!$C$3))*$B$1+'参数表'!$C$4 -> 918.01396 | W6: 0.127 | X6: 0.0135 | Y6: =(P6*(1-I6)-AE6)*$B$1-J6-Q6 -> 980.54426 | Z6: =Y6/P6/$B$1 -> 0.14446111 | AA6: =Y6/J6 -> 0.29713462 | AB6: =(P6*(1-I6)+R6-AF6)*$B$1-J6-U6-V6 -> 1493.042 | AC6: =AB6/T6/$B$1 -> 0.15742447 | AD6: =AB6/J6 -> 0.45243696 | AE6: =P6*(1-I6)*(1+'参数表'!$C$6)*(W6+X6+H6)*1.1+0.4*1.1 -> 11.458139 | AF6: =(P6*(1-I6)*1.1+R6)*(W6+X6+H6)*1.1+0.4*1.1 -> 15.437494
A7: https://www.amazon.co.jp/%E3%83%A6%E3%83%BC%E3%82%A8%E3%83%A0%E5%B7%A5%E6%A5%AD-403-50-%E3%82%B7%E3%83%AB%E3%82%AD%E3%83%BC-%E3%82%AB%E3%82%BF%E3%83%8A%E3%83%9C%E3%83%BC%E3%82%A4-500mm/dp/B002GKB5PQ/ref=zg_bs_g_2039536051_d_sccl_12/357-9393567-9939435?psc=1 | C7: 01-2601-0076 | D7: 重复 | G7: 7241870617544 | H7: 0.05 | I7: 0 | J7: 10129 | K7: 1880 | L7: 125 | M7: 16.5 | N7: 4.5 | O7: =max(L7*M7*N7/8000*1000,K7) -> 1880 | P7: 158 | Q7: {=XLOOKUP(K7/1000, '运费（邮政）'!$A$2:$A$21, '运费（邮政）'!$B$2:$B$21, "超出范围", 1)} -> 4120 | R7: 34.99 | S7: =(V7+U7-Q7)/$B$1 -> 16.702223 | T7: =P7+R7 -> 192.99 | U7: {=XLOOKUP(O7/1000, '运费（橙联）'!$A$2:$A$57, '运费（橙联）'!$B$2:$B$57, "超出范围", 1)} -> 3976 | V7: =(P7*'参数表'!$C$2*(1+'参数表'!$C$3))*$B$1+'参数表'!$C$4 -> 2515.7156 | W7: 0.127 | X7: 0.0135 | Y7: =(P7*(1-I7)-AE7)*$B$1-J7-Q7 -> 2952.9098 | Z7: =Y7/P7/$B$1 -> 0.13161481 | AA7: =Y7/J7 -> 0.29153024 | AB7: =(P7*(1-I7)+R7-AF7)*$B$1-J7-U7-V7 -> 4508.6083 | AC7: =AB7/T7/$B$1 -> 0.16452025 | AD7: =AB7/J7 -> 0.4451188 | AE7: =P7*(1-I7)*(1+'参数表'!$C$6)*(W7+X7+H7)*1.1+0.4*1.1 -> 36.85979 | AF7: =(P7*(1-I7)*1.1+R7)*(W7+X7+H7)*1.1+0.4*1.1 -> 44.191944
A8: https://www.amazon.co.jp/PILOT-%E3%83%9C%E3%83%BC%E3%83%AB%E3%83%9A%E3%83%B3-%E3%83%95%E3%83%AA%E3%82%AF%E3%82%B7%E3%83%A7%E3%83%B3%E3%83%9C%E3%83%BC%E3%83%AB%E3%83%8E%E3%83%83%E3%82%AF%E3%82%BE%E3%83%BC%E3%83%B3-%E3%82%A4%E3%83%B3%E3%82%B9%E3%83%94%E3%83%AC%E3%83%BC%E3%82%B7%E3%83%A7%E3%83%B3%E3%83%AC%E3%83%83%E3%83%89-LFBKZ3SEFIR/dp/B0BMZT54C5?ref_=ast_sto_dp&th=1 | C8: 01-2601-0078 | G8: 4902505652134 | H8: 0.05 | I8: 0 | J8: 3300 | K8: 80 | L8: 34 | M8: 24 | N8: 2 | O8: =max(L8*M8*N8/8000*1000,K8) -> 204 | P8: 47.8 | Q8: {=XLOOKUP(K8/1000, '运费（邮政）'!$A$2:$A$21, '运费（邮政）'!$B$2:$B$21, "超出范围", 1)} -> 880 | R8: 18.99 | S8: =(V8+U8-Q8)/$B$1 -> 11.401507 | T8: =P8+R8 -> 66.79 | U8: {=XLOOKUP(O8/1000, '运费（橙联）'!$A$2:$A$57, '运费（橙联）'!$B$2:$B$57, "超出范围", 1)} -> 1581 | V8: =(P8*'参数表'!$C$2*(1+'参数表'!$C$3))*$B$1+'参数表'!$C$4 -> 918.01396 | W8: 0.127 | X8: 0.0135 | Y8: =(P8*(1-I8)-AE8)*$B$1-J8-Q8 -> 980.54426 | Z8: =Y8/P8/$B$1 -> 0.14446111 | AA8: =Y8/J8 -> 0.29713462 | AB8: =(P8*(1-I8)+R8-AF8)*$B$1-J8-U8-V8 -> 1493.042 | AC8: =AB8/T8/$B$1 -> 0.15742447 | AD8: =AB8/J8 -> 0.45243696 | AE8: =P8*(1-I8)*(1+'参数表'!$C$6)*(W8+X8+H8)*1.1+0.4*1.1 -> 11.458139 | AF8: =(P8*(1-I8)*1.1+R8)*(W8+X8+H8)*1.1+0.4*1.1 -> 15.437494
A9: https://www.amazon.co.jp/%E3%82%BC%E3%83%96%E3%83%A9-%E3%82%B8%E3%82%A7%E3%83%AB%E3%83%9C%E3%83%BC%E3%83%AB%E3%83%9A%E3%83%B3-%E3%82%B5%E3%83%A9%E3%82%B5%E3%82%AF%E3%83%AA%E3%83%83%E3%83%97-%E3%83%9E%E3%82%A4%E3%83%A1%E3%83%AD%E3%83%87%E3%82%A3%EF%BC%86%E3%82%AF%E3%83%AD%E3%83%9F-JJ15-MMKU-5C/dp/B0F2D4S99Z/ref=sr_1_10?crid=2W1ERF33UNGBZ&dib=eyJ2IjoiMSJ9.xdOQlEeBBWGFNZTSZSp1MHFgv96bUH47qxV9_U74j1A4gie8FjQlRjC6lOGbAPRoY6Mu_pXvFuN20K4E6rIGcDsFo18KNTDfKay5fAsdqtZlDnn9mU44ITQVpyKAZpA-8rZmQ_fOMMqLlyMSobRAg57lQeQjmRX6CyXRpFgu8-UrsZHsNK1ktnSZcDm_e1FQd5Q9nuvip_hQdo84M3IdgJWNrG63S63IYaAYplpKbkktql66tDBbNE__P6Vtfefomej0LYpzsvWPaPGI7KqBSNi_fidsl48U_Our9bp-v-o.RGyKS_UYKkRbuxa6axqsrlRcvU7xaNOJi8s2KNpFcek&dib_tag=se&keywords=zebra&qid=1768526158&sprefix=zebra%2Caps%2C309&sr=8-10 | C9: 01-2601-0079 | D9: 是 | G9: 4901681831463 | H9: 0.05 | I9: 0 | J9: 1106 | K9: 80 | L9: 34 | M9: 24 | N9: 2 | O9: =max(L9*M9*N9/8000*1000,K9) -> 204 | P9: 21.8 | Q9: {=XLOOKUP(K9/1000, '运费（邮政）'!$A$2:$A$21, '运费（邮政）'!$B$2:$B$21, "超出范围", 1)} -> 880 | R9: 12.99 | S9: =(V9+U9-Q9)/$B$1 -> 8.7469068 | T9: =P9+R9 -> 34.79 | U9: {=XLOOKUP(O9/1000, '运费（橙联）'!$A$2:$A$57, '运费（橙联）'!$B$2:$B$57, "超出范围", 1)} -> 1581 | V9: =(P9*'参数表'!$C$2*(1+'参数表'!$C$3))*$B$1+'参数表'!$C$4 -> 541.06076 | W9: 0.127 | X9: 0.0135 | Y9: =(P9*(1-I9)-AE9)*$B$1-J9-Q9 -> 333.56872 | Z9: =Y9/P9/$B$1 -> 0.10775576 | AA9: =Y9/J9 -> 0.30159921 | AB9: =(P9*(1-I9)+R9-AF9)*$B$1-J9-U9-V9 -> 549.55622 | AC9: =AB9/T9/$B$1 -> 0.11124215 | AD9: =AB9/J9 -> 0.49688628 | AE9: =P9*(1-I9)*(1+'参数表'!$C$6)*(W9+X9+H9)*1.1+0.4*1.1 -> 5.465009 | AF9: =(P9*(1-I9)*1.1+R9)*(W9+X9+H9)*1.1+0.4*1.1 -> 8.1870635
A10: https://www.amazon.co.jp/dp/B0FKTCF191/ref=sspa_dk_detail_1?pd_rd_i=B0FKTCF191&pd_rd_w=8EnnM&content-id=amzn1.sym.f293be60-50b7-49bc-95e8-931faf86ed1e&pf_rd_p=f293be60-50b7-49bc-95e8-931faf86ed1e&pf_rd_r=WEZ55RMBKF000HZ0BPD8&pd_rd_wg=JkCxH&pd_rd_r=b041411b-b595-4ba2-9092-601825c9e6ca&sp_csd=d2lkZ2V0TmFtZT1zcF9kZXRhaWw&th=1 | C10: 01-2601-0080 | D10: 3色变体 | G10: 4550624770859 | H10: 0.05 | I10: 0 | J10: 1210 | K10: 80 | L10: 34 | M10: 24 | N10: 2 | O10: =max(L10*M10*N10/8000*1000,K10) -> 204 | P10: 23.8 | Q10: {=XLOOKUP(K10/1000, '运费（邮政）'!$A$2:$A$21, '运费（邮政）'!$B$2:$B$21, "超出范围", 1)} -> 880 | R10: 12.99 | S10: =(V10+U10-Q10)/$B$1 -> 8.9511068 | T10: =P10+R10 -> 36.79 | U10: {=XLOOKUP(O10/1000, '运费（橙联）'!$A$2:$A$57, '运费（橙联）'!$B$2:$B$57, "超出范围", 1)} -> 1581 | V10: =(P10*'参数表'!$C$2*(1+'参数表'!$C$3))*$B$1+'参数表'!$C$4 -> 570.05716 | W10: 0.127 | X10: 0.0135 | Y10: =(P10*(1-I10)-AE10)*$B$1-J10-Q10 -> 448.1053 | Z10: =Y10/P10/$B$1 -> 0.13259122 | AA10: =Y10/J10 -> 0.37033496 | AB10: =(P10*(1-I10)+R10-AF10)*$B$1-J10-U10-V10 -> 635.0964 | AC10: =AB10/T10/$B$1 -> 0.12156863 | AD10: =AB10/J10 -> 0.52487306 | AE10: =P10*(1-I10)*(1+'参数表'!$C$6)*(W10+X10+H10)*1.1+0.4*1.1 -> 5.926019 | AF10: =(P10*(1-I10)*1.1+R10)*(W10+X10+H10)*1.1+0.4*1.1 -> 8.6480735
A11: https://www.amazon.co.jp/dp/B0FKTF2XVZ/ref=sspa_dk_detail_2?pf_rd_p=f293be60-50b7-49bc-95e8-931faf86ed1e&pf_rd_r=WEZ55RMBKF000HZ0BPD8&pd_rd_wg=JkCxH&pd_rd_w=8EnnM&content-id=amzn1.sym.f293be60-50b7-49bc-95e8-931faf86ed1e&pd_rd_r=b041411b-b595-4ba2-9092-601825c9e6ca&sp_csd=d2lkZ2V0TmFtZT1zcF9kZXRhaWw&th=1 | C11: 01-2601-0081 | D11: 同上 | H11: 0.05 | I11: 0 | L11: 34 | M11: 24 | N11: 2 | O11: =max(L11*M11*N11/8000*1000,K11) -> 204 | Q11: {=XLOOKUP(K11/1000, '运费（邮政）'!$A$2:$A$21, '运费（邮政）'!$B$2:$B$21, "超出范围", 1)} -> 880 | S11: =(V11+U11-Q11)/$B$1 -> 6.5211268 | T11: =P11+R11 -> 0 | U11: {=XLOOKUP(O11/1000, '运费（橙联）'!$A$2:$A$57, '运费（橙联）'!$B$2:$B$57, "超出范围", 1)} -> 1581 | V11: =(P11*'参数表'!$C$2*(1+'参数表'!$C$3))*$B$1+'参数表'!$C$4 -> 225 | W11: 0.127 | X11: 0.0135 | Y11: =(P11*(1-I11)-AE11)*$B$1-J11-Q11 -> -942.48 | Z11: =Y11/P11/$B$1 -> #DIV/0! | AA11: =Y11/J11 -> #DIV/0! | AB11: =(P11*(1-I11)+R11-AF11)*$B$1-J11-U11-V11 -> -1868.48 | AC11: =AB11/T11/$B$1 -> #DIV/0! | AD11: =AB11/J11 -> #DIV/0! | AE11: =P11*(1-I11)*(1+'参数表'!$C$6)*(W11+X11+H11)*1.1+0.4*1.1 -> 0.44 | AF11: =(P11*(1-I11)*1.1+R11)*(W11+X11+H11)*1.1+0.4*1.1 -> 0.44
A12: https://www.amazon.co.jp/%E3%82%BC%E3%83%96%E3%83%A9-%E3%82%B8%E3%82%A7%E3%83%AB%E3%83%9C%E3%83%BC%E3%83%AB%E3%83%9A%E3%83%B3-%E3%82%B5%E3%83%A9%E3%82%B5%E3%82%AF%E3%83%AA%E3%83%83%E3%83%97-0-5mm-JJ29-KF-5C/dp/B0DYJQ5GLH/ref=pd_ci_mcx_pspc_dp_d_2_t_3?pd_rd_w=9PcBC&content-id=amzn1.sym.8f1fe2a7-d128-4328-bcac-c2e341dfd86d%3Aamzn1.symc.8c21723d-cd1d-422f-9cc5-7a61ace3c767&pf_rd_p=8f1fe2a7-d128-4328-bcac-c2e341dfd86d&pf_rd_r=WEZ55RMBKF000HZ0BPD8&pd_rd_wg=JkCxH&pd_rd_r=b041411b-b595-4ba2-9092-601825c9e6ca&pd_rd_i=B0DYJQ5GLH | C12: 01-2601-0082 | D12: 是 | G12: 4901681818464 | H12: 0.05 | I12: 0 | J12: 900 | K12: 110 | L12: 34 | M12: 24 | N12: 2 | O12: =max(L12*M12*N12/8000*1000,K12) -> 204 | P12: 21.8 | Q12: {=XLOOKUP(K12/1000, '运费（邮政）'!$A$2:$A$21, '运费（邮政）'!$B$2:$B$21, "超出范围", 1)} -> 1060 | R12: 12.99 | S12: =(V12+U12-Q12)/$B$1 -> 7.4793011 | T12: =P12+R12 -> 34.79 | U12: {=XLOOKUP(O12/1000, '运费（橙联）'!$A$2:$A$57, '运费（橙联）'!$B$2:$B$57, "超出范围", 1)} -> 1581 | V12: =(P12*'参数表'!$C$2*(1+'参数表'!$C$3))*$B$1+'参数表'!$C$4 -> 541.06076 | W12: 0.127 | X12: 0.0135 | Y12: =(P12*(1-I12)-AE12)*$B$1-J12-Q12 -> 359.56872 | Z12: =Y12/P12/$B$1 -> 0.11615478 | AA12: =Y12/J12 -> 0.3995208 | AB12: =(P12*(1-I12)+R12-AF12)*$B$1-J12-U12-V12 -> 755.55622 | AC12: =AB12/T12/$B$1 -> 0.15294103 | AD12: =AB12/J12 -> 0.83950691 | AE12: =P12*(1-I12)*(1+'参数表'!$C$6)*(W12+X12+H12)*1.1+0.4*1.1 -> 5.465009 | AF12: =(P12*(1-I12)*1.1+R12)*(W12+X12+H12)*1.1+0.4*1.1 -> 8.1870635
A13: https://www.amazon.co.jp/%E3%82%BC%E3%83%96%E3%83%A9-%E3%82%B8%E3%82%A7%E3%83%AB%E3%83%9C%E3%83%BC%E3%83%AB%E3%83%9A%E3%83%B3-%E3%82%B5%E3%83%A9%E3%82%B5%E3%82%AF%E3%83%AA%E3%83%83%E3%83%97-%E3%83%8F%E3%83%AA%E3%83%BC%E3%83%BB%E3%83%9D%E3%83%83%E3%82%BF%E3%83%BC-JJ29-HP-4C/dp/B0FXKX12T6/ref=sr_1_5?crid=20024SRCOS2XV&dib=eyJ2IjoiMSJ9.rWLJSoZyhQrM-SeYB-jDgjwm4IMaMb9JiD8j8KQqQ675-XZbLOQLgO0o4rdO4tMaLSVuBNapfEy287eo6kgFc5GW-KwW_VOaDp3yOKVCUh2NnX1h7JtFx8R0bko_R4-eJuhCtQlcEfHldI8rhupFDIKKlnKTt2SCMZ6fkRfc2J1b_QCp2ilFB9aLMgq4--WqOXedeFFaJovdbF6A4n9nYyK7nPlkwaASrrqgH5J3F1TgfHf7YKQha5e9RUIrI-EP0jusGloMopxf910-z4BwYrUPx9i2SNyMPpYy3u2mv18.THAjTe9AVJhGKLZMZNnHyH-dl-LFpajgvif0flGeLQY&dib_tag=se&keywords=zebra+harry+potter&qid=1768526776&sprefix=zebra+ha%2Caps%2C243&sr=8-5 | C13: 01-2601-0083 | D13: 是 | G13: 4901681886388 | H13: 0.05 | I13: 0 | J13: 1350 | K13: 80 | L13: 34 | M13: 24 | N13: 2 | O13: =max(L13*M13*N13/8000*1000,K13) -> 204 | P13: 24.2 | Q13: {=XLOOKUP(K13/1000, '运费（邮政）'!$A$2:$A$21, '运费（邮政）'!$B$2:$B$21, "超出范围", 1)} -> 880 | R13: 12.99 | S13: =(V13+U13-Q13)/$B$1 -> 8.9919468 | T13: =P13+R13 -> 37.19 | U13: {=XLOOKUP(O13/1000, '运费（橙联）'!$A$2:$A$57, '运费（橙联）'!$B$2:$B$57, "超出范围", 1)} -> 1581 | V13: =(P13*'参数表'!$C$2*(1+'参数表'!$C$3))*$B$1+'参数表'!$C$4 -> 575.85644 | W13: 0.127 | X13: 0.0135 | Y13: =(P13*(1-I13)-AE13)*$B$1-J13-Q13 -> 351.81262 | Z13: =Y13/P13/$B$1 -> 0.10237825 | AA13: =Y13/J13 -> 0.26060194 | AB13: =(P13*(1-I13)+R13-AF13)*$B$1-J13-U13-V13 -> 533.00444 | AC13: =AB13/T13/$B$1 -> 0.10092908 | AD13: =AB13/J13 -> 0.3948181 | AE13: =P13*(1-I13)*(1+'参数表'!$C$6)*(W13+X13+H13)*1.1+0.4*1.1 -> 6.018221 | AF13: =(P13*(1-I13)*1.1+R13)*(W13+X13+H13)*1.1+0.4*1.1 -> 8.7402755
A14: https://www.amazon.co.jp/Piececool-%E7%AB%8B%E4%BD%93%E3%83%91%E3%82%BA%E3%83%AB-%E3%83%A1%E3%82%BF%E3%83%AA%E3%83%83%E3%82%AF%E3%83%8A%E3%83%8E%E3%83%91%E3%82%BA%E3%83%AB-%E3%83%95%E3%83%A9%E3%82%A4%E3%83%B3%E3%82%B0%E3%83%BB%E3%83%80%E3%83%83%E3%83%81%E3%83%9E%E3%83%B3-%E3%82%A2%E3%83%83%E3%83%97%E3%82%B0%E3%83%AC%E3%83%BC%E3%83%89%E7%89%88/dp/B09YT1YSKB/ref=sr_1_59?crid=17D3QITS52M7D&dib=eyJ2IjoiMSJ9.olFbl_N22_DSrBlzMUCjMq1ClVmhyqD1jMvs2qKqIebSN2N1uWOJ0dXNw42MNMYKofI-SfhEypjObxqVlvTzAcnnqodHunxfilePYLilXjrib31J56p_uXdQiMPY8vF6LAiGScN24REfB2-wdseiwkqKDmgdmsNlFPWsNV5Lwi7i8SXzbNM5wuo0StZLfL_396hBzKKwd8y_9VOq3yH5r37o_DxYoss5bt67epn-RnRD2INeKYl3P6RUkAGSFQBOKBLA_-wjtmb3BUE4599h9RJJBta-RY065r2I4cDmfL4.VyZo6BC8MPrp8P3xIqarBkd3QU84UKDT4w1mCiNXlPw&dib_tag=se&keywords=rokr&qid=1768526854&sprefix=rokr%2Caps%2C329&sr=8-59&th=1 | C14: 01-2601-0084 | H14: 0.05 | I14: 0 | J14: 4980 | K14: 410 | L14: 34 | M14: 24 | N14: 2 | O14: =max(L14*M14*N14/8000*1000,K14) -> 410 | P14: 74.8 | Q14: {=XLOOKUP(K14/1000, '运费（邮政）'!$A$2:$A$21, '运费（邮政）'!$B$2:$B$21, "超出范围", 1)} -> 1600 | R14: 21.99 | S14: =(V14+U14-Q14)/$B$1 -> 12.461024 | T14: =P14+R14 -> 96.79 | U14: {=XLOOKUP(O14/1000, '运费（橙联）'!$A$2:$A$57, '运费（橙联）'!$B$2:$B$57, "超出范围", 1)} -> 2060 | V14: =(P14*'参数表'!$C$2*(1+'参数表'!$C$3))*$B$1+'参数表'!$C$4 -> 1309.4654 | W14: 0.127 | X14: 0.0135 | Y14: =(P14*(1-I14)-AE14)*$B$1-J14-Q14 -> 1530.7881 | Z14: =Y14/P14/$B$1 -> 0.14412029 | AA14: =Y14/J14 -> 0.30738717 | AB14: =(P14*(1-I14)+R14-AF14)*$B$1-J14-U14-V14 -> 2229.5661 | AC14: =AB14/T14/$B$1 -> 0.16221892 | AD14: =AB14/J14 -> 0.44770403 | AE14: =P14*(1-I14)*(1+'参数表'!$C$6)*(W14+X14+H14)*1.1+0.4*1.1 -> 17.681774 | AF14: =(P14*(1-I14)*1.1+R14)*(W14+X14+H14)*1.1+0.4*1.1 -> 22.289779
A15: https://www.amazon.co.jp/LQHZC%E2%80%8B-%E6%8A%98%E7%95%B3%E3%81%AE%E3%81%93%E3%81%8E%E3%82%8A-%E9%BB%92%E3%83%81%E3%82%BF%E3%83%B3%E3%82%B3%E3%83%BC%E3%83%86%E3%82%A3%E3%83%B3%E3%82%B0-%E5%AE%89%E5%85%A8%E3%83%AD%E3%83%83%E3%82%AF%E4%BB%98%E3%81%8D-%E6%BB%91%E3%82%8A%E6%AD%A2%E3%82%81%E3%82%B0%E3%83%AA%E3%83%83%E3%83%97/dp/B0FP5K8HJB/ref=zg_bs_g_2039536051_d_sccl_14/357-9393567-9939435?th=1 | C15: 01-2601-0085 | D15: 是 | G15: 0769016152157 | H15: 0.05 | I15: 0 | J15: 1399 | K15: 310 | L15: 34 | M15: 24 | N15: 2 | O15: =max(L15*M15*N15/8000*1000,K15) -> 310 | P15: 29.8 | Q15: {=XLOOKUP(K15/1000, '运费（邮政）'!$A$2:$A$21, '运费（邮政）'!$B$2:$B$21, "超出范围", 1)} -> 1420 | R15: 12.99 | S15: =(V15+U15-Q15)/$B$1 -> 7.1482138 | T15: =P15+R15 -> 42.79 | U15: {=XLOOKUP(O15/1000, '运费（橙联）'!$A$2:$A$57, '运费（橙联）'!$B$2:$B$57, "超出范围", 1)} -> 1778 | V15: =(P15*'参数表'!$C$2*(1+'参数表'!$C$3))*$B$1+'参数表'!$C$4 -> 657.04636 | W15: 0.127 | X15: 0.0135 | Y15: =(P15*(1-I15)-AE15)*$B$1-J15-Q15 -> 374.71504 | Z15: =Y15/P15/$B$1 -> 0.088551622 | AA15: =Y15/J15 -> 0.26784492 | AB15: =(P15*(1-I15)+R15-AF15)*$B$1-J15-U15-V15 -> 817.71694 | AC15: =AB15/T15/$B$1 -> 0.13457747 | AD15: =AB15/J15 -> 0.58450103 | AE15: =P15*(1-I15)*(1+'参数表'!$C$6)*(W15+X15+H15)*1.1+0.4*1.1 -> 7.309049 | AF15: =(P15*(1-I15)*1.1+R15)*(W15+X15+H15)*1.1+0.4*1.1 -> 10.031104
A16: https://www.amazon.co.jp/%E3%83%8F%E3%83%8A%E3%83%A4%E3%83%9E-%E3%81%AF%E3%81%9A%E3%82%8B-%E3%82%BC%E3%83%AB%E3%83%80%E3%81%AE%E4%BC%9D%E8%AA%AC-%E3%83%9E%E3%82%B9%E3%82%BF%E3%83%BC%E3%82%BD%E3%83%BC%E3%83%89-075695/dp/B0BVXXJ38P/ref=zg_bs_g_2189598051_d_sccl_7/355-3582507-3163057?th=1 | C16: 01-2601-0086 | D16: 是 | G16: 4977513075695 | H16: 0.05 | I16: 0 | J16: 3300 | K16: 210 | L16: 34 | M16: 24 | N16: 2 | O16: =max(L16*M16*N16/8000*1000,K16) -> 210 | P16: 49.8 | Q16: {=XLOOKUP(K16/1000, '运费（邮政）'!$A$2:$A$21, '运费（邮政）'!$B$2:$B$21, "超出范围", 1)} -> 1240 | R16: 15.99 | S16: =(V16+U16-Q16)/$B$1 -> 9.0704955 | T16: =P16+R16 -> 65.79 | U16: {=XLOOKUP(O16/1000, '运费（橙联）'!$A$2:$A$57, '运费（橙联）'!$B$2:$B$57, "超出范围", 1)} -> 1581 | V16: =(P16*'参数表'!$C$2*(1+'参数表'!$C$3))*$B$1+'参数表'!$C$4 -> 947.01036 | W16: 0.127 | X16: 0.0135 | Y16: =(P16*(1-I16)-AE16)*$B$1-J16-Q16 -> 839.08084 | Z16: =Y16/P16/$B$1 -> 0.11865502 | AA16: =Y16/J16 -> 0.25426692 | AB16: =(P16*(1-I16)+R16-AF16)*$B$1-J16-U16-V16 -> 1345.8504 | AC16: =AB16/T16/$B$1 -> 0.14406171 | AD16: =AB16/J16 -> 0.40783347 | AE16: =P16*(1-I16)*(1+'参数表'!$C$6)*(W16+X16+H16)*1.1+0.4*1.1 -> 11.919149 | AF16: =(P16*(1-I16)*1.1+R16)*(W16+X16+H16)*1.1+0.4*1.1 -> 15.269853
A17: https://www.amazon.co.jp/%E3%83%8F%E3%83%8A%E3%83%A4%E3%83%9E-HANAYAMA-%E3%82%AF%E3%83%AA%E3%82%B9%E3%82%BF%E3%83%AB%E3%82%AE%E3%83%A3%E3%83%A9%E3%83%AA%E3%83%BC-%E3%83%8F%E3%83%AD%E3%83%BC%E3%82%AD%E3%83%86%E3%82%A3/dp/B07FGSQT2J/ref=zg_bs_g_2189598051_d_sccl_16/355-3582507-3163057?th=1 | C17: 01-2601-0087 | D17: 是 | G17: 4977513076289 | H17: 0.05 | I17: 0 | J17: 1309 | K17: 210 | L17: 15 | M17: 5 | N17: 10 | O17: =max(L17*M17*N17/8000*1000,K17) -> 210 | P17: 27.9 | Q17: {=XLOOKUP(K17/1000, '运费（邮政）'!$A$2:$A$21, '运费（邮政）'!$B$2:$B$21, "超出范围", 1)} -> 1240 | R17: 12.99 | S17: =(V17+U17-Q17)/$B$1 -> 6.8345055 | T17: =P17+R17 -> 40.89 | U17: {=XLOOKUP(O17/1000, '运费（橙联）'!$A$2:$A$57, '运费（橙联）'!$B$2:$B$57, "超出范围", 1)} -> 1581 | V17: =(P17*'参数表'!$C$2*(1+'参数表'!$C$3))*$B$1+'参数表'!$C$4 -> 629.49978 | W17: 0.127 | X17: 0.0135 | Y17: =(P17*(1-I17)-AE17)*$B$1-J17-Q17 -> 437.10529 | Z17: =Y17/P17/$B$1 -> 0.11032997 | AA17: =Y17/J17 -> 0.33392306 | AB17: =(P17*(1-I17)+R17-AF17)*$B$1-J17-U17-V17 -> 924.65377 | AC17: =AB17/T17/$B$1 -> 0.15924789 | AD17: =AB17/J17 -> 0.7063818 | AE17: =P17*(1-I17)*(1+'参数表'!$C$6)*(W17+X17+H17)*1.1+0.4*1.1 -> 6.8710895 | AF17: =(P17*(1-I17)*1.1+R17)*(W17+X17+H17)*1.1+0.4*1.1 -> 9.593144
A18: https://www.amazon.co.jp/FUNPOLA-%E3%83%99%E3%83%8D%E3%83%81%E3%82%A2%E3%81%AE%E6%98%9F-Booknook-LED%E3%83%A9%E3%82%A4%E3%83%88%E4%BB%98%E3%81%8D-%E5%88%9D%E5%BF%83%E8%80%85%E3%82%84%E4%B8%AD%E5%AD%A6%E7%94%9F%E5%90%91%E3%81%91/dp/B0FZ2QTRH1/ref=zg_bs_g_2189598051_d_sccl_33/355-3582507-3163057?th=1 | C18: 01-2601-0088 | D18: 4变体 | H18: 0.05 | I18: 0 | J18: 7980 | K18: 1210 | L18: 26 | M18: 16 | N18: 0.1 | O18: =max(L18*M18*N18/8000*1000,K18) -> 1210 | P18: 129 | Q18: {=XLOOKUP(K18/1000, '运费（邮政）'!$A$2:$A$21, '运费（邮政）'!$B$2:$B$21, "超出范围", 1)} -> 3040 | R18: 29.99 | S18: =(V18+U18-Q18)/$B$1 -> 17.051182 | T18: =P18+R18 -> 158.99 | U18: {=XLOOKUP(O18/1000, '运费（橙联）'!$A$2:$A$57, '运费（橙联）'!$B$2:$B$57, "超出范围", 1)} -> 3366 | V18: =(P18*'参数表'!$C$2*(1+'参数表'!$C$3))*$B$1+'参数表'!$C$4 -> 2095.2678 | W18: 0.127 | X18: 0.0135 | Y18: =(P18*(1-I18)-AE18)*$B$1-J18-Q18 -> 3013.1294 | Z18: =Y18/P18/$B$1 -> 0.16449009 | AA18: =Y18/J18 -> 0.37758514 | AB18: =(P18*(1-I18)+R18-AF18)*$B$1-J18-U18-V18 -> 3958.0562 | AC18: =AB18/T18/$B$1 -> 0.17531691 | AD18: =AB18/J18 -> 0.49599701 | AE18: =P18*(1-I18)*(1+'参数表'!$C$6)*(W18+X18+H18)*1.1+0.4*1.1 -> 30.175145 | AF18: =(P18*(1-I18)*1.1+R18)*(W18+X18+H18)*1.1+0.4*1.1 -> 36.45955
A19: https://www.amazon.co.jp/dp/B0G6MF8H65?tag=webspire_new-22&linkCode=osi&th=1&psc=1 | C19: 01-2601-0089 | D19: 0101重复 | H19: 0.05 | I19: 0 | L19: 34 | M19: 24 | N19: 2 | O19: =max(L19*M19*N19/8000*1000,K19) -> 204 | Q19: {=XLOOKUP(K19/1000, '运费（邮政）'!$A$2:$A$21, '运费（邮政）'!$B$2:$B$21, "超出范围", 1)} -> 880 | S19: =(V19+U19-Q19)/$B$1 -> 6.5211268 | T19: =P19+R19 -> 0 | U19: {=XLOOKUP(O19/1000, '运费（橙联）'!$A$2:$A$57, '运费（橙联）'!$B$2:$B$57, "超出范围", 1)} -> 1581 | V19: =(P19*'参数表'!$C$2*(1+'参数表'!$C$3))*$B$1+'参数表'!$C$4 -> 225 | W19: 0.127 | X19: 0.0135 | Y19: =(P19*(1-I19)-AE19)*$B$1-J19-Q19 -> -942.48 | Z19: =Y19/P19/$B$1 -> #DIV/0! | AA19: =Y19/J19 -> #DIV/0! | AB19: =(P19*(1-I19)+R19-AF19)*$B$1-J19-U19-V19 -> -1868.48 | AC19: =AB19/T19/$B$1 -> #DIV/0! | AD19: =AB19/J19 -> #DIV/0! | AE19: =P19*(1-I19)*(1+'参数表'!$C$6)*(W19+X19+H19)*1.1+0.4*1.1 -> 0.44 | AF19: =(P19*(1-I19)*1.1+R19)*(W19+X19+H19)*1.1+0.4*1.1 -> 0.44
A20: https://www.amazon.co.jp/%E7%9F%B3%E9%8B%B8%E5%B7%A5%E6%A5%AD-%E7%8F%BE%E5%A0%B4%E5%B1%8B-%E3%82%B1%E3%83%BC%E3%82%B9%E4%BB%98%E6%9E%9D%E5%88%87%E9%8B%B8-135mm/dp/B006QH7WI4/ref=zg_bs_g_2039536051_d_sccl_19/357-9393567-9939435?psc=1 | C20: 01-2601-0090 | D20: 是 | G20: 4931025006042 | H20: 0.05 | I20: 0 | J20: 961 | K20: 150 | L20: 34 | M20: 24 | N20: 2 | O20: =max(L20*M20*N20/8000*1000,K20) -> 204 | P20: 21.8 | Q20: {=XLOOKUP(K20/1000, '运费（邮政）'!$A$2:$A$21, '运费（邮政）'!$B$2:$B$21, "超出范围", 1)} -> 1060 | R20: 12.99 | S20: =(V20+U20-Q20)/$B$1 -> 7.4793011 | T20: =P20+R20 -> 34.79 | U20: {=XLOOKUP(O20/1000, '运费（橙联）'!$A$2:$A$57, '运费（橙联）'!$B$2:$B$57, "超出范围", 1)} -> 1581 | V20: =(P20*'参数表'!$C$2*(1+'参数表'!$C$3))*$B$1+'参数表'!$C$4 -> 541.06076 | W20: 0.127 | X20: 0.0135 | Y20: =(P20*(1-I20)-AE20)*$B$1-J20-Q20 -> 298.56872 | Z20: =Y20/P20/$B$1 -> 0.096449387 | AA20: =Y20/J20 -> 0.31068545 | AB20: =(P20*(1-I20)+R20-AF20)*$B$1-J20-U20-V20 -> 694.55622 | AC20: =AB20/T20/$B$1 -> 0.1405933 | AD20: =AB20/J20 -> 0.72274321 | AE20: =P20*(1-I20)*(1+'参数表'!$C$6)*(W20+X20+H20)*1.1+0.4*1.1 -> 5.465009 | AF20: =(P20*(1-I20)*1.1+R20)*(W20+X20+H20)*1.1+0.4*1.1 -> 8.1870635
A21: https://www.amazon.co.jp/%E3%82%B8%E3%82%B0%E3%82%BD%E3%83%BC%E3%83%91%E3%82%BA%E3%83%AB-%E3%82%A2%E3%83%8B%E3%83%A1%E3%80%8C%E9%AC%BC%E6%BB%85%E3%81%AE%E5%88%83%E3%80%8D-vol-1-300%E3%83%94%E3%83%BC%E3%82%B9-300-3186/dp/B0FW4R5PDJ/ref=sr_1_4_sspa?crid=165EDGQ6XKBBE&dib=eyJ2IjoiMSJ9.YiLAjQwn9kFGR8qJjXztVneWwv3vFoPSoZJQY0-BNUxnbvPHxIh4GCoedgDs2HntfZSBIMksl_HVw24kClhiBsg1vn4u01nLnq7oTloP62CAqmTL0it_frAXJ-Ul1aEcy34QXAjDAvRPQjcdgKmCEV9v1vj4NSVdEyHsgbLdoA-5N0S6uzgyiG8amcJ7hP-GFZa3dW3CgTEDFgbm56hQVP_RIRPNQekWnCC76hZaFRzFC5rtm3Jhj_QOYP1gnaoKxQvNFwrmqJ9GRI7oUgMLpzjPyuTWEE3UMHpTY6WVBs8.zVWUgCrcFwEIEQxbUGnEiXlTAmjsDIWCdby-236Jku0&dib_tag=se&keywords=%E9%AC%BC%E7%81%AD%E4%B9%8B%E5%88%83%E6%8B%BC%E5%9B%BE&qid=1768528730&refinements=p_123%3A311243&rnid=23341432051&sprefix=%E9%AC%BC%E7%81%AD%E4%B9%8B%E5%88%83%2Caps%2C234&sr=8-4-spons&sp_csd=d2lkZ2V0TmFtZT1zcF9hdGY&psc=1 | C21: 01-2601-0091 | D21: 是 | G21: 4970381529277 | H21: 0.05 | I21: 0 | J21: 1980 | K21: 210 | L21: 34 | M21: 24 | N21: 2 | O21: =max(L21*M21*N21/8000*1000,K21) -> 210 | P21: 37.9 | Q21: {=XLOOKUP(K21/1000, '运费（邮政）'!$A$2:$A$21, '运费（邮政）'!$B$2:$B$21, "超出范围", 1)} -> 1240 | R21: 12.99 | S21: =(V21+U21-Q21)/$B$1 -> 7.8555055 | T21: =P21+R21 -> 50.89 | U21: {=XLOOKUP(O21/1000, '运费（橙联）'!$A$2:$A$57, '运费（橙联）'!$B$2:$B$57, "超出范围", 1)} -> 1581 | V21: =(P21*'参数表'!$C$2*(1+'参数表'!$C$3))*$B$1+'参数表'!$C$4 -> 774.48178 | W21: 0.127 | X21: 0.0135 | Y21: =(P21*(1-I21)-AE21)*$B$1-J21-Q21 -> 858.78819 | Z21: =Y21/P21/$B$1 -> 0.15957267 | AA21: =Y21/J21 -> 0.43373141 | AB21: =(P21*(1-I21)+R21-AF21)*$B$1-J21-U21-V21 -> 1201.3547 | AC21: =AB21/T21/$B$1 -> 0.16624571 | AD21: =AB21/J21 -> 0.60674478 | AE21: =P21*(1-I21)*(1+'参数表'!$C$6)*(W21+X21+H21)*1.1+0.4*1.1 -> 9.1761395 | AF21: =(P21*(1-I21)*1.1+R21)*(W21+X21+H21)*1.1+0.4*1.1 -> 11.898194
A22: https://www.amazon.co.jp/%E8%91%AC%E9%80%81%E3%81%AE%E3%83%95%E3%83%AA%E3%83%BC%E3%83%AC%E3%83%B3-%E3%82%B9%E3%83%86%E3%83%83%E3%82%AB%E3%83%BC-PVC%E6%9D%90%E8%B3%AA-%E9%98%B2%E6%B0%B4%E3%82%B9%E3%83%86%E3%83%83%E3%82%AB%E3%83%BC-%E3%82%B3%E3%83%AC%E3%82%AF%E3%82%B7%E3%83%A7%E3%83%B3/dp/B0GDXFZ223/ref=sr_1_48?crid=9RQITUICNZMP&dib=eyJ2IjoiMSJ9.gmhCn42Cwma9VBqwd0YM5iLXIiO3XqOibqPDLPfWMqYLHALkJDF1-QLotnmIhz9dsXCdnV-2EGbvw0k-OJDMQ7aJ-x5ir0a7gWebKZwUn8oGQluHNGYBHAdqbfCxGxxmr21VNFlE63JIPaLUykubsRw0xK6E5DDSZn-1lSyPGC1Y18juas1DUNlXdjyhIFqC2Em5zNcrviogEDbzGw6jpqF-VPO2TxbMGY_CxkmOe9PcA_1xXgZY7_zhdJJrjAQilQP07bpkhrn7ZYSiICrWBwP2w4RXNSy24-Wbzbr3MsY.i88_sojIt4lnsnshJH_tXbBiSZ3kCw0bLcphOWllfrs&dib_tag=se&keywords=%E8%91%AC%E9%80%81%E3%81%AE%E3%83%95%E3%83%AA%E3%83%BC%E3%83%AC%E3%83%B3%2B%E6%8B%BC%E5%9B%BE&qid=1768529071&sprefix=%E3%82%B8%E3%82%B0%E3%82%BD%E3%83%BC%E3%83%91%E3%82%BA%E3%83%AB%2B%E8%91%AC%E9%80%81%E3%81%AE%E3%83%95%E3%83%AA%E3%83%BC%E3%83%AC%E3%83%B3%2B%E6%8B%BC%E5%9B%BE%2Caps%2C412&sr=8-48&th=1 | C22: 01-2601-0092 | D22: 是 | G22: 4977389281107 | H22: 0.05 | I22: 0 | J22: 1900 | K22: 380 | L22: 34 | M22: 24 | N22: 2 | O22: =max(L22*M22*N22/8000*1000,K22) -> 380 | P22: 37.8 | Q22: {=XLOOKUP(K22/1000, '运费（邮政）'!$A$2:$A$21, '运费（邮政）'!$B$2:$B$21, "超出范围", 1)} -> 1420 | R22: 12.99 | S22: =(V22+U22-Q22)/$B$1 -> 7.9650138 | T22: =P22+R22 -> 50.79 | U22: {=XLOOKUP(O22/1000, '运费（橙联）'!$A$2:$A$57, '运费（橙联）'!$B$2:$B$57, "超出范围", 1)} -> 1778 | V22: =(P22*'参数表'!$C$2*(1+'参数表'!$C$3))*$B$1+'参数表'!$C$4 -> 773.03196 | W22: 0.127 | X22: 0.0135 | Y22: =(P22*(1-I22)-AE22)*$B$1-J22-Q22 -> 747.86136 | Z22: =Y22/P22/$B$1 -> 0.13932882 | AA22: =Y22/J22 -> 0.39361124 | AB22: =(P22*(1-I22)+R22-AF22)*$B$1-J22-U22-V22 -> 1074.8777 | AC22: =AB22/T22/$B$1 -> 0.14903644 | AD22: =AB22/J22 -> 0.56572509 | AE22: =P22*(1-I22)*(1+'参数表'!$C$6)*(W22+X22+H22)*1.1+0.4*1.1 -> 9.153089 | AF22: =(P22*(1-I22)*1.1+R22)*(W22+X22+H22)*1.1+0.4*1.1 -> 11.875144
A23: https://www.amazon.co.jp/%E8%91%AC%E9%80%81%E3%81%AE%E3%83%95%E3%83%AA%E3%83%BC%E3%83%AC%E3%83%B3-%E3%82%AD%E3%83%A3%E3%83%A9%E3%82%AF%E3%82%BF%E3%83%BC%E3%82%B7%E3%83%BC%E3%83%B3%E3%82%BA-%EF%BC%8850%C3%9775cm%EF%BC%89-12-615s-EPOCH/dp/B0CT2FS17Z/ref=pd_day0_d_sccl_2_2/355-3582507-3163057?pd_rd_w=E5TOr&content-id=amzn1.sym.3e742e38-2b5e-4207-a2c9-5d5409d6c433&pf_rd_p=3e742e38-2b5e-4207-a2c9-5d5409d6c433&pf_rd_r=ACGNXG0AFMGZJFF534WD&pd_rd_wg=BwNVH&pd_rd_r=9bde88e4-1f43-4604-8063-bc6090dcd6b9&pd_rd_i=B0D9PXHPBK&th=1 | C23: 01-2601-0093 | D23: 是 | G23: 4977389281169 | H23: 0.05 | I23: 0 | J23: 1900 | K23: 380 | L23: 34 | M23: 24 | N23: 2 | O23: =max(L23*M23*N23/8000*1000,K23) -> 380 | P23: 37.8 | Q23: {=XLOOKUP(K23/1000, '运费（邮政）'!$A$2:$A$21, '运费（邮政）'!$B$2:$B$21, "超出范围", 1)} -> 1420 | R23: 12.99 | S23: =(V23+U23-Q23)/$B$1 -> 7.9650138 | T23: =P23+R23 -> 50.79 | U23: {=XLOOKUP(O23/1000, '运费（橙联）'!$A$2:$A$57, '运费（橙联）'!$B$2:$B$57, "超出范围", 1)} -> 1778 | V23: =(P23*'参数表'!$C$2*(1+'参数表'!$C$3))*$B$1+'参数表'!$C$4 -> 773.03196 | W23: 0.127 | X23: 0.0135 | Y23: =(P23*(1-I23)-AE23)*$B$1-J23-Q23 -> 747.86136 | Z23: =Y23/P23/$B$1 -> 0.13932882 | AA23: =Y23/J23 -> 0.39361124 | AB23: =(P23*(1-I23)+R23-AF23)*$B$1-J23-U23-V23 -> 1074.8777 | AC23: =AB23/T23/$B$1 -> 0.14903644 | AD23: =AB23/J23 -> 0.56572509 | AE23: =P23*(1-I23)*(1+'参数表'!$C$6)*(W23+X23+H23)*1.1+0.4*1.1 -> 9.153089 | AF23: =(P23*(1-I23)*1.1+R23)*(W23+X23+H23)*1.1+0.4*1.1 -> 11.875144
A24: hello kitty笔记本5set | C24: 01-2601-0094 | D24: 是 | G24: 4964694416263 | H24: 0.05 | I24: 0 | J24: 110 | K24: 30 | L24: 34 | M24: 24 | N24: 2 | O24: =max(L24*M24*N24/8000*1000,K24) -> 204 | P24: 15.43 | Q24: {=XLOOKUP(K24/1000, '运费（邮政）'!$A$2:$A$21, '运费（邮政）'!$B$2:$B$21, "超出范围", 1)} -> 880 | R24: 9.99 | S24: =(V24+U24-Q24)/$B$1 -> 8.0965298 | T24: =P24+R24 -> 25.42 | U24: {=XLOOKUP(O24/1000, '运费（橙联）'!$A$2:$A$57, '运费（橙联）'!$B$2:$B$57, "超出范围", 1)} -> 1581 | V24: =(P24*'参数表'!$C$2*(1+'参数表'!$C$3))*$B$1+'参数表'!$C$4 -> 448.70723 | W24: 0.127 | X24: 0.0135 | Y24: =(P24*(1-I24)-AE24)*$B$1-J24-Q24 -> 633.52971 | Z24: =Y24/P24/$B$1 -> 0.28914302 | AA24: =Y24/J24 -> 5.759361 | AB24: =(P24*(1-I24)+R24-AF24)*$B$1-J24-U24-V24 -> 605.13905 | AC24: =AB24/T24/$B$1 -> 0.16764526 | AD24: =AB24/J24 -> 5.5012641 | AE24: =P24*(1-I24)*(1+'参数表'!$C$6)*(W24+X24+H24)*1.1+0.4*1.1 -> 3.9966921 | AF24: =(P24*(1-I24)*1.1+R24)*(W24+X24+H24)*1.1+0.4*1.1 -> 6.0900966
A25: https://www.amazon.co.jp/dp/B07RW7KB6F?tag=webspire_new-22&linkCode=osi&th=1&psc=1 | C25: 01-2601-0095 | D25: 是 | G25: 4571164384306 | H25: 0.05 | I25: 0 | J25: 3056 | K25: 210 | L25: 14.1 | M25: 12.4 | N25: 1.3 | O25: =max(L25*M25*N25/8000*1000,K25) -> 210 | P25: 49.8 | Q25: {=XLOOKUP(K25/1000, '运费（邮政）'!$A$2:$A$21, '运费（邮政）'!$B$2:$B$21, "超出范围", 1)} -> 1240 | R25: 15.99 | S25: =(V25+U25-Q25)/$B$1 -> 9.0704955 | T25: =P25+R25 -> 65.79 | U25: {=XLOOKUP(O25/1000, '运费（橙联）'!$A$2:$A$57, '运费（橙联）'!$B$2:$B$57, "超出范围", 1)} -> 1581 | V25: =(P25*'参数表'!$C$2*(1+'参数表'!$C$3))*$B$1+'参数表'!$C$4 -> 947.01036 | W25: 0.153 | X25: 0.0135 | Y25: =(P25*(1-I25)-AE25)*$B$1-J25-Q25 -> 860.60831 | Z25: =Y25/P25/$B$1 -> 0.12169923 | AA25: =Y25/J25 -> 0.28161267 | AB25: =(P25*(1-I25)+R25-AF25)*$B$1-J25-U25-V25 -> 1302.4393 | AC25: =AB25/T25/$B$1 -> 0.13941492 | AD25: =AB25/J25 -> 0.42619088 | AE25: =P25*(1-I25)*(1+'参数表'!$C$6)*(W25+X25+H25)*1.1+0.4*1.1 -> 13.485857 | AF25: =(P25*(1-I25)*1.1+R25)*(W25+X25+H25)*1.1+0.4*1.1 -> 17.293875
A26: https://www.amazon.co.jp/dp/B0FXGS6X6V?tag=webspire_new-22&linkCode=osi&th=1&psc=1 | C26: 01-2601-0096 | D26: 是 | G26: 4527516024666 | H26: 0.05 | I26: 0 | J26: 3100 | K26: 210 | L26: 14.1 | M26: 12.4 | N26: 1.3 | O26: =max(L26*M26*N26/8000*1000,K26) -> 210 | P26: 49.8 | Q26: {=XLOOKUP(K26/1000, '运费（邮政）'!$A$2:$A$21, '运费（邮政）'!$B$2:$B$21, "超出范围", 1)} -> 1240 | R26: 15.99 | S26: =(V26+U26-Q26)/$B$1 -> 9.0704955 | T26: =P26+R26 -> 65.79 | U26: {=XLOOKUP(O26/1000, '运费（橙联）'!$A$2:$A$57, '运费（橙联）'!$B$2:$B$57, "超出范围", 1)} -> 1581 | V26: =(P26*'参数表'!$C$2*(1+'参数表'!$C$3))*$B$1+'参数表'!$C$4 -> 947.01036 | W26: 0.153 | X26: 0.0135 | Y26: =(P26*(1-I26)-AE26)*$B$1-J26-Q26 -> 816.60831 | Z26: =Y26/P26/$B$1 -> 0.11547716 | AA26: =Y26/J26 -> 0.26342203 | AB26: =(P26*(1-I26)+R26-AF26)*$B$1-J26-U26-V26 -> 1258.4393 | AC26: =AB26/T26/$B$1 -> 0.1347051 | AD26: =AB26/J26 -> 0.40594817 | AE26: =P26*(1-I26)*(1+'参数表'!$C$6)*(W26+X26+H26)*1.1+0.4*1.1 -> 13.485857 | AF26: =(P26*(1-I26)*1.1+R26)*(W26+X26+H26)*1.1+0.4*1.1 -> 17.293875
A27: https://www.amazon.co.jp/dp/B00CCTU9YY?tag=webspire_new-22&linkCode=osi&th=1&psc=1 | C27: 01-2601-0097 | D27: 是 | G27: 4988005770455 | H27: 0.05 | I27: 0 | J27: 2075 | K27: 210 | L27: 28.5 | M27: 20 | N27: 2 | O27: =max(L27*M27*N27/8000*1000,K27) -> 210 | P27: 37.9 | Q27: {=XLOOKUP(K27/1000, '运费（邮政）'!$A$2:$A$21, '运费（邮政）'!$B$2:$B$21, "超出范围", 1)} -> 1240 | R27: 12.99 | S27: =(V27+U27-Q27)/$B$1 -> 7.8555055 | T27: =P27+R27 -> 50.89 | U27: {=XLOOKUP(O27/1000, '运费（橙联）'!$A$2:$A$57, '运费（橙联）'!$B$2:$B$57, "超出范围", 1)} -> 1581 | V27: =(P27*'参数表'!$C$2*(1+'参数表'!$C$3))*$B$1+'参数表'!$C$4 -> 774.48178 | W27: 0.153 | X27: 0.0135 | Y27: =(P27*(1-I27)-AE27)*$B$1-J27-Q27 -> 594.47676 | Z27: =Y27/P27/$B$1 -> 0.11046058 | AA27: =Y27/J27 -> 0.28649483 | AB27: =(P27*(1-I27)+R27-AF27)*$B$1-J27-U27-V27 -> 884.28826 | AC27: =AB27/T27/$B$1 -> 0.12236947 | AD27: =AB27/J27 -> 0.42616301 | AE27: =P27*(1-I27)*(1+'参数表'!$C$6)*(W27+X27+H27)*1.1+0.4*1.1 -> 10.368474 | AF27: =(P27*(1-I27)*1.1+R27)*(W27+X27+H27)*1.1+0.4*1.1 -> 13.462042
A28: https://www.amazon.co.jp/dp/B0G394CNLB?tag=webspire_new-22&linkCode=osi&th=1&psc=1 | C28: 01-2601-0098 | D28: 是 | G28: 4943674435432 | H28: 0.05 | I28: 0 | J28: 2970 | K28: 210 | L28: 14.2 | M28: 12.6 | N28: 0.7 | O28: =max(L28*M28*N28/8000*1000,K28) -> 210 | P28: 49.8 | Q28: {=XLOOKUP(K28/1000, '运费（邮政）'!$A$2:$A$21, '运费（邮政）'!$B$2:$B$21, "超出范围", 1)} -> 1240 | R28: 15.99 | S28: =(V28+U28-Q28)/$B$1 -> 9.0704955 | T28: =P28+R28 -> 65.79 | U28: {=XLOOKUP(O28/1000, '运费（橙联）'!$A$2:$A$57, '运费（橙联）'!$B$2:$B$57, "超出范围", 1)} -> 1581 | V28: =(P28*'参数表'!$C$2*(1+'参数表'!$C$3))*$B$1+'参数表'!$C$4 -> 947.01036 | W28: 0.153 | X28: 0.0135 | Y28: =(P28*(1-I28)-AE28)*$B$1-J28-Q28 -> 946.60831 | Z28: =Y28/P28/$B$1 -> 0.13386056 | AA28: =Y28/J28 -> 0.31872334 | AB28: =(P28*(1-I28)+R28-AF28)*$B$1-J28-U28-V28 -> 1388.4393 | AC28: =AB28/T28/$B$1 -> 0.14862048 | AD28: =AB28/J28 -> 0.46748799 | AE28: =P28*(1-I28)*(1+'参数表'!$C$6)*(W28+X28+H28)*1.1+0.4*1.1 -> 13.485857 | AF28: =(P28*(1-I28)*1.1+R28)*(W28+X28+H28)*1.1+0.4*1.1 -> 17.293875
A29: https://www.amazon.co.jp/dp/B0FYDX6Z7D?tag=webspire_new-22&linkCode=osi&th=1&psc=1 | C29: 01-2601-0099 | D29: 是 | G29: 4571614702940 | H29: 0.05 | I29: 0 | J29: 4950 | K29: 210 | L29: 14.1 | M29: 12.4 | N29: 0.9 | O29: =max(L29*M29*N29/8000*1000,K29) -> 210 | P29: 74.8 | Q29: {=XLOOKUP(K29/1000, '运费（邮政）'!$A$2:$A$21, '运费（邮政）'!$B$2:$B$21, "超出范围", 1)} -> 1240 | R29: 21.99 | S29: =(V29+U29-Q29)/$B$1 -> 11.622995 | T29: =P29+R29 -> 96.79 | U29: {=XLOOKUP(O29/1000, '运费（橙联）'!$A$2:$A$57, '运费（橙联）'!$B$2:$B$57, "超出范围", 1)} -> 1581 | V29: =(P29*'参数表'!$C$2*(1+'参数表'!$C$3))*$B$1+'参数表'!$C$4 -> 1309.4654 | W29: 0.153 | X29: 0.0135 | Y29: =(P29*(1-I29)-AE29)*$B$1-J29-Q29 -> 1586.6326 | Z29: =Y29/P29/$B$1 -> 0.14937792 | AA29: =Y29/J29 -> 0.32053183 | AB29: =(P29*(1-I29)+R29-AF29)*$B$1-J29-U29-V29 -> 2315.1048 | AC29: =AB29/T29/$B$1 -> 0.16844255 | AD29: =AB29/J29 -> 0.46769793 | AE29: =P29*(1-I29)*(1+'参数表'!$C$6)*(W29+X29+H29)*1.1+0.4*1.1 -> 20.034982 | AF29: =(P29*(1-I29)*1.1+R29)*(W29+X29+H29)*1.1+0.4*1.1 -> 25.271901
A30: https://store.shopping.yahoo.co.jp/esdigital/10164087.html?sc_e=afvc_shp_3144472 | C30: 01-2601-0100 | D30: 是 | G30: 4560423191557 | H30: 0.05 | I30: 0 | J30: 3232 | K30: 610 | L30: 34 | M30: 24 | N30: 2 | O30: =max(L30*M30*N30/8000*1000,K30) -> 610 | P30: 58.8 | Q30: {=XLOOKUP(K30/1000, '运费（邮政）'!$A$2:$A$21, '运费（邮政）'!$B$2:$B$21, "超出范围", 1)} -> 1960 | R30: 18.99 | S30: =(V30+U30-Q30)/$B$1 -> 10.130241 | T30: =P30+R30 -> 77.79 | U30: {=XLOOKUP(O30/1000, '运费（橙联）'!$A$2:$A$57, '运费（橙联）'!$B$2:$B$57, "超出范围", 1)} -> 2321 | V30: =(P30*'参数表'!$C$2*(1+'参数表'!$C$3))*$B$1+'参数表'!$C$4 -> 1077.4942 | W30: 0.153 | X30: 0.0135 | Y30: =(P30*(1-I30)-AE30)*$B$1-J30-Q30 -> 907.81704 | Z30: =Y30/P30/$B$1 -> 0.10872581 | AA30: =Y30/J30 -> 0.28088398 | AB30: =(P30*(1-I30)+R30-AF30)*$B$1-J30-U30-V30 -> 1523.7123 | AC30: =AB30/T30/$B$1 -> 0.13794021 | AD30: =AB30/J30 -> 0.47144565 | AE30: =P30*(1-I30)*(1+'参数表'!$C$6)*(W30+X30+H30)*1.1+0.4*1.1 -> 15.843542 | AF30: =(P30*(1-I30)*1.1+R30)*(W30+X30+H30)*1.1+0.4*1.1 -> 20.366011
A31: https://www.amazon.co.jp/18%E3%82%A8%E3%82%AF%E3%82%B9%E3%83%88%E3%83%A9%E3%82%B9%E3%82%B1%E3%83%BC%E3%83%AB%E5%9B%BD%E7%94%A3%E5%90%8D%E8%BB%8A-%E5%89%B5%E5%88%8A-2026%E5%B9%B4-21-%E5%8F%B7-%E9%9B%91%E8%AA%8C/dp/B0G6MF8H65/ref=pd_sbs_d_sccl_2_3/355-3582507-3163057?pd_rd_w=eLa6J&content-id=amzn1.sym.06c48127-87ed-46e1-9c82-5caa3f707eab&pf_rd_p=06c48127-87ed-46e1-9c82-5caa3f707eab&pf_rd_r=VCMA0SBFFVJ78BS9PE9N&pd_rd_wg=RIn5r&pd_rd_r=d58db1eb-817f-4980-ab1c-c9fb6d3c9939&pd_rd_i=B0G6MF8H65&psc=1 | C31: 01-2601-0101 | D31: 是 | G31: 4912305330163 | H31: 0.05 | I31: 0 | J31: 2990 | K31: 1366 | L31: 40 | M31: 25 | N31: 15 | O31: =max(L31*M31*N31/8000*1000,K31) -> 1875 | P31: 69.8 | Q31: {=XLOOKUP(K31/1000, '运费（邮政）'!$A$2:$A$21, '运费（邮政）'!$B$2:$B$21, "超出范围", 1)} -> 3220 | R31: 25 | S31: =(V31+U31-Q31)/$B$1 -> 14.035031 | T31: =P31+R31 -> 94.8 | U31: {=XLOOKUP(O31/1000, '运费（橙联）'!$A$2:$A$57, '运费（橙联）'!$B$2:$B$57, "超出范围", 1)} -> 3976 | V31: =(P31*'参数表'!$C$2*(1+'参数表'!$C$3))*$B$1+'参数表'!$C$4 -> 1236.9744 | W31: 0.153 | X31: 0.0135 | Y31: =(P31*(1-I31)-AE31)*$B$1-J31-Q31 -> 1042.6277 | Z31: =Y31/P31/$B$1 -> 0.10519267 | AA31: =Y31/J31 -> 0.34870492 | AB31: =(P31*(1-I31)+R31-AF31)*$B$1-J31-U31-V31 -> 1754.2208 | AC31: =AB31/T31/$B$1 -> 0.13031295 | AD31: =AB31/J31 -> 0.58669594 | AE31: =P31*(1-I31)*(1+'参数表'!$C$6)*(W31+X31+H31)*1.1+0.4*1.1 -> 18.725157 | AF31: =(P31*(1-I31)*1.1+R31)*(W31+X31+H31)*1.1+0.4*1.1 -> 24.678907
A32: https://www.1101.com/store/techo/en/2026/pc/detail_toolstoys/tt_memo_okumi/ | C32: 01-2601-0102 | D32: 是 | H32: 0.05 | I32: 0 | J32: 1570 | K32: 80 | L32: 28.5 | M32: 20 | N32: 2 | O32: 2 | P32: 32.8 | Q32: {=XLOOKUP(K32/1000, '运费（邮政）'!$A$2:$A$21, '运费（邮政）'!$B$2:$B$21, "超出范围", 1)} -> 880 | R32: 12.99 | S32: =(V32+U32-Q32)/$B$1 -> 7.377049 | T32: =P32+R32 -> 45.79 | U32: {=XLOOKUP(O32/1000, '运费（橙联）'!$A$2:$A$57, '运费（橙联）'!$B$2:$B$57, "超出范围", 1)} -> 1227 | V32: =(P32*'参数表'!$C$2*(1+'参数表'!$C$3))*$B$1+'参数表'!$C$4 -> 700.54096 | W32: 0.153 | X32: 0.0135 | Y32: =(P32*(1-I32)-AE32)*$B$1-J32-Q32 -> 924.99182 | Z32: =Y32/P32/$B$1 -> 0.19859838 | AA32: =Y32/J32 -> 0.58916676 | AB32: =(P32*(1-I32)+R32-AF32)*$B$1-J32-U32-V32 -> 1282.7441 | AC32: =AB32/T32/$B$1 -> 0.19727909 | AD32: =AB32/J32 -> 0.81703448 | AE32: =P32*(1-I32)*(1+'参数表'!$C$6)*(W32+X32+H32)*1.1+0.4*1.1 -> 9.032452 | AF32: =(P32*(1-I32)*1.1+R32)*(W32+X32+H32)*1.1+0.4*1.1 -> 12.12602
A33: https://www.1101.com/store/techo/en/2026/pc/detail_toolstoys/tt_papers_okumi/ | C33: 01-2601-0103 | D33: 是 | H33: 0.05 | I33: 0 | J33: 1520 | K33: 280 | L33: 15 | M33: 10.5 | N33: 2 | O33: 2 | P33: 32.8 | Q33: {=XLOOKUP(K33/1000, '运费（邮政）'!$A$2:$A$21, '运费（邮政）'!$B$2:$B$21, "超出范围", 1)} -> 1240 | R33: 12.99 | S33: =(V33+U33-Q33)/$B$1 -> 4.8418377 | T33: =P33+R33 -> 45.79 | U33: {=XLOOKUP(O33/1000, '运费（橙联）'!$A$2:$A$57, '运费（橙联）'!$B$2:$B$57, "超出范围", 1)} -> 1227 | V33: =(P33*'参数表'!$C$2*(1+'参数表'!$C$3))*$B$1+'参数表'!$C$4 -> 700.54096 | W33: 0.127 | X33: 0.0135 | Y33: =(P33*(1-I33)-AE33)*$B$1-J33-Q33 -> 761.51991 | Z33: =Y33/P33/$B$1 -> 0.1635005 | AA33: =Y33/J33 -> 0.50099994 | AB33: =(P33*(1-I33)+R33-AF33)*$B$1-J33-U33-V33 -> 1532.0272 | AC33: =AB33/T33/$B$1 -> 0.23561747 | AD33: =AB33/J33 -> 1.0079126 | AE33: =P33*(1-I33)*(1+'参数表'!$C$6)*(W33+X33+H33)*1.1+0.4*1.1 -> 8.000564 | AF33: =(P33*(1-I33)*1.1+R33)*(W33+X33+H33)*1.1+0.4*1.1 -> 10.722618
A34: https://www.1101.com/store/techo/en/2026/pc/detail_toolstoys/tt_clearfilec_okumi/ | C34: 01-2601-0104 | D34: 是 | H34: 0.05 | I34: 0 | J34: 1520 | K34: 110 | L34: 20 | M34: 15 | N34: 0.4 | O34: =max(L34*M34*N34/8000*1000,K34) -> 110 | P34: 32.8 | Q34: {=XLOOKUP(K34/1000, '运费（邮政）'!$A$2:$A$21, '运费（邮政）'!$B$2:$B$21, "超出范围", 1)} -> 1060 | R34: 12.99 | S34: =(V34+U34-Q34)/$B$1 -> 7.0953589 | T34: =P34+R34 -> 45.79 | U34: {=XLOOKUP(O34/1000, '运费（橙联）'!$A$2:$A$57, '运费（橙联）'!$B$2:$B$57, "超出范围", 1)} -> 1367 | V34: =(P34*'参数表'!$C$2*(1+'参数表'!$C$3))*$B$1+'参数表'!$C$4 -> 700.54096 | W34: 0.127 | X34: 0.0135 | Y34: =(P34*(1-I34)-AE34)*$B$1-J34-Q34 -> 941.51991 | Z34: =Y34/P34/$B$1 -> 0.20214701 | AA34: =Y34/J34 -> 0.61942099 | AB34: =(P34*(1-I34)+R34-AF34)*$B$1-J34-U34-V34 -> 1392.0272 | AC34: =AB34/T34/$B$1 -> 0.21408623 | AD34: =AB34/J34 -> 0.91580738 | AE34: =P34*(1-I34)*(1+'参数表'!$C$6)*(W34+X34+H34)*1.1+0.4*1.1 -> 8.000564 | AF34: =(P34*(1-I34)*1.1+R34)*(W34+X34+H34)*1.1+0.4*1.1 -> 10.722618
A35: https://www.1101.com/store/techo/en/2026/pc/detail_toolstoys/tt_cocc_okumi/ | C35: 01-2601-0105 | D35: 是 | H35: 0.05 | I35: 0 | J35: 1680 | K35: 110 | L35: 24 | M35: 35 | N35: 0.6 | O35: =max(L35*M35*N35/8000*1000,K35) -> 110 | P35: 33.6 | Q35: {=XLOOKUP(K35/1000, '运费（邮政）'!$A$2:$A$21, '运费（邮政）'!$B$2:$B$21, "超出范围", 1)} -> 1060 | R35: 12.99 | S35: =(V35+U35-Q35)/$B$1 -> 7.1770389 | T35: =P35+R35 -> 46.59 | U35: {=XLOOKUP(O35/1000, '运费（橙联）'!$A$2:$A$57, '运费（橙联）'!$B$2:$B$57, "超出范围", 1)} -> 1367 | V35: =(P35*'参数表'!$C$2*(1+'参数表'!$C$3))*$B$1+'参数表'!$C$4 -> 712.13952 | W35: 0.127 | X35: 0.0135 | Y35: =(P35*(1-I35)-AE35)*$B$1-J35-Q35 -> 868.93454 | Z35: =Y35/P35/$B$1 -> 0.18212075 | AA35: =Y35/J35 -> 0.51722294 | AB35: =(P35*(1-I35)+R35-AF35)*$B$1-J35-U35-V35 -> 1307.8433 | AC35: =AB35/T35/$B$1 -> 0.19768543 | AD35: =AB35/J35 -> 0.77847815 | AE35: =P35*(1-I35)*(1+'参数表'!$C$6)*(W35+X35+H35)*1.1+0.4*1.1 -> 8.184968 | AF35: =(P35*(1-I35)*1.1+R35)*(W35+X35+H35)*1.1+0.4*1.1 -> 10.907023
A36: https://www.1101.com/store/techo/en/2026/pc/detail_toolstoys/tt_liner_okumi/ | B36: https://www.amazon.co.jp/%E5%A5%A5%E8%A6%8B%E4%BC%8A%E4%BB%A3-%E3%81%BB%E3%81%BC%E6%97%A5%E3%81%AE%E4%B8%8B%E6%95%B7%E3%81%8D-HAPPY-taste-%E3%82%AB%E3%82%BA%E3%83%B3%E3%82%B5%E3%82%A4%E3%82%BA%E7%94%A8/dp/B0FG2JVCDV?th=1 | C36: 01-2601-0106 | D36: 是 | F36: set | G36: 4573630240512 | H36: 0.05 | I36: 0 | J36: 1710 | K36: 110 | L36: 34 | M36: 24 | N36: 2 | O36: =max(L36*M36*N36/8000*1000,K36) -> 204 | P36: 32.5 | Q36: {=XLOOKUP(K36/1000, '运费（邮政）'!$A$2:$A$21, '运费（邮政）'!$B$2:$B$21, "超出范围", 1)} -> 1060 | R36: 12.99 | S36: =(V36+U36-Q36)/$B$1 -> 8.5717711 | T36: =P36+R36 -> 45.49 | U36: {=XLOOKUP(O36/1000, '运费（橙联）'!$A$2:$A$57, '运费（橙联）'!$B$2:$B$57, "超出范围", 1)} -> 1581 | V36: =(P36*'参数表'!$C$2*(1+'参数表'!$C$3))*$B$1+'参数表'!$C$4 -> 696.1915 | W36: 0.127 | X36: 0.0135 | Y36: =(P36*(1-I36)-AE36)*$B$1-J36-Q36 -> 718.73942 | Z36: =Y36/P36/$B$1 -> 0.15573985 | AA36: =Y36/J36 -> 0.42031545 | AB36: =(P36*(1-I36)+R36-AF36)*$B$1-J36-U36-V36 -> 959.59619 | AC36: =AB36/T36/$B$1 -> 0.14855396 | AD36: =AB36/J36 -> 0.56116736 | AE36: =P36*(1-I36)*(1+'参数表'!$C$6)*(W36+X36+H36)*1.1+0.4*1.1 -> 7.9314125 | AF36: =(P36*(1-I36)*1.1+R36)*(W36+X36+H36)*1.1+0.4*1.1 -> 10.653467
A37: https://www.1101.com/store/techo/en/2026/pc/detail_toolstoys/tt_cc_okumi/ | C37: 01-2601-0107 | D37: 是 | H37: 0.05 | I37: 0 | J37: 1520 | K37: 80 | L37: 20 | M37: 20 | N37: 0.9 | O37: =max(L37*M37*N37/8000*1000,K37) -> 80 | P37: 32.8 | Q37: {=XLOOKUP(K37/1000, '运费（邮政）'!$A$2:$A$21, '运费（邮政）'!$B$2:$B$21, "超出范围", 1)} -> 880 | R37: 12.99 | S37: =(V37+U37-Q37)/$B$1 -> 7.377049 | T37: =P37+R37 -> 45.79 | U37: {=XLOOKUP(O37/1000, '运费（橙联）'!$A$2:$A$57, '运费（橙联）'!$B$2:$B$57, "超出范围", 1)} -> 1227 | V37: =(P37*'参数表'!$C$2*(1+'参数表'!$C$3))*$B$1+'参数表'!$C$4 -> 700.54096 | W37: 0.127 | X37: 0.0135 | Y37: =(P37*(1-I37)-AE37)*$B$1-J37-Q37 -> 1121.5199 | Z37: =Y37/P37/$B$1 -> 0.24079352 | AA37: =Y37/J37 -> 0.73784205 | AB37: =(P37*(1-I37)+R37-AF37)*$B$1-J37-U37-V37 -> 1532.0272 | AC37: =AB37/T37/$B$1 -> 0.23561747 | AD37: =AB37/J37 -> 1.0079126 | AE37: =P37*(1-I37)*(1+'参数表'!$C$6)*(W37+X37+H37)*1.1+0.4*1.1 -> 8.000564 | AF37: =(P37*(1-I37)*1.1+R37)*(W37+X37+H37)*1.1+0.4*1.1 -> 10.722618
A38: https://www.amazon.co.jp/dp/B0DCD2CSS1?tag=webspire_new-22&linkCode=osi&th=1&psc=1 | C38: 01-2601-0108 | D38: 是 | G38: 4988031675755 | H38: 0.05 | I38: 0 | J38: 2750 | K38: 210 | L38: 14.1 | M38: 12.4 | N38: 0.9 | O38: =max(L38*M38*N38/8000*1000,K38) -> 210 | P38: 44.8 | Q38: {=XLOOKUP(K38/1000, '运费（邮政）'!$A$2:$A$21, '运费（邮政）'!$B$2:$B$21, "超出范围", 1)} -> 1240 | R38: 15.99 | S38: =(V38+U38-Q38)/$B$1 -> 8.5599955 | T38: =P38+R38 -> 60.79 | U38: {=XLOOKUP(O38/1000, '运费（橙联）'!$A$2:$A$57, '运费（橙联）'!$B$2:$B$57, "超出范围", 1)} -> 1581 | V38: =(P38*'参数表'!$C$2*(1+'参数表'!$C$3))*$B$1+'参数表'!$C$4 -> 874.51936 | W38: 0.127 | X38: 0.0135 | Y38: =(P38*(1-I38)-AE38)*$B$1-J38-Q38 -> 842.73939 | Z38: =Y38/P38/$B$1 -> 0.13247287 | AA38: =Y38/J38 -> 0.30645069 | AB38: =(P38*(1-I38)+R38-AF38)*$B$1-J38-U38-V38 -> 1422 | AC38: =AB38/T38/$B$1 -> 0.16473243 | AD38: =AB38/J38 -> 0.51709091 | AE38: =P38*(1-I38)*(1+'参数表'!$C$6)*(W38+X38+H38)*1.1+0.4*1.1 -> 10.766624 | AF38: =(P38*(1-I38)*1.1+R38)*(W38+X38+H38)*1.1+0.4*1.1 -> 14.117328
A39: https://www.amazon.co.jp/%E3%80%90Amazon-co-jp-%E9%99%90%E5%AE%9A%E3%80%91%E3%82%B7%E3%83%AB%E3%83%90%E3%83%8B%E3%82%A2%E3%83%95%E3%82%A1%E3%83%9F%E3%83%AA%E3%83%BC-%E8%B5%A4%E3%81%84%E5%B1%8B%E6%A0%B9%E3%81%AE%E5%A4%A7%E3%81%8D%E3%81%AA%E3%81%8A%E5%AE%B6-%E5%B1%8B%E6%A0%B9%E8%A3%8F%E3%81%AF%E3%81%B2%E3%81%BF%E3%81%A4%E3%81%AE%E3%81%8A%E9%83%A8%E5%B1%8B-22-RZ/dp/B0BBT9GZ5J/ref=sr_1_1_sspa?crid=2L1N1L8X8E7GY&dib=eyJ2IjoiMSJ9.SpscTIEXrgIcKzrEJ6cefh34U0X21LOcjx472J8jcOsnVKIWjGXyYsWKflM6BUPS2TEoMLTm319CRoIev6kET7JQriElusxqss7RosSabpZA0nLX1ouwCl8hW6cVmS23nBBgg_udd12w7IU0Q0ZAohvCF4S2dngmVnGu1Zo-54VIDI023hGPpQcZIzO0qZePvd6JEe8GaUmFkcWrQqLA1Yo2q9cMy27xP6aaVfODo6eM2SW9DNcA9VR3DgdQ_mPhE6e-ZB35jrZu9CPG1FFPt4M7ND3ZP4U5FH5m0v1y9W4.6OL6uvuO6FxJmSNEddPuJou_Gpxg2CNEXLBsd4xf97c&dib_tag=se&keywords=sylvanian%2Bfamilies&qid=1768886676&sprefix=sylvanian%2Caps%2C243&sr=8-1-spons&sp_csd=d2lkZ2V0TmFtZT1zcF9hdGY&th=1 | C39: 01-2601-0109 | D39: 是 | F39: 大件 | G39: 4905040152015 | H39: 0.05 | I39: 0 | J39: 11000 | K39: 6000 | L39: 65 | M39: 25 | N39: 40 | O39: =max(L39*M39*N39/8000*1000,K39) -> 8125 | P39: 142 | Q39: {=XLOOKUP(K39/1000, '运费（邮政）'!$A$2:$A$21, '运费（邮政）'!$B$2:$B$21, "超出范围", 1)} -> 超出范围 | R39: 280 | S39: =(V39+U39-Q39)/$B$1 -> #VALUE! | T39: =P39+R39 -> 422 | U39: {=XLOOKUP(O39/1000, '运费（橙联）'!$A$2:$A$57, '运费（橙联）'!$B$2:$B$57, "超出范围", 1)} -> 9884 | V39: =(P39*'参数表'!$C$2*(1+'参数表'!$C$3))*$B$1+'参数表'!$C$4 -> 2283.7444 | W39: 0.127 | X39: 0.0135 | Y39: =(P39*(1-I39)-AE39)*$B$1-J39-Q39 -> #VALUE! | Z39: =Y39/P39/$B$1 -> #VALUE! | AA39: =Y39/J39 -> #VALUE! | AB39: =(P39*(1-I39)+R39-AF39)*$B$1-J39-U39-V39 -> 23714.165 | AC39: =AB39/T39/$B$1 -> 0.39573735 | AD39: =AB39/J39 -> 2.1558332 | AE39: =P39*(1-I39)*(1+'参数表'!$C$6)*(W39+X39+H39)*1.1+0.4*1.1 -> 33.17171 | AF39: =(P39*(1-I39)*1.1+R39)*(W39+X39+H39)*1.1+0.4*1.1 -> 91.84571
A40: https://www.1101.com/store/techo/en/2026/pc/detail_cover/cc26_okumi/ | C40: 01-2601-0110 | D40: 是 | H40: 0.05 | I40: 0 | J40: 6580 | K40: 170 | L40: 33.7 | M40: 28 | N40: 3 | O40: =max(L40*M40*N40/8000*1000,K40) -> 353.85 | P40: 89.54 | Q40: {=XLOOKUP(K40/1000, '运费（邮政）'!$A$2:$A$21, '运费（邮政）'!$B$2:$B$21, "超出范围", 1)} -> 1060 | R40: 28.99 | S40: =(V40+U40-Q40)/$B$1 -> 15.782879 | T40: =P40+R40 -> 118.53 | U40: {=XLOOKUP(O40/1000, '运费（橙联）'!$A$2:$A$57, '运费（橙联）'!$B$2:$B$57, "超出范围", 1)} -> 1778 | V40: =(P40*'参数表'!$C$2*(1+'参数表'!$C$3))*$B$1+'参数表'!$C$4 -> 1523.1688 | W40: 0.127 | X40: 0.0135 | Y40: =(P40*(1-I40)-AE40)*$B$1-J40-Q40 -> 2081.4027 | Z40: =Y40/P40/$B$1 -> 0.16370075 | AA40: =Y40/J40 -> 0.3163226 | AB40: =(P40*(1-I40)+R40-AF40)*$B$1-J40-U40-V40 -> 3094.1845 | AC40: =AB40/T40/$B$1 -> 0.18383558 | AD40: =AB40/J40 -> 0.47024081 | AE40: =P40*(1-I40)*(1+'参数表'!$C$6)*(W40+X40+H40)*1.1+0.4*1.1 -> 21.079418 | AF40: =(P40*(1-I40)*1.1+R40)*(W40+X40+H40)*1.1+0.4*1.1 -> 27.154272
A41: https://www.amazon.co.jp/dp/B000059O4K?tag=webspire_new-22&linkCode=osi&th=1&psc=1 | C41: 01-2601-0111 | D41: 是 | G41: 4988001131991 | H41: 0.05 | I41: 0 | J41: 3204 | K41: 210 | L41: 12 | M41: 14 | N41: 1 | O41: =max(L41*M41*N41/8000*1000,K41) -> 210 | P41: 52.8 | Q41: {=XLOOKUP(K41/1000, '运费（邮政）'!$A$2:$A$21, '运费（邮政）'!$B$2:$B$21, "超出范围", 1)} -> 1240 | R41: 15.99 | S41: =(V41+U41-Q41)/$B$1 -> 9.3767955 | T41: =P41+R41 -> 68.79 | U41: {=XLOOKUP(O41/1000, '运费（橙联）'!$A$2:$A$57, '运费（橙联）'!$B$2:$B$57, "超出范围", 1)} -> 1581 | V41: =(P41*'参数表'!$C$2*(1+'参数表'!$C$3))*$B$1+'参数表'!$C$4 -> 990.50496 | W41: 0.153 | X41: 0.0135 | Y41: =(P41*(1-I41)-AE41)*$B$1-J41-Q41 -> 1027.0112 | Z41: =Y41/P41/$B$1 -> 0.13697866 | AA41: =Y41/J41 -> 0.32054033 | AB41: =(P41*(1-I41)+R41-AF41)*$B$1-J41-U41-V41 -> 1425.3476 | AC41: =AB41/T41/$B$1 -> 0.14591742 | AD41: =AB41/J41 -> 0.44486505 | AE41: =P41*(1-I41)*(1+'参数表'!$C$6)*(W41+X41+H41)*1.1+0.4*1.1 -> 14.271752 | AF41: =(P41*(1-I41)*1.1+R41)*(W41+X41+H41)*1.1+0.4*1.1 -> 18.07977
A42: https://www.amazon.co.jp/dp/B0CCXJXSLT?tag=webspire_new-22&linkCode=osi&th=1&psc=1 | C42: 01-2601-0112 | D42: 是 | G42: 4988031591116 | H42: 0.05 | I42: 0 | J42: 3630 | K42: 180 | L42: 14.1 | M42: 12.4 | N42: 0.9 | O42: =max(L42*M42*N42/8000*1000,K42) -> 180 | P42: 54.8 | Q42: {=XLOOKUP(K42/1000, '运费（邮政）'!$A$2:$A$21, '运费（邮政）'!$B$2:$B$21, "超出范围", 1)} -> 1060 | R42: 15.99 | S42: =(V42+U42-Q42)/$B$1 -> 9.3415589 | T42: =P42+R42 -> 70.79 | U42: {=XLOOKUP(O42/1000, '运费（橙联）'!$A$2:$A$57, '运费（橙联）'!$B$2:$B$57, "超出范围", 1)} -> 1367 | V42: =(P42*'参数表'!$C$2*(1+'参数表'!$C$3))*$B$1+'参数表'!$C$4 -> 1019.5014 | W42: 0.153 | X42: 0.0135 | Y42: =(P42*(1-I42)-AE42)*$B$1-J42-Q42 -> 990.61316 | Z42: =Y42/P42/$B$1 -> 0.12730199 | AA42: =Y42/J42 -> 0.27289619 | AB42: =(P42*(1-I42)+R42-AF42)*$B$1-J42-U42-V42 -> 1393.9532 | AC42: =AB42/T42/$B$1 -> 0.13867173 | AD42: =AB42/J42 -> 0.38400914 | AE42: =P42*(1-I42)*(1+'参数表'!$C$6)*(W42+X42+H42)*1.1+0.4*1.1 -> 14.795682 | AF42: =(P42*(1-I42)*1.1+R42)*(W42+X42+H42)*1.1+0.4*1.1 -> 18.6037
A43: https://www.amazon.co.jp/dp/B0G8Y9NPN7?tag=webspire_new-22&linkCode=osi&th=1&psc=1 | C43: 01-2601-0113 | D43: 预售月底上架 | G43: 4988031843574 | H43: 0.05 | I43: 0 | J43: 1540 | K43: 180 | L43: 14.1 | M43: 12.4 | N43: 0.9 | O43: =max(L43*M43*N43/8000*1000,K43) -> 180 | P43: 28.8 | Q43: {=XLOOKUP(K43/1000, '运费（邮政）'!$A$2:$A$21, '运费（邮政）'!$B$2:$B$21, "超出范围", 1)} -> 1060 | R43: 12.99 | S43: =(V43+U43-Q43)/$B$1 -> 6.6869589 | T43: =P43+R43 -> 41.79 | U43: {=XLOOKUP(O43/1000, '运费（橙联）'!$A$2:$A$57, '运费（橙联）'!$B$2:$B$57, "超出范围", 1)} -> 1367 | V43: =(P43*'参数表'!$C$2*(1+'参数表'!$C$3))*$B$1+'参数表'!$C$4 -> 642.54816 | W43: 0.153 | X43: 0.0135 | Y43: =(P43*(1-I43)-AE43)*$B$1-J43-Q43 -> 355.78794 | Z43: =Y43/P43/$B$1 -> 0.086998224 | AA43: =Y43/J43 -> 0.23103113 | AB43: =(P43*(1-I43)+R43-AF43)*$B$1-J43-U43-V43 -> 811.53305 | AC43: =AB43/T43/$B$1 -> 0.13675572 | AD43: =AB43/J43 -> 0.52696951 | AE43: =P43*(1-I43)*(1+'参数表'!$C$6)*(W43+X43+H43)*1.1+0.4*1.1 -> 7.984592 | AF43: =(P43*(1-I43)*1.1+R43)*(W43+X43+H43)*1.1+0.4*1.1 -> 11.07816
A44: https://www.amazon.co.jp/dp/B003WIT4FY?tag=webspire_new-22&linkCode=osi&th=1&psc=1 | C44: 01-2601-0114 | D44: 是 | G44: 4988003392482 | H44: 0.05 | I44: 0 | J44: 1781 | K44: 280 | L44: 16 | M44: 13 | N44: 2 | O44: =max(L44*M44*N44/8000*1000,K44) -> 280 | P44: 34.8 | Q44: {=XLOOKUP(K44/1000, '运费（邮政）'!$A$2:$A$21, '运费（邮政）'!$B$2:$B$21, "超出范围", 1)} -> 1240 | R44: 12.99 | S44: =(V44+U44-Q44)/$B$1 -> 7.5389955 | T44: =P44+R44 -> 47.79 | U44: {=XLOOKUP(O44/1000, '运费（橙联）'!$A$2:$A$57, '运费（橙联）'!$B$2:$B$57, "超出范围", 1)} -> 1581 | V44: =(P44*'参数表'!$C$2*(1+'参数表'!$C$3))*$B$1+'参数表'!$C$4 -> 729.53736 | W44: 0.153 | X44: 0.0135 | Y44: =(P44*(1-I44)-AE44)*$B$1-J44-Q44 -> 563.59376 | Z44: =Y44/P44/$B$1 -> 0.11405087 | AA44: =Y44/J44 -> 0.31644793 | AB44: =(P44*(1-I44)+R44-AF44)*$B$1-J44-U44-V44 -> 898.34967 | AC44: =AB44/T44/$B$1 -> 0.13237929 | AD44: =AB44/J44 -> 0.50440745 | AE44: =P44*(1-I44)*(1+'参数表'!$C$6)*(W44+X44+H44)*1.1+0.4*1.1 -> 9.556382 | AF44: =(P44*(1-I44)*1.1+R44)*(W44+X44+H44)*1.1+0.4*1.1 -> 12.64995
A45: https://www.amazon.co.jp/dp/B0756M7JDB?tag=webspire_new-22&linkCode=osi&th=1&psc=1 | C45: 01-2601-0115 | D45: 是 | G45: 4547366327199 | H45: 0.05 | I45: 0 | J45: 1100 | K45: 150 | L45: 14 | M45: 12 | N45: 2 | O45: =max(L45*M45*N45/8000*1000,K45) -> 150 | P45: 24.8 | Q45: {=XLOOKUP(K45/1000, '运费（邮政）'!$A$2:$A$21, '运费（邮政）'!$B$2:$B$21, "超出范围", 1)} -> 1060 | R45: 9.99 | S45: =(V45+U45-Q45)/$B$1 -> 6.2785589 | T45: =P45+R45 -> 34.79 | U45: {=XLOOKUP(O45/1000, '运费（橙联）'!$A$2:$A$57, '运费（橙联）'!$B$2:$B$57, "超出范围", 1)} -> 1367 | V45: =(P45*'参数表'!$C$2*(1+'参数表'!$C$3))*$B$1+'参数表'!$C$4 -> 584.55536 | W45: 0.153 | X45: 0.0135 | Y45: =(P45*(1-I45)-AE45)*$B$1-J45-Q45 -> 376.58406 | Z45: =Y45/P45/$B$1 -> 0.1069355 | AA45: =Y45/J45 -> 0.34234914 | AB45: =(P45*(1-I45)+R45-AF45)*$B$1-J45-U45-V45 -> 565.77387 | AC45: =AB45/T45/$B$1 -> 0.11452495 | AD45: =AB45/J45 -> 0.51433988 | AE45: =P45*(1-I45)*(1+'参数表'!$C$6)*(W45+X45+H45)*1.1+0.4*1.1 -> 6.936732 | AF45: =(P45*(1-I45)*1.1+R45)*(W45+X45+H45)*1.1+0.4*1.1 -> 9.3158505
A46: https://www.amazon.co.jp/dp/B002CNV3P4?tag=webspire_new-22&linkCode=osi&th=1&psc=1 | C46: 01-2601-0116 | D46: 是 | G46: 4988005573513 | H46: 0.05 | I46: 0 | J46: 1561 | K46: 150 | L46: 14 | M46: 12 | N46: 2 | O46: =max(L46*M46*N46/8000*1000,K46) -> 150 | P46: 29.8 | Q46: {=XLOOKUP(K46/1000, '运费（邮政）'!$A$2:$A$21, '运费（邮政）'!$B$2:$B$21, "超出范围", 1)} -> 1060 | R46: 12.99 | S46: =(V46+U46-Q46)/$B$1 -> 6.7890589 | T46: =P46+R46 -> 42.79 | U46: {=XLOOKUP(O46/1000, '运费（橙联）'!$A$2:$A$57, '运费（橙联）'!$B$2:$B$57, "超出范围", 1)} -> 1367 | V46: =(P46*'参数表'!$C$2*(1+'参数表'!$C$3))*$B$1+'参数表'!$C$4 -> 657.04636 | W46: 0.153 | X46: 0.0135 | Y46: =(P46*(1-I46)-AE46)*$B$1-J46-Q46 -> 439.58891 | Z46: =Y46/P46/$B$1 -> 0.10388243 | AA46: =Y46/J46 -> 0.28160724 | AB46: =(P46*(1-I46)+R46-AF46)*$B$1-J46-U46-V46 -> 880.83582 | AC46: =AB46/T46/$B$1 -> 0.14496539 | AD46: =AB46/J46 -> 0.56427663 | AE46: =P46*(1-I46)*(1+'参数表'!$C$6)*(W46+X46+H46)*1.1+0.4*1.1 -> 8.246557 | AF46: =(P46*(1-I46)*1.1+R46)*(W46+X46+H46)*1.1+0.4*1.1 -> 11.340125
A47: https://www.amazon.co.jp/%E3%82%A8%E3%83%9D%E3%83%83%E3%82%AF%E7%A4%BE%EF%BC%88EPOCH%EF%BC%89-%E3%80%90%E3%83%88%E3%83%AC%E3%83%BC%E3%83%87%E3%82%A3%E3%83%B3%E3%82%B0%E3%82%AB%E3%83%BC%E3%83%89%E3%82%B5%E3%82%A4%E3%82%BA%E3%81%AE%E3%82%B8%E3%82%B0%E3%82%BD%E3%83%BC%E3%83%91%E3%82%BA%E3%83%AB%E3%80%91-58-204-%E3%83%88%E3%83%AC%E3%83%BC%E3%83%87%E3%82%A3%E3%83%B3%E3%82%B0%E3%83%91%E3%82%BA%E3%83%AB-%EF%BC%886%C3%978-6cm%EF%BC%89/dp/B0DTJX6XZK/ref=sr_1_3?crid=9RQITUICNZMP&dib=eyJ2IjoiMSJ9.gmhCn42Cwma9VBqwd0YM5iLXIiO3XqOibqPDLPfWMqYLHALkJDF1-QLotnmIhz9dsXCdnV-2EGbvw0k-OJDMQ7aJ-x5ir0a7gWebKZwUn8oGQluHNGYBHAdqbfCxGxxmr21VNFlE63JIPaLUykubsRw0xK6E5DDSZn-1lSyPGC1Y18juas1DUNlXdjyhIFqC2Em5zNcrviogEDbzGw6jpqF-VPO2TxbMGY_CxkmOe9PcA_1xXgZY7_zhdJJrjAQilQP07bpkhrn7ZYSiICrWBwP2w4RXNSy24-Wbzbr3MsY.i88_sojIt4lnsnshJH_tXbBiSZ3kCw0bLcphOWllfrs&dib_tag=se&keywords=%E8%91%AC%E9%80%81%E3%81%AE%E3%83%95%E3%83%AA%E3%83%BC%E3%83%AC%E3%83%B3%2B%E6%8B%BC%E5%9B%BE&qid=1768529071&sprefix=%E3%82%B8%E3%82%B0%E3%82%BD%E3%83%BC%E3%83%91%E3%82%BA%E3%83%AB%2B%E8%91%AC%E9%80%81%E3%81%AE%E3%83%95%E3%83%AA%E3%83%BC%E3%83%AC%E3%83%B3%2B%E6%8B%BC%E5%9B%BE%2Caps%2C412&sr=8-3&th=1 | C47: 01-2601-0117 | G47: 4977389582044 | H47: 0.05 | I47: 0 | J47: 10000 | K47: 790 | L47: 20 | M47: 20 | N47: 19 | O47: =max(L47*M47*N47/8000*1000,K47) -> 950 | P47: 149.39 | Q47: {=XLOOKUP(K47/1000, '运费（邮政）'!$A$2:$A$21, '运费（邮政）'!$B$2:$B$21, "超出范围", 1)} -> 2140 | R47: 45.99 | S47: =(V47+U47-Q47)/$B$1 -> 23.034409 | T47: =P47+R47 -> 195.38 | U47: {=XLOOKUP(O47/1000, '运费（橙联）'!$A$2:$A$57, '运费（橙联）'!$B$2:$B$57, "超出范围", 1)} -> 3020 | V47: =(P47*'参数表'!$C$2*(1+'参数表'!$C$3))*$B$1+'参数表'!$C$4 -> 2390.8861 | W47: 0.127 | X47: 0.0135 | Y47: =(P47*(1-I47)-AE47)*$B$1-J47-Q47 -> 4121.1098 | Z47: =Y47/P47/$B$1 -> 0.19426936 | AA47: =Y47/J47 -> 0.41211098 | AB47: =(P47*(1-I47)+R47-AF47)*$B$1-J47-U47-V47 -> 6012.3207 | AC47: =AB47/T47/$B$1 -> 0.21670737 | AD47: =AB47/J47 -> 0.60123207 | AE47: =P47*(1-I47)*(1+'参数表'!$C$6)*(W47+X47+H47)*1.1+0.4*1.1 -> 34.875142 | AF47: =(P47*(1-I47)*1.1+R47)*(W47+X47+H47)*1.1+0.4*1.1 -> 44.512346
A48: https://shop.shinfuji.co.jp/products/st-261?variant=44274645532895 | C48: 01-2601-0118 | D48: 是 | G48: 4953571001975 | H48: 0.05 | I48: 0 | J48: 7920 | K48: 255 | L48: 20 | M48: 14 | N48: 15 | O48: =max(L48*M48*N48/8000*1000,K48) -> 525 | P48: 99.58 | Q48: {=XLOOKUP(K48/1000, '运费（邮政）'!$A$2:$A$21, '运费（邮政）'!$B$2:$B$21, "超出范围", 1)} -> 1240 | R48: 35 | S48: =(V48+U48-Q48)/$B$1 -> 18.667118 | T48: =P48+R48 -> 134.58 | U48: {=XLOOKUP(O48/1000, '运费（橙联）'!$A$2:$A$57, '运费（橙联）'!$B$2:$B$57, "超出范围", 1)} -> 2222 | V48: =(P48*'参数表'!$C$2*(1+'参数表'!$C$3))*$B$1+'参数表'!$C$4 -> 1668.7308 | W48: 0.127 | X48: 0.0135 | Y48: =(P48*(1-I48)-AE48)*$B$1-J48-Q48 -> 1658.4563 | Z48: =Y48/P48/$B$1 -> 0.1172853 | AA48: =Y48/J48 -> 0.20940105 | AB48: =(P48*(1-I48)+R48-AF48)*$B$1-J48-U48-V48 -> 2936.2621 | AC48: =AB48/T48/$B$1 -> 0.15364766 | AD48: =AB48/J48 -> 0.37074016 | AE48: =P48*(1-I48)*(1+'参数表'!$C$6)*(W48+X48+H48)*1.1+0.4*1.1 -> 23.393688 | AF48: =(P48*(1-I48)*1.1+R48)*(W48+X48+H48)*1.1+0.4*1.1 -> 30.727938
A49: https://www.cdjapan.co.jp/product/NEODAI-93477 | C49: 01-2601-0119 | D49: 是 | H49: 0.05 | I49: 0 | J49: 3200 | K49: 180 | L49: 14 | M49: 12 | N49: 2 | O49: =max(L49*M49*N49/8000*1000,K49) -> 180 | P49: 49.8 | Q49: {=XLOOKUP(K49/1000, '运费（邮政）'!$A$2:$A$21, '运费（邮政）'!$B$2:$B$21, "超出范围", 1)} -> 1060 | R49: 15.99 | S49: =(V49+U49-Q49)/$B$1 -> 8.8310589 | T49: =P49+R49 -> 65.79 | U49: {=XLOOKUP(O49/1000, '运费（橙联）'!$A$2:$A$57, '运费（橙联）'!$B$2:$B$57, "超出范围", 1)} -> 1367 | V49: =(P49*'参数表'!$C$2*(1+'参数表'!$C$3))*$B$1+'参数表'!$C$4 -> 947.01036 | W49: 0.153 | X49: 0.0135 | Y49: =(P49*(1-I49)-AE49)*$B$1-J49-Q49 -> 896.60831 | Z49: =Y49/P49/$B$1 -> 0.12679002 | AA49: =Y49/J49 -> 0.2801901 | AB49: =(P49*(1-I49)+R49-AF49)*$B$1-J49-U49-V49 -> 1372.4393 | AC49: =AB49/T49/$B$1 -> 0.14690782 | AD49: =AB49/J49 -> 0.42888729 | AE49: =P49*(1-I49)*(1+'参数表'!$C$6)*(W49+X49+H49)*1.1+0.4*1.1 -> 13.485857 | AF49: =(P49*(1-I49)*1.1+R49)*(W49+X49+H49)*1.1+0.4*1.1 -> 17.293875
A50: https://www.amazon.co.jp/dp/B002WQSVHY?tag=webspire_new-22&linkCode=osi&th=1&psc=1 | C50: 01-2601-0120 | D50: 是 | G50: 4988001274001 | H50: 0.05 | I50: 0 | J50: 2096 | K50: 180 | L50: 14 | M50: 12 | N50: 2 | O50: =max(L50*M50*N50/8000*1000,K50) -> 180 | P50: 36.8 | Q50: {=XLOOKUP(K50/1000, '运费（邮政）'!$A$2:$A$21, '运费（邮政）'!$B$2:$B$21, "超出范围", 1)} -> 1060 | R50: 12.99 | S50: =(V50+U50-Q50)/$B$1 -> 7.5037589 | T50: =P50+R50 -> 49.79 | U50: {=XLOOKUP(O50/1000, '运费（橙联）'!$A$2:$A$57, '运费（橙联）'!$B$2:$B$57, "超出范围", 1)} -> 1367 | V50: =(P50*'参数表'!$C$2*(1+'参数表'!$C$3))*$B$1+'参数表'!$C$4 -> 758.53376 | W50: 0.153 | X50: 0.0135 | Y50: =(P50*(1-I50)-AE50)*$B$1-J50-Q50 -> 638.1957 | Z50: =Y50/P50/$B$1 -> 0.12212869 | AA50: =Y50/J50 -> 0.30448268 | AB50: =(P50*(1-I50)+R50-AF50)*$B$1-J50-U50-V50 -> 977.95521 | AC50: =AB50/T50/$B$1 -> 0.13832112 | AD50: =AB50/J50 -> 0.46658168 | AE50: =P50*(1-I50)*(1+'参数表'!$C$6)*(W50+X50+H50)*1.1+0.4*1.1 -> 10.080312 | AF50: =(P50*(1-I50)*1.1+R50)*(W50+X50+H50)*1.1+0.4*1.1 -> 13.17388
A51: https://www.amazon.co.jp/dp/B0F1F1LGCQ?tag=webspire_new-22&linkCode=osi&th=1&psc=1 | C51: 01-2601-0121 | D51: 是 | G51: 4571603150899 | H51: 0.05 | I51: 0 | J51: 4200 | K51: 210 | L51: 14 | M51: 12 | N51: 2 | O51: =max(L51*M51*N51/8000*1000,K51) -> 210 | P51: 62.8 | Q51: {=XLOOKUP(K51/1000, '运费（邮政）'!$A$2:$A$21, '运费（邮政）'!$B$2:$B$21, "超出范围", 1)} -> 1240 | R51: 18.99 | S51: =(V51+U51-Q51)/$B$1 -> 10.397795 | T51: =P51+R51 -> 81.79 | U51: {=XLOOKUP(O51/1000, '运费（橙联）'!$A$2:$A$57, '运费（橙联）'!$B$2:$B$57, "超出范围", 1)} -> 1581 | V51: =(P51*'参数表'!$C$2*(1+'参数表'!$C$3))*$B$1+'参数表'!$C$4 -> 1135.487 | W51: 0.153 | X51: 0.0135 | Y51: =(P51*(1-I51)-AE51)*$B$1-J51-Q51 -> 1079.0209 | Z51: =Y51/P51/$B$1 -> 0.12099903 | AA51: =Y51/J51 -> 0.25690974 | AB51: =(P51*(1-I51)+R51-AF51)*$B$1-J51-U51-V51 -> 1656.9234 | AC51: =AB51/T51/$B$1 -> 0.14266383 | AD51: =AB51/J51 -> 0.39450558 | AE51: =P51*(1-I51)*(1+'参数表'!$C$6)*(W51+X51+H51)*1.1+0.4*1.1 -> 16.891402 | AF51: =(P51*(1-I51)*1.1+R51)*(W51+X51+H51)*1.1+0.4*1.1 -> 21.413871
A52: https://item.rakuten.co.jp/guruguru2/tyct-69338/?scid=af_pc_etc&sc2id=af_106_0_10002231&af_tr_src=i2i_bh__g5_g4&af_tct=t_0_top | C52: 01-2601-0122 | D52: 是 | G52: 4988031681350 | H52: 0.05 | I52: 0 | J52: 2573 | K52: 210 | L52: 14 | M52: 12 | N52: 2 | O52: 180 | P52: 42.9 | Q52: {=XLOOKUP(K52/1000, '运费（邮政）'!$A$2:$A$21, '运费（邮政）'!$B$2:$B$21, "超出范围", 1)} -> 1240 | R52: 12.99 | S52: =(V52+U52-Q52)/$B$1 -> 6.8589632 | T52: =P52+R52 -> 55.89 | U52: {=XLOOKUP(O52/1000, '运费（橙联）'!$A$2:$A$57, '运费（橙联）'!$B$2:$B$57, "超出范围", 1)} -> 1367 | V52: =(P52*'参数表'!$C$2*(1+'参数表'!$C$3))*$B$1+'参数表'!$C$4 -> 846.97278 | W52: 0.153 | X52: 0.0135 | Y52: =(P52*(1-I52)-AE52)*$B$1-J52-Q52 -> 620.48161 | Z52: =Y52/P52/$B$1 -> 0.10185522 | AA52: =Y52/J52 -> 0.24115104 | AB52: =(P52*(1-I52)+R52-AF52)*$B$1-J52-U52-V52 -> 1051.8021 | AC52: =AB52/T52/$B$1 -> 0.1325292 | AD52: =AB52/J52 -> 0.40878434 | AE52: =P52*(1-I52)*(1+'参数表'!$C$6)*(W52+X52+H52)*1.1+0.4*1.1 -> 11.678299 | AF52: =(P52*(1-I52)*1.1+R52)*(W52+X52+H52)*1.1+0.4*1.1 -> 14.771867
A53: https://www.amazon.co.jp/dp/B09MD9XN4B?tag=webspire_new-22&linkCode=osi&th=1 | B53: https://store.shopping.yahoo.co.jp/tomysshop/1225-001035.html?sc_e=afvc_shp_3144472 | C53: 01-2601-0123 | D53: 是 | G53: 4573597550020 | H53: 0.05 | I53: 0 | J53: 2480 | K53: 380 | L53: 21 | M53: 6 | N53: 2.5 | O53: =max(L53*M53*N53/8000*1000,K53) -> 380 | P53: 43.9 | Q53: {=XLOOKUP(K53/1000, '运费（邮政）'!$A$2:$A$21, '运费（邮政）'!$B$2:$B$21, "超出范围", 1)} -> 1420 | R53: 15.99 | S53: =(V53+U53-Q53)/$B$1 -> 8.5878238 | T53: =P53+R53 -> 59.89 | U53: {=XLOOKUP(O53/1000, '运费（橙联）'!$A$2:$A$57, '运费（橙联）'!$B$2:$B$57, "超出范围", 1)} -> 1778 | V53: =(P53*'参数表'!$C$2*(1+'参数表'!$C$3))*$B$1+'参数表'!$C$4 -> 861.47098 | W53: 0.127 | X53: 0.0135 | Y53: =(P53*(1-I53)-AE53)*$B$1-J53-Q53 -> 834.39793 | Z53: =Y53/P53/$B$1 -> 0.13385061 | AA53: =Y53/J53 -> 0.33645078 | AB53: =(P53*(1-I53)+R53-AF53)*$B$1-J53-U53-V53 -> 1409.7069 | AC53: =AB53/T53/$B$1 -> 0.16576246 | AD53: =AB53/J53 -> 0.56843021 | AE53: =P53*(1-I53)*(1+'参数表'!$C$6)*(W53+X53+H53)*1.1+0.4*1.1 -> 10.559169 | AF53: =(P53*(1-I53)*1.1+R53)*(W53+X53+H53)*1.1+0.4*1.1 -> 13.909874
A54: https://www.amazon.co.jp/dp/B0G7RVNVWL?tag=webspire_new-22&linkCode=osi&th=1 | C54: 01-2601-0124 | D54: 是 | G54: 0786354046733 | H54: 0.05 | I54: 0 | J54: 4280 | K54: 310 | L54: 27 | M54: 9 | N54: 2 | O54: =max(L54*M54*N54/8000*1000,K54) -> 310 | P54: 63.8 | Q54: {=XLOOKUP(K54/1000, '运费（邮政）'!$A$2:$A$21, '运费（邮政）'!$B$2:$B$21, "超出范围", 1)} -> 1420 | R54: 18.99 | S54: =(V54+U54-Q54)/$B$1 -> 10.619614 | T54: =P54+R54 -> 82.79 | U54: {=XLOOKUP(O54/1000, '运费（橙联）'!$A$2:$A$57, '运费（橙联）'!$B$2:$B$57, "超出范围", 1)} -> 1778 | V54: =(P54*'参数表'!$C$2*(1+'参数表'!$C$3))*$B$1+'参数表'!$C$4 -> 1149.9852 | W54: 0.127 | X54: 0.0135 | Y54: =(P54*(1-I54)-AE54)*$B$1-J54-Q54 -> 1208.8369 | Z54: =Y54/P54/$B$1 -> 0.1334316 | AA54: =Y54/J54 -> 0.28243853 | AB54: =(P54*(1-I54)+R54-AF54)*$B$1-J54-U54-V54 -> 1832.3634 | AC54: =AB54/T54/$B$1 -> 0.15586384 | AD54: =AB54/J54 -> 0.42812229 | AE54: =P54*(1-I54)*(1+'参数表'!$C$6)*(W54+X54+H54)*1.1+0.4*1.1 -> 15.146219 | AF54: =(P54*(1-I54)*1.1+R54)*(W54+X54+H54)*1.1+0.4*1.1 -> 19.125574
A55: https://www.amazon.co.jp/%E3%80%902026%E4%BA%BA%E6%B0%97%E5%BA%AD%E5%B8%AB%E6%8E%A8%E8%96%A6%E3%80%91%E5%89%AA%E5%AE%9A%E3%83%90%E3%82%B5%E3%83%9F-Pycuse-2%E6%AE%B5%E9%9A%8E%E8%AA%BF%E7%AF%80%E5%8F%AF%E8%83%BD-SK85%E9%AB%98%E7%82%AD%E7%B4%A0%E9%8B%BC-%E8%BB%BD%E9%87%8F%E5%8C%96%E3%82%A2%E3%83%AB%E3%83%9F%E3%83%8F%E3%83%B3%E3%83%89%E3%83%AB/dp/B0FV8Q36L4/ref=zg_bs_g_392701011_d_sccl_4/357-9393567-9939435?th=1 | C55: 01-2601-0125 | D55: 是 | G55: 0755589786646 | H55: 0.05 | I55: 0 | J55: 3999 | K55: 380 | L55: 22 | M55: 6 | N55: 0.1 | O55: =max(L55*M55*N55/8000*1000,K55) -> 380 | P55: 59.6 | Q55: {=XLOOKUP(K55/1000, '运费（邮政）'!$A$2:$A$21, '运费（邮政）'!$B$2:$B$21, "超出范围", 1)} -> 1420 | R55: 18.99 | S55: =(V55+U55-Q55)/$B$1 -> 10.190794 | T55: =P55+R55 -> 78.59 | U55: {=XLOOKUP(O55/1000, '运费（橙联）'!$A$2:$A$57, '运费（橙联）'!$B$2:$B$57, "超出范围", 1)} -> 1778 | V55: =(P55*'参数表'!$C$2*(1+'参数表'!$C$3))*$B$1+'参数表'!$C$4 -> 1089.0927 | W55: 0.127 | X55: 0.0135 | Y55: =(P55*(1-I55)-AE55)*$B$1-J55-Q55 -> 1030.9101 | Z55: =Y55/P55/$B$1 -> 0.12181091 | AA55: =Y55/J55 -> 0.25779197 | AB55: =(P55*(1-I55)+R55-AF55)*$B$1-J55-U55-V55 -> 1715.329 | AC55: =AB55/T55/$B$1 -> 0.15370635 | AD55: =AB55/J55 -> 0.42893949 | AE55: =P55*(1-I55)*(1+'参数表'!$C$6)*(W55+X55+H55)*1.1+0.4*1.1 -> 14.178098 | AF55: =(P55*(1-I55)*1.1+R55)*(W55+X55+H55)*1.1+0.4*1.1 -> 18.157453
A56: https://www.amazon.co.jp/Garage-Brand-Product-GBP-065-%EF%BC%88%E5%A5%B3%E6%80%A7%E5%B0%82%E7%94%A8%EF%BC%89%E3%80%90%E6%A4%8D%E7%89%A9%E8%82%B2%E6%88%90%E3%81%AE%E3%83%97%E3%83%ADW%E7%9B%A3%E4%BF%AE%E3%80%91%E6%8F%A1%E3%82%8A%E3%82%84%E3%81%99%E3%81%8F%E8%BB%BD%E9%87%8F%E3%81%AA%E3%82%BF%E3%82%A4%E3%83%97%EF%BD%98%E3%82%B5%E3%82%AF%E3%82%B5%E3%82%AF%E5%88%87%E3%82%8C%E3%81%BE%E3%81%99%EF%BC%BBGarageBrandProduct%EF%BC%BD/dp/B0DM8NDFLN/ref=zg_bs_g_392701011_d_sccl_5/357-9393567-9939435?psc=1 | C56: 01-2601-0126 | D56: 是 | G56: 4570109807528 | H56: 0.05 | I56: 0 | J56: 999 | K56: 180 | L56: 25 | M56: 8 | N56: 2 | O56: =max(L56*M56*N56/8000*1000,K56) -> 180 | P56: 23.8 | Q56: {=XLOOKUP(K56/1000, '运费（邮政）'!$A$2:$A$21, '运费（邮政）'!$B$2:$B$21, "超出范围", 1)} -> 1060 | R56: 9.99 | S56: =(V56+U56-Q56)/$B$1 -> 6.1764589 | T56: =P56+R56 -> 33.79 | U56: {=XLOOKUP(O56/1000, '运费（橙联）'!$A$2:$A$57, '运费（橙联）'!$B$2:$B$57, "超出范围", 1)} -> 1367 | V56: =(P56*'参数表'!$C$2*(1+'参数表'!$C$3))*$B$1+'参数表'!$C$4 -> 570.05716 | W56: 0.127 | X56: 0.0135 | Y56: =(P56*(1-I56)-AE56)*$B$1-J56-Q56 -> 479.1053 | Z56: =Y56/P56/$B$1 -> 0.14176391 | AA56: =Y56/J56 -> 0.47958489 | AB56: =(P56*(1-I56)+R56-AF56)*$B$1-J56-U56-V56 -> 723.3647 | AC56: =AB56/T56/$B$1 -> 0.15075814 | AD56: =AB56/J56 -> 0.72408879 | AE56: =P56*(1-I56)*(1+'参数表'!$C$6)*(W56+X56+H56)*1.1+0.4*1.1 -> 5.926019 | AF56: =(P56*(1-I56)*1.1+R56)*(W56+X56+H56)*1.1+0.4*1.1 -> 8.0194235
A57: https://www.amazon.co.jp/SOLODOTO-%E8%BB%BD%E9%87%8F%EF%BC%86%E6%8F%A1%E3%82%8A%E3%82%84%E3%81%99%E3%81%84-%E5%88%87%E3%82%8C%E5%91%B35%E5%80%8D%EF%BD%9C%E6%97%A5%E6%9C%AC%E8%A3%BDSK-5%E9%8B%BC%EF%BC%8C%E8%80%90%E4%B9%85%E6%80%A76%E5%80%8D%EF%BD%9C%E9%8C%86%E3%81%B3%E3%81%AB%E3%81%8F%E3%81%84%EF%BD%9C%E7%96%B2%E3%82%8C%E3%81%AB%E3%81%8F%E3%81%84%E4%BA%BA%E9%96%93%E5%B7%A5%E5%AD%A6%E3%82%A2%E3%83%AB%E3%83%9F%E5%90%88%E9%87%91%E3%82%B0%E3%83%AA%E3%83%83%E3%83%97%EF%BD%9C%E6%9E%9D%E5%88%87%E3%82%8A%E3%83%90%E3%82%B5%E3%83%9F-%E3%81%88%E3%81%A0%E3%81%8D%E3%82%8A%E3%81%B0%E3%81%95%E3%81%BF%EF%BD%9C%E3%82%AE%E3%83%95%E3%83%88%E3%81%AB%E3%82%82-%E4%BA%BA%E6%B0%97%EF%BD%9C2025%E4%BA%BA%E6%B0%97%E5%BA%AD%E5%B8%AB%E3%81%8A%E3%81%99%E3%81%99%E3%82%81%E3%81%AE%E5%89%AA%E5%AE%9A%E3%83%90%E3%82%B5%E3%83%9F/dp/B0FJ8GK33G/ref=zg_bs_g_392701011_d_sccl_6/357-9393567-9939435?psc=1 | C57: 01-2601-0127 | D57: 是 | H57: 0.05 | I57: 0 | J57: 3999 | K57: 280 | L57: 34 | M57: 24 | N57: 2 | O57: =max(L57*M57*N57/8000*1000,K57) -> 280 | P57: 59.8 | Q57: {=XLOOKUP(K57/1000, '运费（邮政）'!$A$2:$A$21, '运费（邮政）'!$B$2:$B$21, "超出范围", 1)} -> 1240 | R57: 18.99 | S57: =(V57+U57-Q57)/$B$1 -> 10.091495 | T57: =P57+R57 -> 78.79 | U57: {=XLOOKUP(O57/1000, '运费（橙联）'!$A$2:$A$57, '运费（橙联）'!$B$2:$B$57, "超出范围", 1)} -> 1581 | V57: =(P57*'参数表'!$C$2*(1+'参数表'!$C$3))*$B$1+'参数表'!$C$4 -> 1091.9924 | W57: 0.127 | X57: 0.0135 | Y57: =(P57*(1-I57)-AE57)*$B$1-J57-Q57 -> 1232.7637 | Z57: =Y57/P57/$B$1 -> 0.14517449 | AA57: =Y57/J57 -> 0.308268 | AB57: =(P57*(1-I57)+R57-AF57)*$B$1-J57-U57-V57 -> 1931.283 | AC57: =AB57/T57/$B$1 -> 0.17261816 | AD57: =AB57/J57 -> 0.4829415 | AE57: =P57*(1-I57)*(1+'参数表'!$C$6)*(W57+X57+H57)*1.1+0.4*1.1 -> 14.224199 | AF57: =(P57*(1-I57)*1.1+R57)*(W57+X57+H57)*1.1+0.4*1.1 -> 18.203554
A58: https://www.amazon.co.jp/LIVINGO-253mm%E3%82%B9%E3%83%88%E3%83%AD%E3%83%B3%E3%82%B0%E4%B8%87%E8%83%BD%E3%81%AF%E3%81%95%E3%81%BF-%E3%83%81%E3%82%BF%E3%83%B3%E3%82%B3%E3%83%BC%E3%83%86%E3%82%A3%E3%83%B3%E3%82%B0-%E3%82%B9%E3%83%86%E3%83%B3%E3%83%AC%E3%82%B9%E9%8B%BC%E8%A3%BD-%E5%A4%9A%E7%9B%AE%E7%9A%84%E5%88%87%E6%96%AD%E5%B7%A5%E5%85%B7/dp/B088B8JZ6P/ref=zg_bs_g_392701011_d_sccl_7/357-9393567-9939435?th=1 | C58: 01-2601-0128 | D58: 是 | G58: 0721968264609 | H58: 0.05 | I58: 0 | J58: 3999 | K58: 310 | L58: 26 | M58: 9.5 | N58: 2 | O58: =max(L58*M58*N58/8000*1000,K58) -> 310 | P58: 59.8 | Q58: {=XLOOKUP(K58/1000, '运费（邮政）'!$A$2:$A$21, '运费（邮政）'!$B$2:$B$21, "超出范围", 1)} -> 1420 | R58: 18.99 | S58: =(V58+U58-Q58)/$B$1 -> 10.211214 | T58: =P58+R58 -> 78.79 | U58: {=XLOOKUP(O58/1000, '运费（橙联）'!$A$2:$A$57, '运费（橙联）'!$B$2:$B$57, "超出范围", 1)} -> 1778 | V58: =(P58*'参数表'!$C$2*(1+'参数表'!$C$3))*$B$1+'参数表'!$C$4 -> 1091.9924 | W58: 0.127 | X58: 0.0135 | Y58: =(P58*(1-I58)-AE58)*$B$1-J58-Q58 -> 1052.7637 | Z58: =Y58/P58/$B$1 -> 0.12397708 | AA58: =Y58/J58 -> 0.26325675 | AB58: =(P58*(1-I58)+R58-AF58)*$B$1-J58-U58-V58 -> 1734.283 | AC58: =AB58/T58/$B$1 -> 0.15501029 | AD58: =AB58/J58 -> 0.43367918 | AE58: =P58*(1-I58)*(1+'参数表'!$C$6)*(W58+X58+H58)*1.1+0.4*1.1 -> 14.224199 | AF58: =(P58*(1-I58)*1.1+R58)*(W58+X58+H58)*1.1+0.4*1.1 -> 18.203554
A59: https://www.amazon.co.jp/gp/aw/d/B0FKB9SV87/?_encoding=UTF8&pd_rd_plhdr=t&aaxitk=fb499e8e7fc29ab4b05a48bc30d23c4d&hsa_cr_id=4980547050603&qid=1768886676&sr=1-2-ac08f2b1-eb5b-4f1a-aa64-9e8f448c33ed&ref_=sbx_s_sparkle_sbtcd_asin_1_img&pd_rd_w=ZTaL0&content-id=amzn1.sym.f0facdbd-e6c4-4c86-85ba-0b3f009056ed%3Aamzn1.sym.f0facdbd-e6c4-4c86-85ba-0b3f009056ed&pf_rd_p=f0facdbd-e6c4-4c86-85ba-0b3f009056ed&pf_rd_r=G5JY8AEZPEGVY61K6ZBN&pd_rd_wg=uBeh3&pd_rd_r=8420df48-752f-413a-a5b3-dfedafaa66b0&th=1 | C59: 01-2601-0129 | F59: 大件 | G59: 4905040159489 | H59: 0.05 | I59: 0 | J59: 8980 | K59: 4500 | L59: 49 | M59: 40 | N59: 23 | O59: =max(L59*M59*N59/8000*1000,K59) -> 5635 | P59: 115 | Q59: {=XLOOKUP(K59/1000, '运费（邮政）'!$A$2:$A$21, '运费（邮政）'!$B$2:$B$21, "超出范围", 1)} -> 超出范围 | S59: =(V59+U59-Q59)/$B$1 -> #VALUE! | T59: =P59+R59 -> 115 | U59: {=XLOOKUP(O59/1000, '运费（橙联）'!$A$2:$A$57, '运费（橙联）'!$B$2:$B$57, "超出范围", 1)} -> 7512 | V59: =(P59*'参数表'!$C$2*(1+'参数表'!$C$3))*$B$1+'参数表'!$C$4 -> 1892.293 | W59: 0.127 | X59: 0.0135 | Y59: =(P59*(1-I59)-AE59)*$B$1-J59-Q59 -> #VALUE! | Z59: =Y59/P59/$B$1 -> #VALUE! | AA59: =Y59/J59 -> #VALUE! | AB59: =(P59*(1-I59)+R59-AF59)*$B$1-J59-U59-V59 -> -5880.9196 | AC59: =AB59/T59/$B$1 -> -0.3601298 | AD59: =AB59/J59 -> -0.65489083 | AE59: =P59*(1-I59)*(1+'参数表'!$C$6)*(W59+X59+H59)*1.1+0.4*1.1 -> 26.948075 | AF59: =(P59*(1-I59)*1.1+R59)*(W59+X59+H59)*1.1+0.4*1.1 -> 26.948075
A60: https://www.amazon.co.jp/%E5%8D%83%E5%90%89-Senkichi-SGP-22R-%E3%83%A9%E3%83%81%E3%82%A7%E3%83%83%E3%83%88%E5%BC%8F-%E5%89%AA%E5%AE%9A%E9%8B%8F/dp/B003UYTDGA/ref=zg_bs_g_392701011_d_sccl_11/357-9393567-9939435?th=1 | C60: 01-2601-0130 | D60: 是 | G60: 4977292628037 | H60: 0.05 | I60: 0 | J60: 1300 | K60: 310 | L60: 26 | M60: 10 | N60: 1.2 | O60: =max(L60*M60*N60/8000*1000,K60) -> 310 | P60: 28.8 | Q60: {=XLOOKUP(K60/1000, '运费（邮政）'!$A$2:$A$21, '运费（邮政）'!$B$2:$B$21, "超出范围", 1)} -> 1420 | R60: 12.99 | S60: =(V60+U60-Q60)/$B$1 -> 7.0461138 | T60: =P60+R60 -> 41.79 | U60: {=XLOOKUP(O60/1000, '运费（橙联）'!$A$2:$A$57, '运费（橙联）'!$B$2:$B$57, "超出范围", 1)} -> 1778 | V60: =(P60*'参数表'!$C$2*(1+'参数表'!$C$3))*$B$1+'参数表'!$C$4 -> 642.54816 | W60: 0.127 | X60: 0.0135 | Y60: =(P60*(1-I60)-AE60)*$B$1-J60-Q60 -> 364.44675 | Z60: =Y60/P60/$B$1 -> 0.089115501 | AA60: =Y60/J60 -> 0.28034366 | AB60: =(P60*(1-I60)+R60-AF60)*$B$1-J60-U60-V60 -> 821.94685 | AC60: =AB60/T60/$B$1 -> 0.1385106 | AD60: =AB60/J60 -> 0.63226681 | AE60: =P60*(1-I60)*(1+'参数表'!$C$6)*(W60+X60+H60)*1.1+0.4*1.1 -> 7.078544 | AF60: =(P60*(1-I60)*1.1+R60)*(W60+X60+H60)*1.1+0.4*1.1 -> 9.8005985
A61: https://www.amazon.co.jp/%E5%B2%A1%E6%81%92-%E5%89%AA%E5%AE%9A%E9%8B%8F%E3%83%A6%E3%83%8B%E3%83%BC%E3%82%AF-210mm-%E3%83%96%E3%83%AA%E3%82%B9%E3%82%BF%E3%83%BC%E5%85%A5-No-104/dp/B004JKKOZI/ref=zg_bs_g_392701011_d_sccl_17/357-9393567-9939435?th=1 | C61: 01-2601-0131 | D61: 是 | G61: 4968779104014 | H61: 0.05 | I61: 0 | J61: 2973 | K61: 310 | L61: 27 | M61: 8 | N61: 2.5 | O61: =max(L61*M61*N61/8000*1000,K61) -> 310 | P61: 47.8 | Q61: {=XLOOKUP(K61/1000, '运费（邮政）'!$A$2:$A$21, '运费（邮政）'!$B$2:$B$21, "超出范围", 1)} -> 1420 | R61: 15.99 | S61: =(V61+U61-Q61)/$B$1 -> 8.9860138 | T61: =P61+R61 -> 63.79 | U61: {=XLOOKUP(O61/1000, '运费（橙联）'!$A$2:$A$57, '运费（橙联）'!$B$2:$B$57, "超出范围", 1)} -> 1778 | V61: =(P61*'参数表'!$C$2*(1+'参数表'!$C$3))*$B$1+'参数表'!$C$4 -> 918.01396 | W61: 0.127 | X61: 0.0135 | Y61: =(P61*(1-I61)-AE61)*$B$1-J61-Q61 -> 767.54426 | Z61: =Y61/P61/$B$1 -> 0.11308036 | AA61: =Y61/J61 -> 0.25817163 | AB61: =(P61*(1-I61)+R61-AF61)*$B$1-J61-U61-V61 -> 1286.3103 | AC61: =AB61/T61/$B$1 -> 0.14200538 | AD61: =AB61/J61 -> 0.43266406 | AE61: =P61*(1-I61)*(1+'参数表'!$C$6)*(W61+X61+H61)*1.1+0.4*1.1 -> 11.458139 | AF61: =(P61*(1-I61)*1.1+R61)*(W61+X61+H61)*1.1+0.4*1.1 -> 14.808844
A62: https://www.amazon.co.jp/%E3%82%B5%E3%83%9C%E3%83%86%E3%83%B3-%E3%81%B6%E3%81%A9%E3%81%86%E7%94%A8-%E7%99%BA%E8%8A%BD%E4%BF%83%E9%80%B2-MEBUKI-No-B-11/dp/B01ART0FJ4/ref=zg_bs_g_392701011_d_sccl_18/357-9393567-9939435?psc=1 | C62: 01-2601-0132 | D62: 是 | G62: 4976365200934 | H62: 0.05 | I62: 0 | J62: 1630 | K62: 210 | L62: 18 | M62: 2.5 | N62: 5 | O62: =max(L62*M62*N62/8000*1000,K62) -> 210 | P62: 30.2 | Q62: {=XLOOKUP(K62/1000, '运费（邮政）'!$A$2:$A$21, '运费（邮政）'!$B$2:$B$21, "超出范围", 1)} -> 1240 | R62: 12.99 | S62: =(V62+U62-Q62)/$B$1 -> 7.0693355 | T62: =P62+R62 -> 43.19 | U62: {=XLOOKUP(O62/1000, '运费（橙联）'!$A$2:$A$57, '运费（橙联）'!$B$2:$B$57, "超出范围", 1)} -> 1581 | V62: =(P62*'参数表'!$C$2*(1+'参数表'!$C$3))*$B$1+'参数表'!$C$4 -> 662.84564 | W62: 0.127 | X62: 0.0135 | Y62: =(P62*(1-I62)-AE62)*$B$1-J62-Q62 -> 367.42236 | Z62: =Y62/P62/$B$1 -> 0.085678192 | AA62: =Y62/J62 -> 0.22541249 | AB62: =(P62*(1-I62)+R62-AF62)*$B$1-J62-U62-V62 -> 821.62498 | AC62: =AB62/T62/$B$1 -> 0.13396831 | AD62: =AB62/J62 -> 0.5040644 | AE62: =P62*(1-I62)*(1+'参数表'!$C$6)*(W62+X62+H62)*1.1+0.4*1.1 -> 7.401251 | AF62: =(P62*(1-I62)*1.1+R62)*(W62+X62+H62)*1.1+0.4*1.1 -> 10.123306
A63: https://www.amazon.co.jp/WORKPRO-%E5%89%AA%E5%AE%9A%E3%81%B0%E3%81%95%E3%81%BF-%E5%9C%92%E8%8A%B8%E3%81%B0%E3%81%95%E3%81%BF-%E3%82%B5%E3%82%AF%E3%82%B5%E3%82%AF%E5%88%87%E3%82%8C%E3%82%8B-%E5%AE%89%E5%85%A8%E3%83%AD%E3%83%83%E3%82%AF%E4%BB%98%E3%81%8D/dp/B09ST3DW4K/ref=zg_bs_g_392701011_d_sccl_20/357-9393567-9939435?th=1 | C63: 01-2601-0133 | D63: 是 | G63: 0820909775843 | H63: 0.05 | I63: 0 | J63: 1280 | K63: 180 | L63: 20 | M63: 5.6 | N63: 2.5 | O63: =max(L63*M63*N63/8000*1000,K63) -> 180 | P63: 26.8 | Q63: {=XLOOKUP(K63/1000, '运费（邮政）'!$A$2:$A$21, '运费（邮政）'!$B$2:$B$21, "超出范围", 1)} -> 1060 | R63: 9.99 | S63: =(V63+U63-Q63)/$B$1 -> 6.4827589 | T63: =P63+R63 -> 36.79 | U63: {=XLOOKUP(O63/1000, '运费（橙联）'!$A$2:$A$57, '运费（橙联）'!$B$2:$B$57, "超出范围", 1)} -> 1367 | V63: =(P63*'参数表'!$C$2*(1+'参数表'!$C$3))*$B$1+'参数表'!$C$4 -> 613.55176 | W63: 0.127 | X63: 0.0135 | Y63: =(P63*(1-I63)-AE63)*$B$1-J63-Q63 -> 525.91017 | Z63: =Y63/P63/$B$1 -> 0.13819376 | AA63: =Y63/J63 -> 0.41086732 | AB63: =(P63*(1-I63)+R63-AF63)*$B$1-J63-U63-V63 -> 726.67497 | AC63: =AB63/T63/$B$1 -> 0.13909838 | AD63: =AB63/J63 -> 0.56771482 | AE63: =P63*(1-I63)*(1+'参数表'!$C$6)*(W63+X63+H63)*1.1+0.4*1.1 -> 6.617534 | AF63: =(P63*(1-I63)*1.1+R63)*(W63+X63+H63)*1.1+0.4*1.1 -> 8.7109385
A64: https://www.amazon.co.jp/%E8%BF%91%E6%AD%A3-CHIKAMASA-B-500SLF-%E3%82%B9%E3%83%86%E3%83%B3%E3%83%AC%E3%82%B9%E3%83%95%E3%83%83%E7%B4%A0%E5%8A%A0%E5%B7%A5%E3%81%B6%E3%81%A9%E3%81%86%E6%89%8B%E5%85%A5%E3%82%8C%E9%8B%8FL%E5%9E%8B/dp/B00JSYLY1I/ref=zg_bs_g_392701011_d_sccl_41/357-9393567-9939435?th=1 | C64: 01-2601-0134 | D64: 是 | G64: 4967645013535 | H64: 0.05 | I64: 0 | J64: 1612 | K64: 110 | L64: 16 | M64: 8 | N64: 0.1 | O64: =max(L64*M64*N64/8000*1000,K64) -> 110 | P64: 29.8 | Q64: {=XLOOKUP(K64/1000, '运费（邮政）'!$A$2:$A$21, '运费（邮政）'!$B$2:$B$21, "超出范围", 1)} -> 1060 | R64: 12.99 | S64: =(V64+U64-Q64)/$B$1 -> 6.7890589 | T64: =P64+R64 -> 42.79 | U64: {=XLOOKUP(O64/1000, '运费（橙联）'!$A$2:$A$57, '运费（橙联）'!$B$2:$B$57, "超出范围", 1)} -> 1367 | V64: =(P64*'参数表'!$C$2*(1+'参数表'!$C$3))*$B$1+'参数表'!$C$4 -> 657.04636 | W64: 0.127 | X64: 0.0135 | Y64: =(P64*(1-I64)-AE64)*$B$1-J64-Q64 -> 521.71504 | Z64: =Y64/P64/$B$1 -> 0.12329025 | AA64: =Y64/J64 -> 0.32364457 | AB64: =(P64*(1-I64)+R64-AF64)*$B$1-J64-U64-V64 -> 1015.7169 | AC64: =AB64/T64/$B$1 -> 0.16716373 | AD64: =AB64/J64 -> 0.63009736 | AE64: =P64*(1-I64)*(1+'参数表'!$C$6)*(W64+X64+H64)*1.1+0.4*1.1 -> 7.309049 | AF64: =(P64*(1-I64)*1.1+R64)*(W64+X64+H64)*1.1+0.4*1.1 -> 10.031104
A65: https://www.amazon.co.jp/%E3%83%AA%E3%83%95%E3%82%A1-ReFa-%E3%82%B7%E3%83%A3%E3%83%B3%E3%83%97%E3%83%BC%E3%83%96%E3%83%A9%E3%82%B7%E3%83%9F%E3%83%AB%E3%82%AF-%E3%82%B7%E3%83%AB%E3%83%90%E3%83%BC/dp/B0DVSL5L19/ref=sr_1_18?crid=1C5IMS2RXPXZZ&dib=eyJ2IjoiMSJ9.bHLRuK1C6OSO_r1Ta4tDJEZEskCeUT4eF_-88bNvAo4k-PNxxIeeRMbp-t2D3jko_7_Lh9Aka0LlBxlXNkX4HQcljXYl-Xlm8FQaZE4QZSZNP6PlFUIoHrdQsm-9NfJIBSNYpQ-IziiRDKPBo-O51eJwO-091fuLA9x6ym33GIussQX4IcPLal-Giaw8DIT3V3zp78oDAMmEq5QjzcI9J08jnlXJRATXqwgrjJnJ8FSozIyyuwso420HwU-l3XPtnFZj4G2bbdYt123mrMkZv6PKhmZeSE5GkvVwxeXShkQ.-xO0vTCciwn2jVz6NRXlKnHGMYi6bkfoCMtlzwsDDIQ&dib_tag=se&keywords=refa&qid=1768889468&sprefix=refa%2Caps%2C238&sr=8-18&th=1 | C65: 01-2601-0135 | D65: 是 | G65: 4974011815792 | H65: 0.05 | I65: 0 | J65: 3300 | K65: 120 | L65: 23 | M65: 11 | N65: 10 | O65: =max(L65*M65*N65/8000*1000,K65) -> 316.25 | P65: 49.39 | Q65: {=XLOOKUP(K65/1000, '运费（邮政）'!$A$2:$A$21, '运费（邮政）'!$B$2:$B$21, "超出范围", 1)} -> 1060 | R65: 18 | S65: =(V65+U65-Q65)/$B$1 -> 11.683564 | T65: =P65+R65 -> 67.39 | U65: {=XLOOKUP(O65/1000, '运费（橙联）'!$A$2:$A$57, '运费（橙联）'!$B$2:$B$57, "超出范围", 1)} -> 1778 | V65: =(P65*'参数表'!$C$2*(1+'参数表'!$C$3))*$B$1+'参数表'!$C$4 -> 941.0661 | W65: 0.127 | X65: 0.0135 | Y65: =(P65*(1-I65)-AE65)*$B$1-J65-Q65 -> 974.28084 | Z65: =Y65/P65/$B$1 -> 0.13891745 | AA65: =Y65/J65 -> 0.29523662 | AB65: =(P65*(1-I65)+R65-AF65)*$B$1-J65-U65-V65 -> 1335.6049 | AC65: =AB65/T65/$B$1 -> 0.13957069 | AD65: =AB65/J65 -> 0.40472877 | AE65: =P65*(1-I65)*(1+'参数表'!$C$6)*(W65+X65+H65)*1.1+0.4*1.1 -> 11.824642 | AF65: =(P65*(1-I65)*1.1+R65)*(W65+X65+H65)*1.1+0.4*1.1 -> 15.596542
A66: https://www.amazon.co.jp/%E5%9D%82%E6%BA%90-%E3%83%8F%E3%83%B3%E3%83%89%E3%82%AF%E3%83%AA%E3%82%A8%E3%83%BC%E3%82%B7%E3%83%A7%E3%83%B3-%E5%8F%A4%E6%B5%81%E3%82%BF%E3%82%A4%E3%83%97-%E3%83%96%E3%83%AB%E3%83%BC-F-170/dp/B001C0CCYE/ref=zg_bs_g_392701011_d_sccl_42/357-9393567-9939435?th=1 | C66: 01-2601-0136 | D66: 是 | G66: 4900686703522 | H66: 0.05 | I66: 0 | J66: 3850 | K66: 280 | L66: 10 | M66: 9 | N66: 1 | O66: =max(L66*M66*N66/8000*1000,K66) -> 280 | P66: 58.9 | Q66: {=XLOOKUP(K66/1000, '运费（邮政）'!$A$2:$A$21, '运费（邮政）'!$B$2:$B$21, "超出范围", 1)} -> 1240 | R66: 18.99 | S66: =(V66+U66-Q66)/$B$1 -> 9.9996055 | T66: =P66+R66 -> 77.89 | U66: {=XLOOKUP(O66/1000, '运费（橙联）'!$A$2:$A$57, '运费（橙联）'!$B$2:$B$57, "超出范围", 1)} -> 1581 | V66: =(P66*'参数表'!$C$2*(1+'参数表'!$C$3))*$B$1+'参数表'!$C$4 -> 1078.944 | W66: 0.127 | X66: 0.0135 | Y66: =(P66*(1-I66)-AE66)*$B$1-J66-Q66 -> 1283.4223 | Z66: =Y66/P66/$B$1 -> 0.15344966 | AA66: =Y66/J66 -> 0.33335644 | AB66: =(P66*(1-I66)+R66-AF66)*$B$1-J66-U66-V66 -> 1994.99 | AC66: =AB66/T66/$B$1 -> 0.18037264 | AD66: =AB66/J66 -> 0.51817921 | AE66: =P66*(1-I66)*(1+'参数表'!$C$6)*(W66+X66+H66)*1.1+0.4*1.1 -> 14.016744 | AF66: =(P66*(1-I66)*1.1+R66)*(W66+X66+H66)*1.1+0.4*1.1 -> 17.996099
A67: https://www.amazon.co.jp/%E8%97%A4%E5%85%89-31077-%E6%B1%A0%E3%81%AE%E5%9D%8A%E9%8B%8F-165mm/dp/B00N3TXH96/ref=zg_bs_g_392701011_d_sccl_43/357-9393567-9939435?th=1 | C67: 01-2601-0137 | D67: 是 | G67: 4969968310773 | H67: 0.05 | I67: 0 | J67: 1254 | K67: 280 | L67: 16.5 | M67: 5 | N67: 2 | O67: =max(L67*M67*N67/8000*1000,K67) -> 280 | P67: 26.9 | Q67: {=XLOOKUP(K67/1000, '运费（邮政）'!$A$2:$A$21, '运费（邮政）'!$B$2:$B$21, "超出范围", 1)} -> 1240 | R67: 12.99 | S67: =(V67+U67-Q67)/$B$1 -> 6.7324055 | T67: =P67+R67 -> 39.89 | U67: {=XLOOKUP(O67/1000, '运费（橙联）'!$A$2:$A$57, '运费（橙联）'!$B$2:$B$57, "超出范围", 1)} -> 1581 | V67: =(P67*'参数表'!$C$2*(1+'参数表'!$C$3))*$B$1+'参数表'!$C$4 -> 615.00158 | W67: 0.127 | X67: 0.0135 | Y67: =(P67*(1-I67)-AE67)*$B$1-J67-Q67 -> 382.837 | Z67: =Y67/P67/$B$1 -> 0.10022436 | AA67: =Y67/J67 -> 0.30529266 | AB67: =(P67*(1-I67)+R67-AF67)*$B$1-J67-U67-V67 -> 884.88368 | AC67: =AB67/T67/$B$1 -> 0.15621898 | AD67: =AB67/J67 -> 0.70564887 | AE67: =P67*(1-I67)*(1+'参数表'!$C$6)*(W67+X67+H67)*1.1+0.4*1.1 -> 6.6405845 | AF67: =(P67*(1-I67)*1.1+R67)*(W67+X67+H67)*1.1+0.4*1.1 -> 9.362639
A68: https://www.amazon.co.jp/%E5%B2%A1%E6%81%92-Okatsune-No-108-%E5%89%AA%E5%AE%9A%E7%9A%AE%E3%82%B5%E3%83%83%E3%82%AF-1%E4%B8%81%E5%85%A5/dp/B003EII5ES/ref=zg_bs_g_392701011_d_sccl_44/357-9393567-9939435?th=1 | C68: 01-2601-0138 | D68: 是 | G68: 4968779108005 | H68: 0.05 | I68: 0 | J68: 1372 | K68: 110 | L68: 28 | M68: 10 | N68: 4 | O68: =max(L68*M68*N68/8000*1000,K68) -> 140 | P68: 26.8 | Q68: {=XLOOKUP(K68/1000, '运费（邮政）'!$A$2:$A$21, '运费（邮政）'!$B$2:$B$21, "超出范围", 1)} -> 1060 | R68: 9.99 | S68: =(V68+U68-Q68)/$B$1 -> 6.4827589 | T68: =P68+R68 -> 36.79 | U68: {=XLOOKUP(O68/1000, '运费（橙联）'!$A$2:$A$57, '运费（橙联）'!$B$2:$B$57, "超出范围", 1)} -> 1367 | V68: =(P68*'参数表'!$C$2*(1+'参数表'!$C$3))*$B$1+'参数表'!$C$4 -> 613.55176 | W68: 0.127 | X68: 0.0135 | Y68: =(P68*(1-I68)-AE68)*$B$1-J68-Q68 -> 433.91017 | Z68: =Y68/P68/$B$1 -> 0.11401886 | AA68: =Y68/J68 -> 0.31626106 | AB68: =(P68*(1-I68)+R68-AF68)*$B$1-J68-U68-V68 -> 634.67497 | AC68: =AB68/T68/$B$1 -> 0.12148796 | AD68: =AB68/J68 -> 0.46259109 | AE68: =P68*(1-I68)*(1+'参数表'!$C$6)*(W68+X68+H68)*1.1+0.4*1.1 -> 6.617534 | AF68: =(P68*(1-I68)*1.1+R68)*(W68+X68+H68)*1.1+0.4*1.1 -> 8.7109385
A69: https://www.amazon.co.jp/Iwatani-%E3%82%A4%E3%83%AF%E3%82%BF%E3%83%8B-CB-ABR-1-%E7%82%89%E3%81%B0%E3%81%9F%E7%84%BC%E5%99%A8-%E7%82%99%E3%82%8A%E3%82%84/dp/B01IGHIFV4/ref=pd_day0_d_sccl_2_3/355-3582507-3163057?pd_rd_w=1N3cy&content-id=amzn1.sym.3e742e38-2b5e-4207-a2c9-5d5409d6c433&pf_rd_p=3e742e38-2b5e-4207-a2c9-5d5409d6c433&pf_rd_r=WJTB1WKPDNHAT6S63YJ0&pd_rd_wg=7GjEU&pd_rd_r=247d2701-084b-46fb-beaa-f2493724c340&pd_rd_i=B01IGHIFV4&th=1 | C69: 01-2601-0139 | D69: 是 | G69: 4901140907999 | H69: 0.05 | I69: 0 | J69: 6980 | K69: 2750 | L69: 34 | M69: 24 | N69: 2 | O69: =max(L69*M69*N69/8000*1000,K69) -> 2750 | P69: 87.84 | Q69: {=XLOOKUP(K69/1000, '运费（邮政）'!$A$2:$A$21, '运费（邮政）'!$B$2:$B$21, "超出范围", 1)} -> 超出范围 | R69: 70 | S69: =(V69+U69-Q69)/$B$1 -> #VALUE! | T69: =P69+R69 -> 157.84 | U69: {=XLOOKUP(O69/1000, '运费（橙联）'!$A$2:$A$57, '运费（橙联）'!$B$2:$B$57, "超出范围", 1)} -> 4956 | V69: =(P69*'参数表'!$C$2*(1+'参数表'!$C$3))*$B$1+'参数表'!$C$4 -> 1498.5219 | W69: 0.127 | X69: 0.0135 | Y69: =(P69*(1-I69)-AE69)*$B$1-J69-Q69 -> #VALUE! | Z69: =Y69/P69/$B$1 -> #VALUE! | AA69: =Y69/J69 -> #VALUE! | AB69: =(P69*(1-I69)+R69-AF69)*$B$1-J69-U69-V69 -> 3958.1977 | AC69: =AB69/T69/$B$1 -> 0.17660056 | AD69: =AB69/J69 -> 0.56707704 | AE69: =P69*(1-I69)*(1+'参数表'!$C$6)*(W69+X69+H69)*1.1+0.4*1.1 -> 20.687559 | AF69: =(P69*(1-I69)*1.1+R69)*(W69+X69+H69)*1.1+0.4*1.1 -> 35.356059
A70: https://www.amazon.co.jp/%E4%BD%BF%E3%81%84%E3%82%84%E3%81%99MELEJIA-%E5%89%AA%E5%AE%9A%E9%8B%8F%E3%81%95%E3%81%B3%E3%81%AA%E3%81%84-%E3%82%B9%E3%83%86%E3%83%B3%E3%83%AC%E3%82%B9%E3%81%AF%E3%81%95%E3%81%BF-%E6%9E%9D%E5%88%87%E3%82%8A%E9%8B%8F%E3%83%BB%E7%94%9F%E3%81%91%E8%8A%B1%E3%83%BB%E5%89%AA%E5%AE%9A%E6%A4%8D%E7%89%A9%E3%83%BB%E9%89%A2%E6%A4%8D%E3%81%88%E3%83%BB%E6%9E%9C%E7%89%A9%E6%91%98%E3%81%BF-%E6%8F%A1%E3%82%8A%E3%82%84%E3%81%99%E3%81%84%E3%83%8F%E3%82%B5%E3%83%9F/dp/B0B2K39PWX/ref=zg_bs_g_392701011_d_sccl_46/357-9393567-9939435?th=1 | C70: 01-2601-0140 | D70: 是 | G70: 0700773259826 | H70: 0.05 | I70: 0 | J70: 1299 | K70: 150 | L70: 25 | M70: 8 | N70: 2 | O70: =max(L70*M70*N70/8000*1000,K70) -> 150 | P70: 26.9 | Q70: {=XLOOKUP(K70/1000, '运费（邮政）'!$A$2:$A$21, '运费（邮政）'!$B$2:$B$21, "超出范围", 1)} -> 1060 | R70: 9.99 | S70: =(V70+U70-Q70)/$B$1 -> 6.4929689 | T70: =P70+R70 -> 36.89 | U70: {=XLOOKUP(O70/1000, '运费（橙联）'!$A$2:$A$57, '运费（橙联）'!$B$2:$B$57, "超出范围", 1)} -> 1367 | V70: =(P70*'参数表'!$C$2*(1+'参数表'!$C$3))*$B$1+'参数表'!$C$4 -> 615.00158 | W70: 0.127 | X70: 0.0135 | Y70: =(P70*(1-I70)-AE70)*$B$1-J70-Q70 -> 517.837 | Z70: =Y70/P70/$B$1 -> 0.13556652 | AA70: =Y70/J70 -> 0.3986428 | AB70: =(P70*(1-I70)+R70-AF70)*$B$1-J70-U70-V70 -> 717.15198 | AC70: =AB70/T70/$B$1 -> 0.13690339 | AD70: =AB70/J70 -> 0.55208005 | AE70: =P70*(1-I70)*(1+'参数表'!$C$6)*(W70+X70+H70)*1.1+0.4*1.1 -> 6.6405845 | AF70: =(P70*(1-I70)*1.1+R70)*(W70+X70+H70)*1.1+0.4*1.1 -> 8.733989
A71: https://www.amazon.co.jp/%E9%AB%98%E5%84%80-GISUKE-%E3%83%87%E3%82%B6%E3%82%A4%E3%83%B3%E9%8B%8F-%E3%83%95%E3%83%83%E7%B4%A0%E3%82%B3%E3%83%BC%E3%83%86%E3%82%A3%E3%83%B3%E3%82%B0%E5%88%83-105mm/dp/B006JZDAZW/ref=zg_bs_g_392701011_d_sccl_47/357-9393567-9939435?th=1 | C71: 01-2601-0141 | D71: 是 | G71: 4907052442931 | H71: 0.05 | I71: 0 | J71: 1170 | K71: 80 | L71: 10 | M71: 5 | N71: 0.1 | O71: =max(L71*M71*N71/8000*1000,K71) -> 80 | P71: 23.8 | Q71: {=XLOOKUP(K71/1000, '运费（邮政）'!$A$2:$A$21, '运费（邮政）'!$B$2:$B$21, "超出范围", 1)} -> 880 | R71: 9.99 | S71: =(V71+U71-Q71)/$B$1 -> 6.458149 | T71: =P71+R71 -> 33.79 | U71: {=XLOOKUP(O71/1000, '运费（橙联）'!$A$2:$A$57, '运费（橙联）'!$B$2:$B$57, "超出范围", 1)} -> 1227 | V71: =(P71*'参数表'!$C$2*(1+'参数表'!$C$3))*$B$1+'参数表'!$C$4 -> 570.05716 | W71: 0.127 | X71: 0.0135 | Y71: =(P71*(1-I71)-AE71)*$B$1-J71-Q71 -> 488.1053 | Z71: =Y71/P71/$B$1 -> 0.14442694 | AA71: =Y71/J71 -> 0.41718402 | AB71: =(P71*(1-I71)+R71-AF71)*$B$1-J71-U71-V71 -> 692.3647 | AC71: =AB71/T71/$B$1 -> 0.14429736 | AD71: =AB71/J71 -> 0.5917647 | AE71: =P71*(1-I71)*(1+'参数表'!$C$6)*(W71+X71+H71)*1.1+0.4*1.1 -> 5.926019 | AF71: =(P71*(1-I71)*1.1+R71)*(W71+X71+H71)*1.1+0.4*1.1 -> 8.0194235
A72: https://www.amazon.co.jp/%E3%82%A2%E3%83%AB%E3%82%B9%E3%82%B3%E3%83%BC%E3%83%9D%E3%83%AC%E3%83%BC%E3%82%B7%E3%83%A7%E3%83%B3-V-8PRO-%E3%82%A2%E3%83%AB%E3%82%B9-%E9%AB%98%E7%B4%9A%E5%89%AA%E5%AE%9A%E9%8B%8F/dp/B00CFDW88W/ref=zg_bs_g_392701011_d_sccl_49/357-9393567-9939435?psc=1 | C72: 01-2601-0142 | D72: 是 | G72: 4965280679048 | H72: 0.05 | I72: 0 | J72: 4327 | K72: 210 | L72: 22 | M72: 11 | N72: 2 | O72: =max(L72*M72*N72/8000*1000,K72) -> 210 | P72: 64.8 | Q72: {=XLOOKUP(K72/1000, '运费（邮政）'!$A$2:$A$21, '运费（邮政）'!$B$2:$B$21, "超出范围", 1)} -> 1240 | R72: 15.99 | S72: =(V72+U72-Q72)/$B$1 -> 10.601995 | T72: =P72+R72 -> 80.79 | U72: {=XLOOKUP(O72/1000, '运费（橙联）'!$A$2:$A$57, '运费（橙联）'!$B$2:$B$57, "超出范围", 1)} -> 1581 | V72: =(P72*'参数表'!$C$2*(1+'参数表'!$C$3))*$B$1+'参数表'!$C$4 -> 1164.4834 | W72: 0.127 | X72: 0.0135 | Y72: =(P72*(1-I72)-AE72)*$B$1-J72-Q72 -> 1451.1052 | Z72: =Y72/P72/$B$1 -> 0.1577014 | AA72: =Y72/J72 -> 0.33536057 | AB72: =(P72*(1-I72)+R72-AF72)*$B$1-J72-U72-V72 -> 1740.4018 | AC72: =AB72/T72/$B$1 -> 0.15170628 | AD72: =AB72/J72 -> 0.40221904 | AE72: =P72*(1-I72)*(1+'参数表'!$C$6)*(W72+X72+H72)*1.1+0.4*1.1 -> 15.376724 | AF72: =(P72*(1-I72)*1.1+R72)*(W72+X72+H72)*1.1+0.4*1.1 -> 18.727428
A73: https://www.amazon.co.jp/LEATHER-VILLAGE-%E9%9D%A9%E8%A3%BD%E3%82%B8%E3%83%A3%E3%83%BC%E3%83%8A%E3%83%AB-%E3%83%A9%E3%82%B9%E3%83%86%E3%82%A3%E3%83%83%E3%82%AF%E3%83%96%E3%83%A9%E3%82%A6%E3%83%B3%E3%80%817%E3%82%A4%E3%83%B3%E3%83%81%C3%975%E3%82%A4%E3%83%B3%E3%83%81%E3%80%81220%E3%83%9A%E3%83%BC%E3%82%B8-%E3%83%B4%E3%82%A3%E3%83%B3%E3%83%86%E3%83%BC%E3%82%B8%E3%81%AA%E7%99%BD%E7%B4%99%E3%81%AE%E6%97%A5%E8%A8%98%E5%B8%B3%E3%80%82%E6%9B%B8%E3%81%8D%E8%BE%BC%E3%81%BF%E3%80%81%E6%8F%8F%E7%94%BB%E3%80%81%E3%82%B9%E3%82%B1%E3%83%83%E3%83%81%E3%83%96%E3%83%83%E3%82%AF%E3%80%81%E6%97%85%E8%A1%8C%E3%83%8E%E3%83%BC%E3%83%88%E3%81%AB%E6%9C%80%E9%81%A9/dp/B09D98HKXQ/ref=sxbs_pa_sp_search_thematic_btf_sspa?content-id=amzn1.sym.c9fc3167-1645-468c-a34c-ad5184b71e89%3Aamzn1.sym.c9fc3167-1645-468c-a34c-ad5184b71e89&crid=2M8AQG6WYEN55&cv_ct_cx=%E3%81%8A%E3%81%8A%E3%81%8D%E3%81%84%E3%81%BB%E3%81%BC%E6%97%A5%EF%BC%95%E5%B9%B4%E6%89%8B%E5%B8%B3%EF%BC%882026-2030%EF%BC%89&keywords=%E3%81%8A%E3%81%8A%E3%81%8D%E3%81%84%E3%81%BB%E3%81%BC%E6%97%A5%EF%BC%95%E5%B9%B4%E6%89%8B%E5%B8%B3%EF%BC%882026-2030%EF%BC%89&pd_rd_i=B09D98HKXQ&pd_rd_r=1741f6d9-6ef0-4cb4-88ec-f55eb7497408&pd_rd_w=YC2RG&pd_rd_wg=h5xsp&pf_rd_p=c9fc3167-1645-468c-a34c-ad5184b71e89&pf_rd_r=AP675FMF0W9GHTPN0SC5&qid=1768973329&sbo=RZvfv%2F%2FHxDF%2BO5021pAnSA%3D%3D&sprefix=%E3%81%8A%E3%81%8A%E3%81%8D%E3%81%84%E3%81%BB%E3%81%BC%E6%97%A55%E5%B9%B4%E6%89%8B%E5%B8%B3%2B2026-2030%2B%2Caps%2C468&sr=1-3-365a78ba-4fa9-4033-9d76-c706237ba9cd-spons&sp_csd=d2lkZ2V0TmFtZT1zcF9zZWFyY2hfdGhlbWF0aWNfYnRm&th=1 | C73: 01-2601-0143 | G73: 9559676539532 | H73: 0.05 | I73: 0 | J73: 2899 | K73: 372 | L73: 25 | M73: 20 | N73: 7 | O73: =max(L73*M73*N73/8000*1000,K73) -> 437.5 | P73: 49.39 | Q73: {=XLOOKUP(K73/1000, '运费（邮政）'!$A$2:$A$21, '运费（邮政）'!$B$2:$B$21, "超出范围", 1)} -> 1420 | R73: 21.99 | S73: =(V73+U73-Q73)/$B$1 -> 11.134268 | T73: =P73+R73 -> 71.38 | U73: {=XLOOKUP(O73/1000, '运费（橙联）'!$A$2:$A$57, '运费（橙联）'!$B$2:$B$57, "超出范围", 1)} -> 2060 | V73: =(P73*'参数表'!$C$2*(1+'参数表'!$C$3))*$B$1+'参数表'!$C$4 -> 941.0661 | W73: 0.127 | X73: 0.0135 | Y73: =(P73*(1-I73)-AE73)*$B$1-J73-Q73 -> 1015.2808 | Z73: =Y73/P73/$B$1 -> 0.14476342 | AA73: =Y73/J73 -> 0.35021761 | AB73: =(P73*(1-I73)+R73-AF73)*$B$1-J73-U73-V73 -> 1902.4581 | AC73: =AB73/T73/$B$1 -> 0.18769392 | AD73: =AB73/J73 -> 0.65624633 | AE73: =P73*(1-I73)*(1+'参数表'!$C$6)*(W73+X73+H73)*1.1+0.4*1.1 -> 11.824642 | AF73: =(P73*(1-I73)*1.1+R73)*(W73+X73+H73)*1.1+0.4*1.1 -> 16.432646
A74: https://www.amazon.co.jp/KAKURI-%E5%8F%8E%E7%B4%8D%E3%82%B1%E3%83%BC%E3%82%B9%E4%BB%98-%E5%B9%B3%E9%9D%A2%E3%82%92%E5%89%8A%E3%82%8B-%E3%83%9F%E3%83%8B%E3%82%AB%E3%83%B3%E3%83%8A-41650/dp/B0D5Q7V64H/ref=sr_1_18?__mk_ja_JP=%E3%82%AB%E3%82%BF%E3%82%AB%E3%83%8A&crid=TI3FUL4TJ9HN&dib=eyJ2IjoiMSJ9.oo7GBs5PmIZpIRaO1j2NG_Cm31fNIVC6wBEGu30TYUWKNuuxJ4FE1P8S6OQb-RR-rhIXwgrZQkCFAV152ILbK193mou2qmf0STZWvnIG95nBSlwlLTCWEVz4u6eraLdhi-VKGJWZafBsNqxoEPeAae-91LSL6e5FCZD3_Wcl4swGZNi4uYBt3qgzcxL9vn5TwoJ1C-JDg2U3yfKuJuLBR4_WIO0yA5os0gO1URLFmYK09Fshns5BRcesUGyEVcI_tRPvw8WcxbiLNPbKEbHHhzmnHPqdh1cZrUJRUCJqwKo.zoKFYMZUoRTO-YR4Q2C9Bd_bQFZhbXObkbOTsMB040U&dib_tag=se&keywords=%E8%A7%92%E5%88%A9&qid=1769043302&sprefix=%E8%A7%92%E5%88%A9%2Caps%2C319&sr=8-18&th=1 | C74: 01-2601-0144 | D74: 是 | G74: 4969402416504 | H74: 0.05 | I74: 0 | J74: 3175 | K74: 100 | L74: 16 | M74: 9 | N74: 8 | O74: =max(L74*M74*N74/8000*1000,K74) -> 144 | P74: 49.28 | Q74: {=XLOOKUP(K74/1000, '运费（邮政）'!$A$2:$A$21, '运费（邮政）'!$B$2:$B$21, "超出范围", 1)} -> 880 | R74: 15.99 | S74: =(V74+U74-Q74)/$B$1 -> 10.045573 | T74: =P74+R74 -> 65.27 | U74: {=XLOOKUP(O74/1000, '运费（橙联）'!$A$2:$A$57, '运费（橙联）'!$B$2:$B$57, "超出范围", 1)} -> 1367 | V74: =(P74*'参数表'!$C$2*(1+'参数表'!$C$3))*$B$1+'参数表'!$C$4 -> 939.4713 | W74: 0.127 | X74: 0.0135 | Y74: =(P74*(1-I74)-AE74)*$B$1-J74-Q74 -> 1267.2613 | Z74: =Y74/P74/$B$1 -> 0.18109528 | AA74: =Y74/J74 -> 0.39913743 | AB74: =(P74*(1-I74)+R74-AF74)*$B$1-J74-U74-V74 -> 1635.57 | AC74: =AB74/T74/$B$1 -> 0.17646849 | AD74: =AB74/J74 -> 0.51514016 | AE74: =P74*(1-I74)*(1+'参数表'!$C$6)*(W74+X74+H74)*1.1+0.4*1.1 -> 11.799286 | AF74: =(P74*(1-I74)*1.1+R74)*(W74+X74+H74)*1.1+0.4*1.1 -> 15.149991
A75: https://www.amazon.co.jp/KAKURI-%E5%8F%8E%E7%B4%8D%E3%82%B1%E3%83%BC%E3%82%B9%E4%BB%98-%E5%B9%B3%E9%9D%A2%E3%82%92%E5%89%8A%E3%82%8B-%E3%83%9F%E3%83%8B%E3%82%AB%E3%83%B3%E3%83%8A-41650/dp/B0D5QC1XX6/ref=sr_1_18?__mk_ja_JP=%E3%82%AB%E3%82%BF%E3%82%AB%E3%83%8A&crid=TI3FUL4TJ9HN&dib=eyJ2IjoiMSJ9.oo7GBs5PmIZpIRaO1j2NG_Cm31fNIVC6wBEGu30TYUWKNuuxJ4FE1P8S6OQb-RR-rhIXwgrZQkCFAV152ILbK193mou2qmf0STZWvnIG95nBSlwlLTCWEVz4u6eraLdhi-VKGJWZafBsNqxoEPeAae-91LSL6e5FCZD3_Wcl4swGZNi4uYBt3qgzcxL9vn5TwoJ1C-JDg2U3yfKuJuLBR4_WIO0yA5os0gO1URLFmYK09Fshns5BRcesUGyEVcI_tRPvw8WcxbiLNPbKEbHHhzmnHPqdh1cZrUJRUCJqwKo.zoKFYMZUoRTO-YR4Q2C9Bd_bQFZhbXObkbOTsMB040U&dib_tag=se&keywords=%E8%A7%92%E5%88%A9&qid=1769043302&sprefix=%E8%A7%92%E5%88%A9%2Caps%2C319&sr=8-18&th=1 | C75: 01-2601-0145 | D75: 重复 | H75: 0.05 | I75: 0 | L75: 34 | M75: 24 | N75: 2 | O75: =max(L75*M75*N75/8000*1000,K75) -> 204 | Q75: {=XLOOKUP(K75/1000, '运费（邮政）'!$A$2:$A$21, '运费（邮政）'!$B$2:$B$21, "超出范围", 1)} -> 880 | S75: =(V75+U75-Q75)/$B$1 -> 6.5211268 | T75: =P75+R75 -> 0 | U75: {=XLOOKUP(O75/1000, '运费（橙联）'!$A$2:$A$57, '运费（橙联）'!$B$2:$B$57, "超出范围", 1)} -> 1581 | V75: =(P75*'参数表'!$C$2*(1+'参数表'!$C$3))*$B$1+'参数表'!$C$4 -> 225 | W75: 0.127 | X75: 0.0135 | Y75: =(P75*(1-I75)-AE75)*$B$1-J75-Q75 -> -942.48 | Z75: =Y75/P75/$B$1 -> #DIV/0! | AA75: =Y75/J75 -> #DIV/0! | AB75: =(P75*(1-I75)+R75-AF75)*$B$1-J75-U75-V75 -> -1868.48 | AC75: =AB75/T75/$B$1 -> #DIV/0! | AD75: =AB75/J75 -> #DIV/0! | AE75: =P75*(1-I75)*(1+'参数表'!$C$6)*(W75+X75+H75)*1.1+0.4*1.1 -> 0.44 | AF75: =(P75*(1-I75)*1.1+R75)*(W75+X75+H75)*1.1+0.4*1.1 -> 0.44
A76: https://www.amazon.co.jp/KAKURI-%E5%8F%8E%E7%B4%8D%E3%82%B1%E3%83%BC%E3%82%B9%E4%BB%98-%E5%8F%B3%E6%96%9C%E5%88%833mm-%E5%8F%B3%E6%96%9C%E5%88%837mm-%E4%B8%89%E8%A7%92%E5%88%834mm/dp/B002TYZQT0/ref=sr_1_28?__mk_ja_JP=%E3%82%AB%E3%82%BF%E3%82%AB%E3%83%8A&crid=TI3FUL4TJ9HN&dib=eyJ2IjoiMSJ9.oo7GBs5PmIZpIRaO1j2NG_Cm31fNIVC6wBEGu30TYUWKNuuxJ4FE1P8S6OQb-RR-rhIXwgrZQkCFAV152ILbK193mou2qmf0STZWvnIG95nBSlwlLTCWEVz4u6eraLdhi-VKGJWZafBsNqxoEPeAae-91LSL6e5FCZD3_Wcl4swGZNi4uYBt3qgzcxL9vn5TwoJ1C-JDg2U3yfKuJuLBR4_WIO0yA5os0gO1URLFmYK09Fshns5BRcesUGyEVcI_tRPvw8WcxbiLNPbKEbHHhzmnHPqdh1cZrUJRUCJqwKo.zoKFYMZUoRTO-YR4Q2C9Bd_bQFZhbXObkbOTsMB040U&dib_tag=se&keywords=%E8%A7%92%E5%88%A9&qid=1769043302&sprefix=%E8%A7%92%E5%88%A9%2Caps%2C319&sr=8-28 | C76: 01-2601-0146 | D76: 是 | H76: 0.05 | I76: 0 | J76: 3314 | K76: 310 | L76: 34 | M76: 24 | N76: 2 | O76: =max(L76*M76*N76/8000*1000,K76) -> 310 | P76: 52.8 | Q76: {=XLOOKUP(K76/1000, '运费（邮政）'!$A$2:$A$21, '运费（邮政）'!$B$2:$B$21, "超出范围", 1)} -> 1420 | R76: 15.99 | S76: =(V76+U76-Q76)/$B$1 -> 9.4965138 | T76: =P76+R76 -> 68.79 | U76: {=XLOOKUP(O76/1000, '运费（橙联）'!$A$2:$A$57, '运费（橙联）'!$B$2:$B$57, "超出范围", 1)} -> 1778 | V76: =(P76*'参数表'!$C$2*(1+'参数表'!$C$3))*$B$1+'参数表'!$C$4 -> 990.50496 | W76: 0.127 | X76: 0.0135 | Y76: =(P76*(1-I76)-AE76)*$B$1-J76-Q76 -> 972.88571 | Z76: =Y76/P76/$B$1 -> 0.12975962 | AA76: =Y76/J76 -> 0.29356841 | AB76: =(P76*(1-I76)+R76-AF76)*$B$1-J76-U76-V76 -> 1419.1607 | AC76: =AB76/T76/$B$1 -> 0.14528405 | AD76: =AB76/J76 -> 0.42823196 | AE76: =P76*(1-I76)*(1+'参数表'!$C$6)*(W76+X76+H76)*1.1+0.4*1.1 -> 12.610664 | AF76: =(P76*(1-I76)*1.1+R76)*(W76+X76+H76)*1.1+0.4*1.1 -> 15.961369
A77: https://www.amazon.co.jp/%E9%AB%98%E5%84%80-%E3%82%BF%E3%82%AB%E3%82%AE-4907052121508-%E6%9C%A8%E5%B7%A5%E7%94%A8-3%E6%9C%AC%E7%B5%84/dp/B00G8PR66W/ref=zg_bs_g_2039562051_d_sccl_1/357-9393567-9939435?th=1 | C77: 01-2601-0147 | D77: 是 | G77: 4907052121508 | H77: 0.05 | I77: 0 | J77: 1114 | K77: 590 | L77: 31 | M77: 13 | N77: 3.5 | O77: =max(L77*M77*N77/8000*1000,K77) -> 590 | P77: 29.8 | Q77: {=XLOOKUP(K77/1000, '运费（邮政）'!$A$2:$A$21, '运费（邮政）'!$B$2:$B$21, "超出范围", 1)} -> 1780 | R77: 12.99 | S77: =(V77+U77-Q77)/$B$1 -> 7.7397631 | T77: =P77+R77 -> 42.79 | U77: {=XLOOKUP(O77/1000, '运费（橙联）'!$A$2:$A$57, '运费（橙联）'!$B$2:$B$57, "超出范围", 1)} -> 2222 | V77: =(P77*'参数表'!$C$2*(1+'参数表'!$C$3))*$B$1+'参数表'!$C$4 -> 657.04636 | W77: 0.127 | X77: 0.0135 | Y77: =(P77*(1-I77)-AE77)*$B$1-J77-Q77 -> 299.71504 | Z77: =Y77/P77/$B$1 -> 0.070827829 | AA77: =Y77/J77 -> 0.26904402 | AB77: =(P77*(1-I77)+R77-AF77)*$B$1-J77-U77-V77 -> 658.71694 | AC77: =AB77/T77/$B$1 -> 0.10840972 | AD77: =AB77/J77 -> 0.59130785 | AE77: =P77*(1-I77)*(1+'参数表'!$C$6)*(W77+X77+H77)*1.1+0.4*1.1 -> 7.309049 | AF77: =(P77*(1-I77)*1.1+R77)*(W77+X77+H77)*1.1+0.4*1.1 -> 10.031104
A78: https://www.amazon.co.jp/EZARC-%E5%88%87%E3%82%8C%E5%91%B3%E6%8A%9C%E7%BE%A4-%E8%BF%BD%E5%85%A5%E3%81%AE%E3%81%BF-%E3%83%97%E3%83%AD%E4%BB%95%E6%A7%98-%E3%83%96%E3%83%A9%E3%83%83%E3%82%AF%E3%82%AF%E3%83%AB%E3%83%9F/dp/B07HMWMZW1/ref=zg_bs_g_2039562051_d_sccl_2/357-9393567-9939435?th=1 | C78: 01-2601-0148 | D78: 是 | G78: 0611553064090 | H78: 0.05 | I78: 0 | J78: 5580 | K78: 1200 | L78: 29 | M78: 3.8 | N78: 23 | O78: =max(L78*M78*N78/8000*1000,K78) -> 1200 | P78: 89.2 | Q78: {=XLOOKUP(K78/1000, '运费（邮政）'!$A$2:$A$21, '运费（邮政）'!$B$2:$B$21, "超出范围", 1)} -> 2860 | R78: 24.99 | S78: =(V78+U78-Q78)/$B$1 -> 13.438306 | T78: =P78+R78 -> 114.19 | U78: {=XLOOKUP(O78/1000, '运费（橙联）'!$A$2:$A$57, '运费（橙联）'!$B$2:$B$57, "超出范围", 1)} -> 3250 | V78: =(P78*'参数表'!$C$2*(1+'参数表'!$C$3))*$B$1+'参数表'!$C$4 -> 1518.2394 | W78: 0.127 | X78: 0.0135 | Y78: =(P78*(1-I78)-AE78)*$B$1-J78-Q78 -> 1244.2515 | Z78: =Y78/P78/$B$1 -> 0.098232447 | AA78: =Y78/J78 -> 0.22298413 | AB78: =(P78*(1-I78)+R78-AF78)*$B$1-J78-U78-V78 -> 2140.9871 | AC78: =AB78/T78/$B$1 -> 0.1320376 | AD78: =AB78/J78 -> 0.38368944 | AE78: =P78*(1-I78)*(1+'参数表'!$C$6)*(W78+X78+H78)*1.1+0.4*1.1 -> 21.001046 | AF78: =(P78*(1-I78)*1.1+R78)*(W78+X78+H78)*1.1+0.4*1.1 -> 26.2377
A79: https://www.amazon.co.jp/%E6%9C%A8%E5%B7%A5%E5%B9%B3%E3%83%8E%E3%83%9F-4%E6%9C%AC%E3%82%BB%E3%83%83%E3%83%88-%E3%82%AF%E3%83%AD%E3%83%A0%E3%83%90%E3%83%8A%E3%82%B8%E3%82%A6%E3%83%A0%E9%8B%BC-%E3%81%AE%E3%81%BF%E3%82%BB%E3%83%83%E3%83%88-%E5%88%87%E3%82%8C%E5%91%B3%E6%8A%9C%E7%BE%A4/dp/B0DJ39635R/ref=zg_bs_g_2039562051_d_sccl_3/357-9393567-9939435?th=1 | C79: 01-2601-0149 | D79: 是 | H79: 0.05 | I79: 0 | J79: 2170 | K79: 510 | L79: 34 | M79: 24 | N79: 2 | O79: =max(L79*M79*N79/8000*1000,K79) -> 510 | P79: 42.8 | Q79: {=XLOOKUP(K79/1000, '运费（邮政）'!$A$2:$A$21, '运费（邮政）'!$B$2:$B$21, "超出范围", 1)} -> 1780 | R79: 15.99 | S79: =(V79+U79-Q79)/$B$1 -> 9.0670631 | T79: =P79+R79 -> 58.79 | U79: {=XLOOKUP(O79/1000, '运费（橙联）'!$A$2:$A$57, '运费（橙联）'!$B$2:$B$57, "超出范围", 1)} -> 2222 | V79: =(P79*'参数表'!$C$2*(1+'参数表'!$C$3))*$B$1+'参数表'!$C$4 -> 845.52296 | W79: 0.127 | X79: 0.0135 | Y79: =(P79*(1-I79)-AE79)*$B$1-J79-Q79 -> 664.20281 | Z79: =Y79/P79/$B$1 -> 0.10928702 | AA79: =Y79/J79 -> 0.30608425 | AB79: =(P79*(1-I79)+R79-AF79)*$B$1-J79-U79-V79 -> 1171.4598 | AC79: =AB79/T79/$B$1 -> 0.14032517 | AD79: =AB79/J79 -> 0.53984323 | AE79: =P79*(1-I79)*(1+'参数表'!$C$6)*(W79+X79+H79)*1.1+0.4*1.1 -> 10.305614 | AF79: =(P79*(1-I79)*1.1+R79)*(W79+X79+H79)*1.1+0.4*1.1 -> 13.656318
A80: https://www.amazon.co.jp/%E6%9C%A8%E5%B7%A5%E5%B9%B3%E3%83%8E%E3%83%9F-4%E6%9C%AC%E3%82%BB%E3%83%83%E3%83%88-%E3%82%AF%E3%83%AD%E3%83%A0%E3%83%90%E3%83%8A%E3%82%B8%E3%82%A6%E3%83%A0%E9%8B%BC-%E3%81%AE%E3%81%BF%E3%82%BB%E3%83%83%E3%83%88-%E5%88%87%E3%82%8C%E5%91%B3%E6%8A%9C%E7%BE%A4/dp/B0DJ3B9VKX/ref=zg_bs_g_2039562051_d_sccl_3/357-9393567-9939435?th=1 | C80: 01-2601-0150 | D80: 是 | H80: 0.05 | I80: 0 | J80: 2270 | K80: 510 | L80: 34 | M80: 24 | N80: 2 | O80: =max(L80*M80*N80/8000*1000,K80) -> 510 | P80: 43.8 | Q80: {=XLOOKUP(K80/1000, '运费（邮政）'!$A$2:$A$21, '运费（邮政）'!$B$2:$B$21, "超出范围", 1)} -> 1780 | R80: 15.99 | S80: =(V80+U80-Q80)/$B$1 -> 9.1691631 | T80: =P80+R80 -> 59.79 | U80: {=XLOOKUP(O80/1000, '运费（橙联）'!$A$2:$A$57, '运费（橙联）'!$B$2:$B$57, "超出范围", 1)} -> 2222 | V80: =(P80*'参数表'!$C$2*(1+'参数表'!$C$3))*$B$1+'参数表'!$C$4 -> 860.02116 | W80: 0.127 | X80: 0.0135 | Y80: =(P80*(1-I80)-AE80)*$B$1-J80-Q80 -> 673.4711 | Z80: =Y80/P80/$B$1 -> 0.10828206 | AA80: =Y80/J80 -> 0.2966833 | AB80: =(P80*(1-I80)+R80-AF80)*$B$1-J80-U80-V80 -> 1166.2299 | AC80: =AB80/T80/$B$1 -> 0.13736221 | AD80: =AB80/J80 -> 0.51375767 | AE80: =P80*(1-I80)*(1+'参数表'!$C$6)*(W80+X80+H80)*1.1+0.4*1.1 -> 10.536119 | AF80: =(P80*(1-I80)*1.1+R80)*(W80+X80+H80)*1.1+0.4*1.1 -> 13.886824
A81: https://www.amazon.co.jp/%E6%9C%A8%E5%B7%A5%E5%B9%B3%E3%83%8E%E3%83%9F-4%E6%9C%AC%E3%82%BB%E3%83%83%E3%83%88-%E3%82%AF%E3%83%AD%E3%83%A0%E3%83%90%E3%83%8A%E3%82%B8%E3%82%A6%E3%83%A0%E9%8B%BC-%E3%81%AE%E3%81%BF%E3%82%BB%E3%83%83%E3%83%88-%E5%88%87%E3%82%8C%E5%91%B3%E6%8A%9C%E7%BE%A4/dp/B0DJ3CCLWH/ref=zg_bs_g_2039562051_d_sccl_3/357-9393567-9939435?th=1 | C81: 01-2601-0151 | D81: 是 | H81: 0.05 | I81: 0 | J81: 2370 | K81: 610 | L81: 34 | M81: 24 | N81: 2 | O81: =max(L81*M81*N81/8000*1000,K81) -> 610 | P81: 45.8 | Q81: {=XLOOKUP(K81/1000, '运费（邮政）'!$A$2:$A$21, '运费（邮政）'!$B$2:$B$21, "超出范围", 1)} -> 1960 | R81: 15.99 | S81: =(V81+U81-Q81)/$B$1 -> 8.8029406 | T81: =P81+R81 -> 61.79 | U81: {=XLOOKUP(O81/1000, '运费（橙联）'!$A$2:$A$57, '运费（橙联）'!$B$2:$B$57, "超出范围", 1)} -> 2321 | V81: =(P81*'参数表'!$C$2*(1+'参数表'!$C$3))*$B$1+'参数表'!$C$4 -> 889.01756 | W81: 0.127 | X81: 0.0135 | Y81: =(P81*(1-I81)-AE81)*$B$1-J81-Q81 -> 612.00768 | Z81: =Y81/P81/$B$1 -> 0.094102909 | AA81: =Y81/J81 -> 0.25823109 | AB81: =(P81*(1-I81)+R81-AF81)*$B$1-J81-U81-V81 -> 1156.7701 | AC81: =AB81/T81/$B$1 -> 0.13183797 | AD81: =AB81/J81 -> 0.48808864 | AE81: =P81*(1-I81)*(1+'参数表'!$C$6)*(W81+X81+H81)*1.1+0.4*1.1 -> 10.997129 | AF81: =(P81*(1-I81)*1.1+R81)*(W81+X81+H81)*1.1+0.4*1.1 -> 14.347834
A82: https://www.amazon.co.jp/%E9%AB%98%E5%84%80-%E3%82%BF%E3%82%AB%E3%82%AE-4907052121508-%E6%9C%A8%E5%B7%A5%E7%94%A8-3%E6%9C%AC%E7%B5%84/dp/B00G8PR5GI/ref=zg_bs_g_2039562051_d_sccl_1/357-9393567-9939435?th=1 | C82: 01-2601-0152 | D82: 是 | G82: 4907052121515 | H82: 0.05 | I82: 0 | J82: 1416 | K82: 410 | L82: 34 | M82: 24 | N82: 2 | O82: =max(L82*M82*N82/8000*1000,K82) -> 410 | P82: 32.8 | Q82: {=XLOOKUP(K82/1000, '运费（邮政）'!$A$2:$A$21, '运费（邮政）'!$B$2:$B$21, "超出范围", 1)} -> 1600 | R82: 12.99 | S82: =(V82+U82-Q82)/$B$1 -> 8.1728237 | T82: =P82+R82 -> 45.79 | U82: {=XLOOKUP(O82/1000, '运费（橙联）'!$A$2:$A$57, '运费（橙联）'!$B$2:$B$57, "超出范围", 1)} -> 2060 | V82: =(P82*'参数表'!$C$2*(1+'参数表'!$C$3))*$B$1+'参数表'!$C$4 -> 700.54096 | W82: 0.127 | X82: 0.0135 | Y82: =(P82*(1-I82)-AE82)*$B$1-J82-Q82 -> 505.51991 | Z82: =Y82/P82/$B$1 -> 0.10853657 | AA82: =Y82/J82 -> 0.35700559 | AB82: =(P82*(1-I82)+R82-AF82)*$B$1-J82-U82-V82 -> 803.02721 | AC82: =AB82/T82/$B$1 -> 0.12350123 | AD82: =AB82/J82 -> 0.56710961 | AE82: =P82*(1-I82)*(1+'参数表'!$C$6)*(W82+X82+H82)*1.1+0.4*1.1 -> 8.000564 | AF82: =(P82*(1-I82)*1.1+R82)*(W82+X82+H82)*1.1+0.4*1.1 -> 10.722618
A83: https://www.amazon.co.jp/cocoriko-4%E6%9C%AC%E3%82%BB%E3%83%83%E3%83%88-%E3%82%AF%E3%83%AD%E3%83%A0%E3%83%90%E3%83%8A%E3%82%B8%E3%82%A6%E3%83%A0%E9%8B%BC-%E5%8F%8E%E7%B4%8D%E8%A2%8B%E4%BB%98%E3%81%8D-%E5%B9%B3%E3%83%8E%E3%83%9F4%E6%9C%AC%EF%BC%88%E4%B8%AD%E7%82%AD%E7%B4%A0%E9%8B%BC%EF%BC%89/dp/B0G6YM23QW/ref=zg_bs_g_2039562051_d_sccl_4/357-9393567-9939435?th=1 | C83: 01-2601-0153 | D83: 是 | G83: 4571623017332 | H83: 0.05 | I83: 0 | J83: 2180 | K83: 480 | L83: 34 | M83: 24 | N83: 2 | O83: =max(L83*M83*N83/8000*1000,K83) -> 480 | P83: 39.8 | Q83: {=XLOOKUP(K83/1000, '运费（邮政）'!$A$2:$A$21, '运费（邮政）'!$B$2:$B$21, "超出范围", 1)} -> 1600 | R83: 15.99 | S83: =(V83+U83-Q83)/$B$1 -> 8.8875237 | T83: =P83+R83 -> 55.79 | U83: {=XLOOKUP(O83/1000, '运费（橙联）'!$A$2:$A$57, '运费（橙联）'!$B$2:$B$57, "超出范围", 1)} -> 2060 | V83: =(P83*'参数表'!$C$2*(1+'参数表'!$C$3))*$B$1+'参数表'!$C$4 -> 802.02836 | W83: 0.127 | X83: 0.0135 | Y83: =(P83*(1-I83)-AE83)*$B$1-J83-Q83 -> 506.39794 | Z83: =Y83/P83/$B$1 -> 0.08960258 | AA83: =Y83/J83 -> 0.23229263 | AB83: =(P83*(1-I83)+R83-AF83)*$B$1-J83-U83-V83 -> 1039.1495 | AC83: =AB83/T83/$B$1 -> 0.13116965 | AD83: =AB83/J83 -> 0.4766741 | AE83: =P83*(1-I83)*(1+'参数表'!$C$6)*(W83+X83+H83)*1.1+0.4*1.1 -> 9.614099 | AF83: =(P83*(1-I83)*1.1+R83)*(W83+X83+H83)*1.1+0.4*1.1 -> 12.964804
A84: https://www.amazon.co.jp/cocoriko-4%E6%9C%AC%E3%82%BB%E3%83%83%E3%83%88-%E3%82%AF%E3%83%AD%E3%83%A0%E3%83%90%E3%83%8A%E3%82%B8%E3%82%A6%E3%83%A0%E9%8B%BC-%E5%8F%8E%E7%B4%8D%E8%A2%8B%E4%BB%98%E3%81%8D-%E5%B9%B3%E3%83%8E%E3%83%9F4%E6%9C%AC%EF%BC%88%E4%B8%AD%E7%82%AD%E7%B4%A0%E9%8B%BC%EF%BC%89/dp/B0G14DQF4J/ref=zg_bs_g_2039562051_d_sccl_4/357-9393567-9939435?th=1 | C84: 01-2601-0154 | D84: 是 | G84: 同上 | H84: 0.05 | I84: 0 | J84: 2180 | K84: 480 | L84: 34 | M84: 24 | N84: 2 | O84: =max(L84*M84*N84/8000*1000,K84) -> 480 | P84: 39.8 | Q84: {=XLOOKUP(K84/1000, '运费（邮政）'!$A$2:$A$21, '运费（邮政）'!$B$2:$B$21, "超出范围", 1)} -> 1600 | R84: 15.99 | S84: =(V84+U84-Q84)/$B$1 -> 8.8875237 | T84: =P84+R84 -> 55.79 | U84: {=XLOOKUP(O84/1000, '运费（橙联）'!$A$2:$A$57, '运费（橙联）'!$B$2:$B$57, "超出范围", 1)} -> 2060 | V84: =(P84*'参数表'!$C$2*(1+'参数表'!$C$3))*$B$1+'参数表'!$C$4 -> 802.02836 | W84: 0.127 | X84: 0.0135 | Y84: =(P84*(1-I84)-AE84)*$B$1-J84-Q84 -> 506.39794 | Z84: =Y84/P84/$B$1 -> 0.08960258 | AA84: =Y84/J84 -> 0.23229263 | AB84: =(P84*(1-I84)+R84-AF84)*$B$1-J84-U84-V84 -> 1039.1495 | AC84: =AB84/T84/$B$1 -> 0.13116965 | AD84: =AB84/J84 -> 0.4766741 | AE84: =P84*(1-I84)*(1+'参数表'!$C$6)*(W84+X84+H84)*1.1+0.4*1.1 -> 9.614099 | AF84: =(P84*(1-I84)*1.1+R84)*(W84+X84+H84)*1.1+0.4*1.1 -> 12.964804
A85: https://www.amazon.co.jp/cocoriko-4%E6%9C%AC%E3%82%BB%E3%83%83%E3%83%88-%E3%82%AF%E3%83%AD%E3%83%A0%E3%83%90%E3%83%8A%E3%82%B8%E3%82%A6%E3%83%A0%E9%8B%BC-%E5%8F%8E%E7%B4%8D%E8%A2%8B%E4%BB%98%E3%81%8D-%E5%B9%B3%E3%83%8E%E3%83%9F4%E6%9C%AC%EF%BC%88%E4%B8%AD%E7%82%AD%E7%B4%A0%E9%8B%BC%EF%BC%89/dp/B0G14DMHV9/ref=zg_bs_g_2039562051_d_sccl_4/357-9393567-9939435?th=1 | C85: 01-2601-0155 | D85: 是 | G85: 同上上 | H85: 0.05 | I85: 0 | J85: 1980 | K85: 480 | L85: 34 | M85: 24 | N85: 2 | O85: =max(L85*M85*N85/8000*1000,K85) -> 480 | P85: 39.8 | Q85: {=XLOOKUP(K85/1000, '运费（邮政）'!$A$2:$A$21, '运费（邮政）'!$B$2:$B$21, "超出范围", 1)} -> 1600 | R85: 15.99 | S85: =(V85+U85-Q85)/$B$1 -> 8.8875237 | T85: =P85+R85 -> 55.79 | U85: {=XLOOKUP(O85/1000, '运费（橙联）'!$A$2:$A$57, '运费（橙联）'!$B$2:$B$57, "超出范围", 1)} -> 2060 | V85: =(P85*'参数表'!$C$2*(1+'参数表'!$C$3))*$B$1+'参数表'!$C$4 -> 802.02836 | W85: 0.127 | X85: 0.0135 | Y85: =(P85*(1-I85)-AE85)*$B$1-J85-Q85 -> 706.39794 | Z85: =Y85/P85/$B$1 -> 0.12499079 | AA85: =Y85/J85 -> 0.35676664 | AB85: =(P85*(1-I85)+R85-AF85)*$B$1-J85-U85-V85 -> 1239.1495 | AC85: =AB85/T85/$B$1 -> 0.15641522 | AD85: =AB85/J85 -> 0.6258331 | AE85: =P85*(1-I85)*(1+'参数表'!$C$6)*(W85+X85+H85)*1.1+0.4*1.1 -> 9.614099 | AF85: =(P85*(1-I85)*1.1+R85)*(W85+X85+H85)*1.1+0.4*1.1 -> 12.964804
A86: https://www.amazon.co.jp/Amazon%E3%83%99%E3%83%BC%E3%82%B7%E3%83%83%E3%82%AF-Amazon-Basics-DS-CHAMZ004-%E7%B4%840-6-3-8cm/dp/B07V8X5W5R/ref=zg_bs_g_2039562051_d_sccl_5/357-9393567-9939435?th=1 | C86: 01-2601-0156 | G86: 0672352801606 | H86: 0.05 | I86: 0 | J86: 3636 | K86: 2450 | L86: 34 | M86: 24 | N86: 2 | O86: =max(L86*M86*N86/8000*1000,K86) -> 2450 | P86: 54.8 | Q86: {=XLOOKUP(K86/1000, '运费（邮政）'!$A$2:$A$21, '运费（邮政）'!$B$2:$B$21, "超出范围", 1)} -> 超出范围 | S86: =(V86+U86-Q86)/$B$1 -> #VALUE! | T86: =P86+R86 -> 54.8 | U86: {=XLOOKUP(O86/1000, '运费（橙联）'!$A$2:$A$57, '运费（橙联）'!$B$2:$B$57, "超出范围", 1)} -> 4736 | V86: =(P86*'参数表'!$C$2*(1+'参数表'!$C$3))*$B$1+'参数表'!$C$4 -> 1019.5014 | W86: 0.127 | X86: 0.0135 | Y86: =(P86*(1-I86)-AE86)*$B$1-J86-Q86 -> #VALUE! | Z86: =Y86/P86/$B$1 -> #VALUE! | AA86: =Y86/J86 -> #VALUE! | AB86: =(P86*(1-I86)+R86-AF86)*$B$1-J86-U86-V86 -> -3466.0791 | AC86: =AB86/T86/$B$1 -> -0.44541985 | AD86: =AB86/J86 -> -0.95326707 | AE86: =P86*(1-I86)*(1+'参数表'!$C$6)*(W86+X86+H86)*1.1+0.4*1.1 -> 13.071674 | AF86: =(P86*(1-I86)*1.1+R86)*(W86+X86+H86)*1.1+0.4*1.1 -> 13.071674
A87: https://www.amazon.co.jp/Gunpla-%E3%83%97%E3%83%AC%E3%83%9F%E3%82%A2%E3%83%A0%E6%9C%A8%E8%A3%BD%E5%BD%AB%E5%88%BB%E5%88%80%E3%82%BB%E3%83%83%E3%83%88-%E3%82%BD%E3%83%95%E3%83%88%E3%82%B0%E3%83%AA%E3%83%83%E3%83%97%E3%83%8F%E3%83%B3%E3%83%89%E3%83%AB-W%E3%83%8F%E3%83%B3%E3%83%9E%E3%83%BC-%E3%82%B9%E3%83%81%E3%83%BC%E3%83%AB%E3%82%A8%E3%83%B3%E3%83%89%E3%82%AD%E3%83%A3%E3%83%83%E3%83%97/dp/B07354ZYZN/ref=zg_bs_g_2039562051_d_sccl_6/357-9393567-9939435?th=1 | C87: 01-2601-0157 | D87: 是 | G87: 0761780380781 | H87: 0.05 | I87: 0 | J87: 1880 | K87: 690 | L87: 34 | M87: 24 | N87: 2 | O87: =max(L87*M87*N87/8000*1000,K87) -> 690 | P87: 39.8 | Q87: {=XLOOKUP(K87/1000, '运费（邮政）'!$A$2:$A$21, '运费（邮政）'!$B$2:$B$21, "超出范围", 1)} -> 1960 | R87: 15.99 | S87: =(V87+U87-Q87)/$B$1 -> 8.1903406 | T87: =P87+R87 -> 55.79 | U87: {=XLOOKUP(O87/1000, '运费（橙联）'!$A$2:$A$57, '运费（橙联）'!$B$2:$B$57, "超出范围", 1)} -> 2321 | V87: =(P87*'参数表'!$C$2*(1+'参数表'!$C$3))*$B$1+'参数表'!$C$4 -> 802.02836 | W87: 0.127 | X87: 0.0135 | Y87: =(P87*(1-I87)-AE87)*$B$1-J87-Q87 -> 446.39794 | Z87: =Y87/P87/$B$1 -> 0.078986118 | AA87: =Y87/J87 -> 0.23744571 | AB87: =(P87*(1-I87)+R87-AF87)*$B$1-J87-U87-V87 -> 1078.1495 | AC87: =AB87/T87/$B$1 -> 0.13609253 | AD87: =AB87/J87 -> 0.5734838 | AE87: =P87*(1-I87)*(1+'参数表'!$C$6)*(W87+X87+H87)*1.1+0.4*1.1 -> 9.614099 | AF87: =(P87*(1-I87)*1.1+R87)*(W87+X87+H87)*1.1+0.4*1.1 -> 12.964804
A88: https://www.amazon.co.jp/%E6%9C%A8%E5%B7%A5%E7%94%A8%E3%83%8E%E3%83%9F-%E6%97%A5%E6%9B%9C%E5%A4%A7%E5%B7%A5-%E5%A4%A7%E5%B7%A5%E9%81%93%E5%85%B7-%E6%9C%A8%E6%9D%90%E5%8A%A0%E5%B7%A5%E5%B7%A5%E5%85%B7-%E6%9C%A8%E6%9D%90%E3%81%AE%E6%BA%9D%E6%8E%98%E3%82%8A%E3%80%81%E4%BB%95%E4%B8%8A%E3%81%92%E3%80%81%E9%9D%A2%E5%8F%96%E3%82%8A%E3%80%81%E6%9C%A8%E5%BD%AB%E3%82%8A%E3%81%AA%E3%81%A9%E3%81%AB/dp/B098P47829/ref=zg_bs_g_2039562051_d_sccl_7/357-9393567-9939435?psc=1 | C88: 01-2601-0158 | D88: 是 | G88: 9440672657040 | H88: 0.05 | I88: 0 | J88: 1155 | K88: 460 | L88: 34 | M88: 24 | N88: 2 | O88: =max(L88*M88*N88/8000*1000,K88) -> 460 | P88: 28.8 | Q88: {=XLOOKUP(K88/1000, '运费（邮政）'!$A$2:$A$21, '运费（邮政）'!$B$2:$B$21, "超出范围", 1)} -> 1600 | R88: 12.99 | S88: =(V88+U88-Q88)/$B$1 -> 7.7644237 | T88: =P88+R88 -> 41.79 | U88: {=XLOOKUP(O88/1000, '运费（橙联）'!$A$2:$A$57, '运费（橙联）'!$B$2:$B$57, "超出范围", 1)} -> 2060 | V88: =(P88*'参数表'!$C$2*(1+'参数表'!$C$3))*$B$1+'参数表'!$C$4 -> 642.54816 | W88: 0.127 | X88: 0.0135 | Y88: =(P88*(1-I88)-AE88)*$B$1-J88-Q88 -> 329.44675 | Z88: =Y88/P88/$B$1 -> 0.080557207 | AA88: =Y88/J88 -> 0.28523528 | AB88: =(P88*(1-I88)+R88-AF88)*$B$1-J88-U88-V88 -> 684.94685 | AC88: =AB88/T88/$B$1 -> 0.11542401 | AD88: =AB88/J88 -> 0.59302758 | AE88: =P88*(1-I88)*(1+'参数表'!$C$6)*(W88+X88+H88)*1.1+0.4*1.1 -> 7.078544 | AF88: =(P88*(1-I88)*1.1+R88)*(W88+X88+H88)*1.1+0.4*1.1 -> 9.8005985
A89: https://www.amazon.co.jp/%E5%A4%A7%E4%BA%94%E9%83%8E-Daigoro-11638-%E6%9C%A8%E5%BD%AB%E3%81%AE%E3%81%BF-9%E3%83%BB15%E3%83%BB24mm/dp/B00GSJJHJW/ref=zg_bs_g_2039562051_d_sccl_12/357-9393567-9939435?psc=1 | C89: 01-2601-0159 | D89: 是 | G89: 4969968116382 | H89: 0.05 | I89: 0 | J89: 1341 | K89: 210 | L89: 34 | M89: 24 | N89: 2 | O89: =max(L89*M89*N89/8000*1000,K89) -> 210 | P89: 27.8 | Q89: {=XLOOKUP(K89/1000, '运费（邮政）'!$A$2:$A$21, '运费（邮政）'!$B$2:$B$21, "超出范围", 1)} -> 1240 | R89: 12.99 | S89: =(V89+U89-Q89)/$B$1 -> 6.8242955 | T89: =P89+R89 -> 40.79 | U89: {=XLOOKUP(O89/1000, '运费（橙联）'!$A$2:$A$57, '运费（橙联）'!$B$2:$B$57, "超出范围", 1)} -> 1581 | V89: =(P89*'参数表'!$C$2*(1+'参数表'!$C$3))*$B$1+'参数表'!$C$4 -> 628.04996 | W89: 0.127 | X89: 0.0135 | Y89: =(P89*(1-I89)-AE89)*$B$1-J89-Q89 -> 394.17846 | Z89: =Y89/P89/$B$1 -> 0.099852686 | AA89: =Y89/J89 -> 0.29394367 | AB89: =(P89*(1-I89)+R89-AF89)*$B$1-J89-U89-V89 -> 883.17676 | AC89: =AB89/T89/$B$1 -> 0.15247744 | AD89: =AB89/J89 -> 0.65859565 | AE89: =P89*(1-I89)*(1+'参数表'!$C$6)*(W89+X89+H89)*1.1+0.4*1.1 -> 6.848039 | AF89: =(P89*(1-I89)*1.1+R89)*(W89+X89+H89)*1.1+0.4*1.1 -> 9.5700935
A90: https://store.shopping.yahoo.co.jp/e-tool-shopping/0088381830553.html | C90: 01-2601-0160 | D90: 是 | G90: 0088381830553 | H90: 0.05 | I90: 0 | J90: 20641 | L90: 34 | M90: 24 | N90: 2 | O90: =max(L90*M90*N90/8000*1000,K90) -> 204 | Q90: {=XLOOKUP(K90/1000, '运费（邮政）'!$A$2:$A$21, '运费（邮政）'!$B$2:$B$21, "超出范围", 1)} -> 880 | S90: =(V90+U90-Q90)/$B$1 -> 6.5211268 | T90: =P90+R90 -> 0 | U90: {=XLOOKUP(O90/1000, '运费（橙联）'!$A$2:$A$57, '运费（橙联）'!$B$2:$B$57, "超出范围", 1)} -> 1581 | V90: =(P90*'参数表'!$C$2*(1+'参数表'!$C$3))*$B$1+'参数表'!$C$4 -> 225 | W90: 0.127 | X90: 0.0135 | Y90: =(P90*(1-I90)-AE90)*$B$1-J90-Q90 -> -21583.48 | Z90: =Y90/P90/$B$1 -> #DIV/0! | AA90: =Y90/J90 -> -1.0456606 | AB90: =(P90*(1-I90)+R90-AF90)*$B$1-J90-U90-V90 -> -22509.48 | AC90: =AB90/T90/$B$1 -> #DIV/0! | AD90: =AB90/J90 -> -1.0905227 | AE90: =P90*(1-I90)*(1+'参数表'!$C$6)*(W90+X90+H90)*1.1+0.4*1.1 -> 0.44 | AF90: =(P90*(1-I90)*1.1+R90)*(W90+X90+H90)*1.1+0.4*1.1 -> 0.44
A91: https://www.amazon.co.jp/Briskyjp-%E3%83%81%E3%82%BC%E3%83%AB%E3%82%BB%E3%83%83%E3%83%88%E3%80%81PVC%E3%82%B4%E3%83%A0%E3%82%B9%E3%83%AA%E3%83%BC%E3%83%96%E4%BB%98%E3%81%8D%E7%9F%B3%E5%B7%A5%E3%83%81%E3%82%BC%E3%83%AB%E3%80%81%E3%83%95%E3%83%A9%E3%83%83%E3%83%88%E3%83%81%E3%82%BC%E3%83%AB%E3%82%BB%E3%83%A1%E3%83%B3%E3%83%88%E3%83%81%E3%82%BC%E3%83%AB%E3%80%81%E7%9F%B3%E3%83%81%E3%82%BC%E3%83%AB-300mm/dp/B0CD2H5C37/ref=zg_bs_g_2039562051_d_sccl_13/357-9393567-9939435?th=1 | C91: 01-2601-0161 | D91: 是 | H91: 0.05 | I91: 0 | J91: 2160 | K91: 310 | L91: 34 | M91: 24 | N91: 2 | O91: =max(L91*M91*N91/8000*1000,K91) -> 310 | P91: 39.8 | Q91: {=XLOOKUP(K91/1000, '运费（邮政）'!$A$2:$A$21, '运费（邮政）'!$B$2:$B$21, "超出范围", 1)} -> 1420 | R91: 12.99 | S91: =(V91+U91-Q91)/$B$1 -> 8.1692138 | T91: =P91+R91 -> 52.79 | U91: {=XLOOKUP(O91/1000, '运费（橙联）'!$A$2:$A$57, '运费（橙联）'!$B$2:$B$57, "超出范围", 1)} -> 1778 | V91: =(P91*'参数表'!$C$2*(1+'参数表'!$C$3))*$B$1+'参数表'!$C$4 -> 802.02836 | W91: 0.127 | X91: 0.0135 | Y91: =(P91*(1-I91)-AE91)*$B$1-J91-Q91 -> 706.39794 | Z91: =Y91/P91/$B$1 -> 0.12499079 | AA91: =Y91/J91 -> 0.32703608 | AB91: =(P91*(1-I91)+R91-AF91)*$B$1-J91-U91-V91 -> 1004.4178 | AC91: =AB91/T91/$B$1 -> 0.13399063 | AD91: =AB91/J91 -> 0.46500826 | AE91: =P91*(1-I91)*(1+'参数表'!$C$6)*(W91+X91+H91)*1.1+0.4*1.1 -> 9.614099 | AF91: =(P91*(1-I91)*1.1+R91)*(W91+X91+H91)*1.1+0.4*1.1 -> 12.336153
A92: https://www.amazon.co.jp/%E9%AB%98%E6%A9%8B-2026%E5%B9%B4-4%E6%9C%88%E5%A7%8B%E3%81%BE%E3%82%8A-5%E5%B9%B4%E5%8D%93%E4%B8%8A%E6%97%A5%E8%AA%8C-No-953/dp/B0G1135XJ5/ref=sr_1_3?crid=3U4STR9NU1HMY&dib=eyJ2IjoiMSJ9.0S5dj6ZzAPxwYPerMRAzX_VHvSCq5MAmNGX7nOFXQFPfYdZwK0Xs8MwYJTT_fjqbY2e8UuiVQDkRWd3SPomPOcacIJhfX6vAzPk0QfMkDqxVB1nVeZR636fnyjKVaom_qg4fmtxqM_RndhcNjgGQXb9hISyeWLInTNnWL0qBOmofgECgGzR4bAFARXaxLLONbit6s7rExvYH4gGxJuIxV3yFvP1NMcMnmJa-J-9bySHGzh4HaUzYYBsNM-2EvgoLG7zL0NdnRb09rBc9bWl7WZENQ2mRPY7Yww19Za5xMJs.EBHdQ1PDgU-SIxauD5l_JeCAlIkIXeB1VSbWhrvztyQ&dib_tag=se&keywords=%E9%AB%98%E6%A9%8B%2B%E6%89%8B%E5%B8%B3%2B2026%E5%B9%B4%2BA5%2B5%E5%B9%B4&qid=1769066271&sprefix=%E9%AB%98%E6%A9%8B%2B%E6%89%8B%E5%B8%B3%2B2026%E5%B9%B4%2Ba5%2B5%E5%B9%B4%2Caps%2C216&sr=8-3&th=1 | C92: 01-2601-0162 | D92: 是 | G92: 4517163859537 | H92: 0.05 | I92: 0 | J92: 2255 | K92: 610 | L92: 34 | M92: 24 | N92: 2 | O92: =max(L92*M92*N92/8000*1000,K92) -> 610 | P92: 47.8 | Q92: {=XLOOKUP(K92/1000, '运费（邮政）'!$A$2:$A$21, '运费（邮政）'!$B$2:$B$21, "超出范围", 1)} -> 1960 | R92: 15.99 | S92: =(V92+U92-Q92)/$B$1 -> 9.0071406 | T92: =P92+R92 -> 63.79 | U92: {=XLOOKUP(O92/1000, '运费（橙联）'!$A$2:$A$57, '运费（橙联）'!$B$2:$B$57, "超出范围", 1)} -> 2321 | V92: =(P92*'参数表'!$C$2*(1+'参数表'!$C$3))*$B$1+'参数表'!$C$4 -> 918.01396 | W92: 0.127 | X92: 0.0135 | Y92: =(P92*(1-I92)-AE92)*$B$1-J92-Q92 -> 945.54426 | Z92: =Y92/P92/$B$1 -> 0.13930465 | AA92: =Y92/J92 -> 0.41931009 | AB92: =(P92*(1-I92)+R92-AF92)*$B$1-J92-U92-V92 -> 1461.3103 | AC92: =AB92/T92/$B$1 -> 0.16132493 | AD92: =AB92/J92 -> 0.64803116 | AE92: =P92*(1-I92)*(1+'参数表'!$C$6)*(W92+X92+H92)*1.1+0.4*1.1 -> 11.458139 | AF92: =(P92*(1-I92)*1.1+R92)*(W92+X92+H92)*1.1+0.4*1.1 -> 14.808844
A93: https://www.amazon.co.jp/dp/B0FY2PKJGM?tag=webspire_new-22&linkCode=osi&th=1&psc=1 | C93: 01-2601-0163 | D93: 是 | G93: 4571614702858 | H93: 0.05 | I93: 0 | J93: 3850 | K93: 180 | L93: 34 | M93: 24 | N93: 2 | O93: =max(L93*M93*N93/8000*1000,K93) -> 204 | P93: 56.8 | Q93: {=XLOOKUP(K93/1000, '运费（邮政）'!$A$2:$A$21, '运费（邮政）'!$B$2:$B$21, "超出范围", 1)} -> 1060 | R93: 18.99 | S93: =(V93+U93-Q93)/$B$1 -> 11.052801 | T93: =P93+R93 -> 75.79 | U93: {=XLOOKUP(O93/1000, '运费（橙联）'!$A$2:$A$57, '运费（橙联）'!$B$2:$B$57, "超出范围", 1)} -> 1581 | V93: =(P93*'参数表'!$C$2*(1+'参数表'!$C$3))*$B$1+'参数表'!$C$4 -> 1048.4978 | W93: 0.153 | X93: 0.0135 | Y93: =(P93*(1-I93)-AE93)*$B$1-J93-Q93 -> 980.2151 | Z93: =Y93/P93/$B$1 -> 0.12153034 | AA93: =Y93/J93 -> 0.25460132 | AB93: =(P93*(1-I93)+R93-AF93)*$B$1-J93-U93-V93 -> 1465.1068 | AC93: =AB93/T93/$B$1 -> 0.13613476 | AD93: =AB93/J93 -> 0.38054722 | AE93: =P93*(1-I93)*(1+'参数表'!$C$6)*(W93+X93+H93)*1.1+0.4*1.1 -> 15.319612 | AF93: =(P93*(1-I93)*1.1+R93)*(W93+X93+H93)*1.1+0.4*1.1 -> 19.842081
A94: https://www.amazon.co.jp/dp/B0G72JZLFF?tag=webspire_new-22&linkCode=osi&th=1&psc=1 | C94: 01-2601-0164 | D94: 是 | G94: 4988031833186 | H94: 0.05 | I94: 0 | J94: 4400 | K94: 150 | L94: 34 | M94: 24 | N94: 2 | O94: =max(L94*M94*N94/8000*1000,K94) -> 204 | P94: 63.8 | Q94: {=XLOOKUP(K94/1000, '运费（邮政）'!$A$2:$A$21, '运费（邮政）'!$B$2:$B$21, "超出范围", 1)} -> 1060 | R94: 21.99 | S94: =(V94+U94-Q94)/$B$1 -> 11.767501 | T94: =P94+R94 -> 85.79 | U94: {=XLOOKUP(O94/1000, '运费（橙联）'!$A$2:$A$57, '运费（橙联）'!$B$2:$B$57, "超出范围", 1)} -> 1581 | V94: =(P94*'参数表'!$C$2*(1+'参数表'!$C$3))*$B$1+'参数表'!$C$4 -> 1149.9852 | W94: 0.153 | X94: 0.0135 | Y94: =(P94*(1-I94)-AE94)*$B$1-J94-Q94 -> 1163.8219 | Z94: =Y94/P94/$B$1 -> 0.12846283 | AA94: =Y94/J94 -> 0.26450497 | AB94: =(P94*(1-I94)+R94-AF94)*$B$1-J94-U94-V94 -> 1871.7743 | AC94: =AB94/T94/$B$1 -> 0.15364855 | AD94: =AB94/J94 -> 0.42540325 | AE94: =P94*(1-I94)*(1+'参数表'!$C$6)*(W94+X94+H94)*1.1+0.4*1.1 -> 17.153367 | AF94: =(P94*(1-I94)*1.1+R94)*(W94+X94+H94)*1.1+0.4*1.1 -> 22.390286
A95: https://www.amazon.co.jp/dp/B0FHPXMKYH?tag=webspire_new-22&linkCode=osi&th=1&psc=1 | C95: 01-2601-0165 | D95: 是 | G95: 4580055368288 | H95: 0.05 | I95: 0 | J95: 3850 | K95: 150 | L95: 34 | M95: 24 | N95: 2 | O95: =max(L95*M95*N95/8000*1000,K95) -> 204 | P95: 56.8 | Q95: {=XLOOKUP(K95/1000, '运费（邮政）'!$A$2:$A$21, '运费（邮政）'!$B$2:$B$21, "超出范围", 1)} -> 1060 | R95: 18.99 | S95: =(V95+U95-Q95)/$B$1 -> 11.052801 | T95: =P95+R95 -> 75.79 | U95: {=XLOOKUP(O95/1000, '运费（橙联）'!$A$2:$A$57, '运费（橙联）'!$B$2:$B$57, "超出范围", 1)} -> 1581 | V95: =(P95*'参数表'!$C$2*(1+'参数表'!$C$3))*$B$1+'参数表'!$C$4 -> 1048.4978 | W95: 0.153 | X95: 0.0135 | Y95: =(P95*(1-I95)-AE95)*$B$1-J95-Q95 -> 980.2151 | Z95: =Y95/P95/$B$1 -> 0.12153034 | AA95: =Y95/J95 -> 0.25460132 | AB95: =(P95*(1-I95)+R95-AF95)*$B$1-J95-U95-V95 -> 1465.1068 | AC95: =AB95/T95/$B$1 -> 0.13613476 | AD95: =AB95/J95 -> 0.38054722 | AE95: =P95*(1-I95)*(1+'参数表'!$C$6)*(W95+X95+H95)*1.1+0.4*1.1 -> 15.319612 | AF95: =(P95*(1-I95)*1.1+R95)*(W95+X95+H95)*1.1+0.4*1.1 -> 19.842081
A96: https://www.amazon.co.jp/dp/B00HI7SCT4?tag=webspire_new-22&linkCode=osi&th=1&psc=1 | C96: 01-2601-0166 | D96: 是 | G96: 4988061864617 | H96: 0.05 | I96: 0 | J96: 2200 | K96: 150 | L96: 34 | M96: 24 | N96: 2 | O96: =max(L96*M96*N96/8000*1000,K96) -> 204 | P96: 37.8 | Q96: {=XLOOKUP(K96/1000, '运费（邮政）'!$A$2:$A$21, '运费（邮政）'!$B$2:$B$21, "超出范围", 1)} -> 1060 | R96: 15.99 | S96: =(V96+U96-Q96)/$B$1 -> 9.1129011 | T96: =P96+R96 -> 53.79 | U96: {=XLOOKUP(O96/1000, '运费（橙联）'!$A$2:$A$57, '运费（橙联）'!$B$2:$B$57, "超出范围", 1)} -> 1581 | V96: =(P96*'参数表'!$C$2*(1+'参数表'!$C$3))*$B$1+'参数表'!$C$4 -> 773.03196 | W96: 0.153 | X96: 0.0135 | Y96: =(P96*(1-I96)-AE96)*$B$1-J96-Q96 -> 638.99667 | Z96: =Y96/P96/$B$1 -> 0.119047 | AA96: =Y96/J96 -> 0.29045303 | AB96: =(P96*(1-I96)+R96-AF96)*$B$1-J96-U96-V96 -> 1074.8061 | AC96: =AB96/T96/$B$1 -> 0.14071495 | AD96: =AB96/J96 -> 0.48854822 | AE96: =P96*(1-I96)*(1+'参数表'!$C$6)*(W96+X96+H96)*1.1+0.4*1.1 -> 10.342277 | AF96: =(P96*(1-I96)*1.1+R96)*(W96+X96+H96)*1.1+0.4*1.1 -> 14.150296
A97: https://www.amazon.co.jp/dp/B0G5HL7595?tag=webspire_new-22&linkCode=osi&th=1&psc=1 | B97: https://tower.jp/ec/StoreProcure/StoreProcureItem.aspx?iid=7536230 | C97: 01-2601-0167 | D97: 是 | G97: 4988002950713 | H97: 0.05 | I97: 0 | J97: 2890 | K97: 380 | L97: 34 | M97: 24 | N97: 2 | O97: =max(L97*M97*N97/8000*1000,K97) -> 380 | P97: 49.8 | Q97: {=XLOOKUP(K97/1000, '运费（邮政）'!$A$2:$A$21, '运费（邮政）'!$B$2:$B$21, "超出范围", 1)} -> 1420 | R97: 15.99 | S97: =(V97+U97-Q97)/$B$1 -> 9.1902138 | T97: =P97+R97 -> 65.79 | U97: {=XLOOKUP(O97/1000, '运费（橙联）'!$A$2:$A$57, '运费（橙联）'!$B$2:$B$57, "超出范围", 1)} -> 1778 | V97: =(P97*'参数表'!$C$2*(1+'参数表'!$C$3))*$B$1+'参数表'!$C$4 -> 947.01036 | W97: 0.153 | X97: 0.0135 | Y97: =(P97*(1-I97)-AE97)*$B$1-J97-Q97 -> 846.60831 | Z97: =Y97/P97/$B$1 -> 0.11971948 | AA97: =Y97/J97 -> 0.29294405 | AB97: =(P97*(1-I97)+R97-AF97)*$B$1-J97-U97-V97 -> 1271.4393 | AC97: =AB97/T97/$B$1 -> 0.13609664 | AD97: =AB97/J97 -> 0.4399444 | AE97: =P97*(1-I97)*(1+'参数表'!$C$6)*(W97+X97+H97)*1.1+0.4*1.1 -> 13.485857 | AF97: =(P97*(1-I97)*1.1+R97)*(W97+X97+H97)*1.1+0.4*1.1 -> 17.293875
A98: https://www.amazon.co.jp/dp/B0FZSZF7Y2?tag=webspire_new-22&linkCode=osi&th=1&psc=1 | C98: 01-2601-0168 | D98: 是 | G98: 4543034054091 | H98: 0.05 | I98: 0 | J98: 6050 | K98: 180 | L98: 34 | M98: 24 | N98: 2 | O98: =max(L98*M98*N98/8000*1000,K98) -> 204 | P98: 82.8 | Q98: {=XLOOKUP(K98/1000, '运费（邮政）'!$A$2:$A$21, '运费（邮政）'!$B$2:$B$21, "超出范围", 1)} -> 1060 | R98: 24.99 | S98: =(V98+U98-Q98)/$B$1 -> 13.707401 | T98: =P98+R98 -> 107.79 | U98: {=XLOOKUP(O98/1000, '运费（橙联）'!$A$2:$A$57, '运费（橙联）'!$B$2:$B$57, "超出范围", 1)} -> 1581 | V98: =(P98*'参数表'!$C$2*(1+'参数表'!$C$3))*$B$1+'参数表'!$C$4 -> 1425.451 | W98: 0.153 | X98: 0.0135 | Y98: =(P98*(1-I98)-AE98)*$B$1-J98-Q98 -> 1505.0403 | Z98: =Y98/P98/$B$1 -> 0.12800574 | AA98: =Y98/J98 -> 0.24876699 | AB98: =(P98*(1-I98)+R98-AF98)*$B$1-J98-U98-V98 -> 2262.075 | AC98: =AB98/T98/$B$1 -> 0.14778835 | AD98: =AB98/J98 -> 0.3738967 | AE98: =P98*(1-I98)*(1+'参数表'!$C$6)*(W98+X98+H98)*1.1+0.4*1.1 -> 22.130702 | AF98: =(P98*(1-I98)*1.1+R98)*(W98+X98+H98)*1.1+0.4*1.1 -> 28.082071
A99: https://www.amazon.co.jp/dp/B0G5X46GHJ?tag=webspire_new-22&linkCode=osi&th=1&psc=1 | C99: 01-2601-0169 | D99: 是 | G99: 4988031841792 | H99: 0.05 | I99: 0 | J99: 3300 | K99: 120 | L99: 34 | M99: 24 | N99: 2 | O99: =max(L99*M99*N99/8000*1000,K99) -> 204 | P99: 49.8 | Q99: {=XLOOKUP(K99/1000, '运费（邮政）'!$A$2:$A$21, '运费（邮政）'!$B$2:$B$21, "超出范围", 1)} -> 1060 | R99: 18.99 | S99: =(V99+U99-Q99)/$B$1 -> 10.338101 | T99: =P99+R99 -> 68.79 | U99: {=XLOOKUP(O99/1000, '运费（橙联）'!$A$2:$A$57, '运费（橙联）'!$B$2:$B$57, "超出范围", 1)} -> 1581 | V99: =(P99*'参数表'!$C$2*(1+'参数表'!$C$3))*$B$1+'参数表'!$C$4 -> 947.01036 | W99: 0.153 | X99: 0.0135 | Y99: =(P99*(1-I99)-AE99)*$B$1-J99-Q99 -> 796.60831 | Z99: =Y99/P99/$B$1 -> 0.11264895 | AA99: =Y99/J99 -> 0.24139646 | AB99: =(P99*(1-I99)+R99-AF99)*$B$1-J99-U99-V99 -> 1382.9874 | AC99: =AB99/T99/$B$1 -> 0.14158087 | AD99: =AB99/J99 -> 0.4190871 | AE99: =P99*(1-I99)*(1+'参数表'!$C$6)*(W99+X99+H99)*1.1+0.4*1.1 -> 13.485857 | AF99: =(P99*(1-I99)*1.1+R99)*(W99+X99+H99)*1.1+0.4*1.1 -> 18.008326
A100: https://www.amazon.co.jp/dp/B0CS913VBL?tag=webspire_new-22&linkCode=osi&th=1&psc=1 | C100: 01-2601-0170 | D100: 是 | G100: 4988104115904 | H100: 0.05 | I100: 0 | J100: 4000 | K100: 180 | L100: 34 | M100: 24 | N100: 2 | O100: =max(L100*M100*N100/8000*1000,K100) -> 204 | P100: 58.9 | Q100: {=XLOOKUP(K100/1000, '运费（邮政）'!$A$2:$A$21, '运费（邮政）'!$B$2:$B$21, "超出范围", 1)} -> 1060 | R100: 18.99 | S100: =(V100+U100-Q100)/$B$1 -> 11.267211 | T100: =P100+R100 -> 77.89 | U100: {=XLOOKUP(O100/1000, '运费（橙联）'!$A$2:$A$57, '运费（橙联）'!$B$2:$B$57, "超出范围", 1)} -> 1581 | V100: =(P100*'参数表'!$C$2*(1+'参数表'!$C$3))*$B$1+'参数表'!$C$4 -> 1078.944 | W100: 0.153 | X100: 0.0135 | Y100: =(P100*(1-I100)-AE100)*$B$1-J100-Q100 -> 1050.2971 | Z100: =Y100/P100/$B$1 -> 0.12557655 | AA100: =Y100/J100 -> 0.26257428 | AB100: =(P100*(1-I100)+R100-AF100)*$B$1-J100-U100-V100 -> 1504.7426 | AC100: =AB100/T100/$B$1 -> 0.136048 | AD100: =AB100/J100 -> 0.37618566 | AE100: =P100*(1-I100)*(1+'参数表'!$C$6)*(W100+X100+H100)*1.1+0.4*1.1 -> 15.869739 | AF100: =(P100*(1-I100)*1.1+R100)*(W100+X100+H100)*1.1+0.4*1.1 -> 20.392207
...

Sheet 工作表13

Sheet UPC查重表
A1: 4571614702230
A2: 4988005486547
A3: 4547366408959
A4: 4988031675755
A5: 4580357661605
A6: 4972525052801
A7: 4901601288728
A8: 4972525053136
A9: 4901601937343
A10: 4901601236385
A11: 4901601937367
A12: 4901601240337
A13: 4910299340854
A14: 4521329368009
A15: 9784041156834
A16: 4521329266527
A17: 4549660863748
A18: 9784092274266
A19: 4582769865206
A20: 75678599316
A21: 4972525053297
A22: 795864762897
A23: 4972525053310
A24: 4972525053181
A25: 4972525053402
A26: 4972525053419
A27: 4972525021005
A28: 4972525021012
A29: 4972525050586
A30: 4943674415809
A31: 4988002437269
A32: 4547366754759
A33: 4988001131991
A34: 4943674402915
A35: 4547366710892
A36: 4947864600518
A37: 4988031754412
A38: 4524334001473
A39: 4582798814466
A40: 4943674108947
A41: 4943674269242
A42: 4547403007725
A43: 4582239509470
A44: 4988031583722
A45: 4910299371056
A46: 4910299310956
A48: 9784041143346
A49: 9784041150948
A50: 9784041163245
A51: 4972525052443
A52: 9784041135419
A54: 9784065371398
A55: 9784065402979
A56: 9784253322430
A57: 9784253322416
A59: 4943674416202
A61: 4943674416196
A62: 4988017607336
A63: 4972525020817
A64: 4972525052788
A65: 4972525501385
A66: 4972525535182
... A101: 4901480326832
A102: 0610446005486
A103: 4984909210967
A104: 4901601206760
A105: 4573341224337
A106: 4542202664353
A109: 4988002947966
A110: 4904790088766
A111: 4547366756289
A112: なし
A113: 4582769731358
A114: なし
A115: 4988031793275
A116: 4571614702315
A117: 4571614702520
A118: 4868010905
A119: 4527516024406
A120: 978-4763025067
A121: 4988031767955
A122: 4763023306
A123: 4900963747
... A190: 4580010322485
A191: 4547366694253
A192: 4988002367139
A193: 4970181259435
A194: 4905040156365
A195: 4905040148711
A196: 4905040159564
A197: 4905040159687
A198: 4905040140593
A199: 4905040149213
A200: 4905040149640
A201: 4905040144102
A202: 4905040159359
A203: 4905040159618
A204: 4905040158819
A205: 4905040152138
A206: 4905040159472
...

Sheet 运费（邮政）
B1: 日元
A2: 0.1 | B2: 880
A3: 0.2 | B3: 1060
A4: 0.3 | B4: 1240
A5: 0.4 | B5: 1420
A6: 0.5 | B6: 1600
A7: 0.6 | B7: 1780
A8: 0.7 | B8: 1960
A9: 0.8 | B9: 2140
A10: 0.9 | B10: 2320
A11: 1 | B11: 2500
A12: 1.1 | B12: 2680
A13: 1.2 | B13: 2860
... A21: 2 | B21: 4300

Sheet 运费（橙联）
A1: 重量上限 (kg) | B1: 运费 (JPY)
A2: 0.1 | B2: 1227
A3: 0.2 | B3: 1367
A4: 0.3 | B4: 1581
A5: 0.4 | B5: 1778
A6: 0.5 | B6: 2060
A7: 0.6 | B7: 2222
A8: 0.7 | B8: 2321
A9: 0.8 | B9: 2703
A10: 0.9 | B10: 2820
A11: 1 | B11: 3020
A12: 1.1 | B12: 3136
A13: 1.2 | B13: 3250
... A57: 20 | B57: 23946

Sheet 参数表
D1: 备注
B2: 关税 | C2: 0.1
B3: 关税手续费 | C3: 0.021 | D3: 关税基础上
B4: 通关手续费 | C4: 225 | D4: 日元
B5: eBay交易手续费 | C5: 0.4 | D5: 美元/笔
B6: 消费税、VAT、GST | C6: 0.1 | D6: 预设
